Workbook

Sheet moderate_hydrogen_high_ccs
A1: Vintage | B1: Battery_Storage | C1: Battery_Storage_energy | D1: Central_PV | E1: Residential_PV | F1: Gas_Combustion_Turbine | G1: Gas_Combustion_Turbine_CCS | H1: Gas_CCGT | I1: Gas_CCGT_CCS | J1: Wind | K1: Offshore_Wind | L1: Coal | M1: Coal_CCS | N1: Coal_IGCC | O1: Coal_IGCC_CCS | P1: Nuclear | Q1: Hydro_Pumped | R1: Hydro_NonPumped | S1: SMR | T1: SMR_CCS | U1: Gasification | V1: Gasification_CCS | W1: Electrolyzer | X1: Fuel_cell | Y1: Hydrogen_turbine | Z1: Tank | AA1: Salt_cavern | AB1: CCS_storage_oil | AC1: CCS_storage_saline | AD1: CCS_storage_offshore | AE1: DAC
A2: 2020 | B2: =OFFSET(battery!$F$15,(ROW(B1)-1)*5,0)*1000 -> 492307.69 | C2: =OFFSET(battery!$C$15,(ROW(C1)-1)*5,0)*1000 -> 246153.85 | D2: =OFFSET(Solar!$C$11,(ROW(D1)-1)*5,0)*1000 -> 628000 | E2: =OFFSET(Solar!$F$11,(ROW(Solar!E1)-1)*5,0)*1000 -> 746000 | F2: =OFFSET(gas!$C$18,(ROW(gas!C1)-1)*5,0)*1000 -> 367230.77 | G2: =ccs!$H$6*ccs!$B$20*8760 -> 2957746.1 | H2: =OFFSET(gas!$F$18,(ROW(gas!E1)-1)*5,0)*1000 -> 408913.26 | I2: =ccs!$H$6*ccs!$B$20*8760 -> 2957746.1 | J2: =OFFSET(land!$C$12,(ROW(J1)-1)*5,0)*1000 -> 1157000 | K2: =OFFSET(offshore!$K$13,(ROW(K1)-1)*5,0)*1000 -> 2857000 | L2: =OFFSET(coal!$C$20,(ROW(L1)-1)*5,0)*1000 -> 622461.54 | M2: =ccs!$C$6*ccs!$B$20*8760 -> 3086497.8 | N2: =OFFSET(coal!$F$20,(ROW(N1)-1)*5,0)*1000 -> 1089999.5 | O2: =ccs!$F$6*ccs!$B$20*8760 -> 2342606.6 | P2: =OFFSET(nuclear!$B$8,(ROW(P1)-1)*5,0)*1000 -> 2461538.5 | Q2: =5969/6.5*1000 -> 918307.69 | R2: =2240.15384615385*1000 -> 2240153.8 | S2: =SMR!T2 -> 546556.72 | T2: =ccs!$J$6*ccs!B$20*8760 -> 769681.35 | U2: =SMR!V2 -> 3272268.8 | V2: =ccs!$J$6*ccs!B$20*8760 -> 769681.35 | W2: =OFFSET(Electrolyzer!$C$2,(ROW(W1)-1)*5,0)*1000 -> 1245090 | X2: ='Fuel cell'!C2*1000 -> 1562022 | Y2: =OFFSET('H2 turbine'!$B$12,(ROW(Z1)-1)*5,0)*1000 -> 314777.78 | Z2: ='hydrogen storage'!B9 -> 69045.9 | AA2: ='hydrogen storage'!D9 -> 3610.761 | AB2: =2.36*1.1*1.0928 -> 2.8369088 | AC2: =AB2*2 -> 5.6738176 | AD2: =3.89*1.1*1.0928 -> 4.6760912 | AE2: =DAC!$B$19*8760 -> 7357350
A3: 2025 | B3: =OFFSET(battery!$F$15,(ROW(B2)-1)*5,0)*1000 -> 474606.98 | C3: =OFFSET(battery!$C$15,(ROW(C2)-1)*5,0)*1000 -> 219340.56 | D3: =OFFSET(Solar!$C$11,(ROW(D2)-1)*5,0)*1000 -> 607009.58 | E3: =OFFSET(Solar!$F$11,(ROW(Solar!E2)-1)*5,0)*1000 -> 686543.83 | F3: =OFFSET(gas!$C$18,(ROW(gas!C2)-1)*5,0)*1000 -> 358513.34 | G3: =ccs!$H$6*ccs!$B$20*8760 -> 2957746.1 | H3: =OFFSET(gas!$F$18,(ROW(gas!E2)-1)*5,0)*1000 -> 398327.81 | I3: =ccs!$H$6*ccs!$B$20*8760 -> 2957746.1 | J3: =OFFSET(land!$C$12,(ROW(J2)-1)*5,0)*1000 -> 1076641 | K3: =OFFSET(offshore!$K$13,(ROW(K2)-1)*5,0)*1000 -> 2492044 | L3: =OFFSET(coal!$C$20,(ROW(L2)-1)*5,0)*1000 -> 612285.83 | M3: =ccs!$C$6*ccs!$B$20*8760 -> 3086497.8 | N3: =OFFSET(coal!$F$20,(ROW(N2)-1)*5,0)*1000 -> 1083549.8 | O3: =ccs!$F$6*ccs!$B$20*8760 -> 2342606.6 | P3: =OFFSET(nuclear!$B$8,(ROW(P2)-1)*5,0)*1000 -> 2113664.3 | Q3: =5969/6.5*1000 -> 918307.69 | R3: =2240.15384615385*1000 -> 2240153.8 | S3: =SMR!T3 -> 533582.41 | T3: =ccs!$J$6*ccs!B$20*8760 -> 769681.35 | U3: =SMR!V3 -> 3218775.3 | V3: =ccs!$J$6*ccs!B$20*8760 -> 769681.35 | W3: =OFFSET(Electrolyzer!$C$2,(ROW(W2)-1)*5,0)*1000 -> 905520 | X3: ='Fuel cell'!C3*1000 -> 1443172.5 | Y3: =OFFSET('H2 turbine'!$B$12,(ROW(Z2)-1)*5,0)*1000 -> 313166.67 | Z3: ='hydrogen storage'!B10 -> 61688.55 | AA3: ='hydrogen storage'!D10 -> 3010.854 | AB3: =2.36*1.1*1.0928 -> 2.8369088 | AC3: =AB3*2 -> 5.6738176 | AD3: =3.89*1.1*1.0928 -> 4.6760912 | AE3: =DAC!$B$19*8760 -> 7357350
A4: 2030 | B4: =OFFSET(battery!$F$15,(ROW(B3)-1)*5,0)*1000 -> 483790.42 | C4: =OFFSET(battery!$C$15,(ROW(C3)-1)*5,0)*1000 -> 173879.95 | D4: =OFFSET(Solar!$C$11,(ROW(D3)-1)*5,0)*1000 -> 505217.02 | E4: =OFFSET(Solar!$F$11,(ROW(Solar!E3)-1)*5,0)*1000 -> 548996.6 | F4: =OFFSET(gas!$C$18,(ROW(gas!C3)-1)*5,0)*1000 -> 344008.72 | G4: =ccs!$H$6*ccs!$B$20*8760 -> 2957746.1 | H4: =OFFSET(gas!$F$18,(ROW(gas!E3)-1)*5,0)*1000 -> 380673.19 | I4: =ccs!$H$6*ccs!$B$20*8760 -> 2957746.1 | J4: =OFFSET(land!$C$12,(ROW(J3)-1)*5,0)*1000 -> 976192.22 | K4: =OFFSET(offshore!$K$13,(ROW(K3)-1)*5,0)*1000 -> 2290687.3 | L4: =OFFSET(coal!$C$20,(ROW(L3)-1)*5,0)*1000 -> 595355.36 | M4: =ccs!$C$6*ccs!$B$20*8760 -> 3086497.8 | N4: =OFFSET(coal!$F$20,(ROW(N3)-1)*5,0)*1000 -> 1072807.6 | O4: =ccs!$F$6*ccs!$B$20*8760 -> 2342606.6 | P4: =OFFSET(nuclear!$B$8,(ROW(P3)-1)*5,0)*1000 -> 2015508 | Q4: =5969/6.5*1000 -> 918307.69 | R4: =2240.15384615385*1000 -> 2240153.8 | S4: =SMR!T4 -> 511994.89 | T4: =ccs!$J$6*ccs!B$20*8760 -> 769681.35 | U4: =SMR!V4 -> 3129772.1 | V4: =ccs!$J$6*ccs!B$20*8760 -> 769681.35 | W4: =OFFSET(Electrolyzer!$C$2,(ROW(W3)-1)*5,0)*1000 -> 565950 | X4: ='Fuel cell'!C4*1000 -> 1324323 | Y4: =OFFSET('H2 turbine'!$B$12,(ROW(Z3)-1)*5,0)*1000 -> 311555.56 | Z4: ='hydrogen storage'!B11 -> 54331.2 | AA4: ='hydrogen storage'!D11 -> 2410.947 | AB4: =2.36*1.1*1.0928 -> 2.8369088 | AC4: =AB4*2 -> 5.6738176 | AD4: =3.89*1.1*1.0928 -> 4.6760912 | AE4: =DAC!$B$19*8760 -> 7357350
A5: 2035 | B5: =OFFSET(battery!$F$15,(ROW(B4)-1)*5,0)*1000 -> 467109.57 | C5: =OFFSET(battery!$C$15,(ROW(C4)-1)*5,0)*1000 -> 158078 | D5: =OFFSET(Solar!$C$11,(ROW(D4)-1)*5,0)*1000 -> 403424.47 | E5: =OFFSET(Solar!$F$11,(ROW(Solar!E4)-1)*5,0)*1000 -> 411449.37 | F5: =OFFSET(gas!$C$18,(ROW(gas!C4)-1)*5,0)*1000 -> 329504.09 | G5: =ccs!$H$6*ccs!$B$20*8760 -> 2957746.1 | H5: =OFFSET(gas!$F$18,(ROW(gas!E4)-1)*5,0)*1000 -> 363018.57 | I5: =ccs!$H$6*ccs!$B$20*8760 -> 2957746.1 | J5: =OFFSET(land!$C$12,(ROW(J4)-1)*5,0)*1000 -> 928132.19 | K5: =OFFSET(offshore!$K$13,(ROW(K4)-1)*5,0)*1000 -> 2166215.1 | L5: =OFFSET(coal!$C$20,(ROW(L4)-1)*5,0)*1000 -> 578403.11 | M5: =ccs!$C$6*ccs!$B$20*8760 -> 3086497.8 | N5: =OFFSET(coal!$F$20,(ROW(N4)-1)*5,0)*1000 -> 1062087.1 | O5: =ccs!$F$6*ccs!$B$20*8760 -> 2342606.6 | P5: =OFFSET(nuclear!$B$8,(ROW(P4)-1)*5,0)*1000 -> 1948571.2 | Q5: =5969/6.5*1000 -> 918307.69 | R5: =2240.15384615385*1000 -> 2240153.8 | S5: =SMR!T5 -> 490407.37 | T5: =ccs!$J$6*ccs!B$20*8760 -> 769681.35 | U5: =SMR!V5 -> 3040654.4 | V5: =ccs!$J$6*ccs!B$20*8760 -> 769681.35 | W5: =OFFSET(Electrolyzer!$C$2,(ROW(W4)-1)*5,0)*1000 -> 694166.67 | X5: ='Fuel cell'!C5*1000 -> 1233771 | Y5: =OFFSET('H2 turbine'!$B$12,(ROW(Z4)-1)*5,0)*1000 -> 309944.44 | Z5: ='hydrogen storage'!B12 -> 43578.15 | AA5: ='hydrogen storage'!D12 -> 2110.9935 | AB5: =2.36*1.1*1.0928 -> 2.8369088 | AC5: =AB5*2 -> 5.6738176 | AD5: =3.89*1.1*1.0928 -> 4.6760912 | AE5: =DAC!$B$19*8760 -> 7357350
A6: 2040 | B6: =OFFSET(battery!$F$15,(ROW(B5)-1)*5,0)*1000 -> 449709.83 | C6: =OFFSET(battery!$C$15,(ROW(C5)-1)*5,0)*1000 -> 142362.74 | D6: =OFFSET(Solar!$C$11,(ROW(D5)-1)*5,0)*1000 -> 371518.84 | E6: =OFFSET(Solar!$F$11,(ROW(Solar!E5)-1)*5,0)*1000 -> 371597.4 | F6: =OFFSET(gas!$C$18,(ROW(gas!C5)-1)*5,0)*1000 -> 314962.84 | G6: =ccs!$H$6*ccs!$B$20*8760 -> 2957746.1 | H6: =OFFSET(gas!$F$18,(ROW(gas!E5)-1)*5,0)*1000 -> 348074.41 | I6: =ccs!$H$6*ccs!$B$20*8760 -> 2957746.1 | J6: =OFFSET(land!$C$12,(ROW(J5)-1)*5,0)*1000 -> 880072.15 | K6: =OFFSET(offshore!$K$13,(ROW(K5)-1)*5,0)*1000 -> 2075879.5 | L6: =OFFSET(coal!$C$20,(ROW(L5)-1)*5,0)*1000 -> 550665.03 | M6: =ccs!$C$6*ccs!$B$20*8760 -> 3086497.8 | N6: =OFFSET(coal!$F$20,(ROW(N5)-1)*5,0)*1000 -> 1051344.9 | O6: =ccs!$F$6*ccs!$B$20*8760 -> 2342606.6 | P6: =OFFSET(nuclear!$B$8,(ROW(P5)-1)*5,0)*1000 -> 1879782.7 | Q6: =5969/6.5*1000 -> 918307.69 | R6: =2240.15384615385*1000 -> 2240153.8 | S6: =SMR!T6 -> 468765.34 | T6: =ccs!$J$6*ccs!B$20*8760 -> 769681.35 | U6: =SMR!V6 -> 2894835.9 | V6: =ccs!$J$6*ccs!B$20*8760 -> 769681.35 | W6: =OFFSET(Electrolyzer!$C$2,(ROW(W5)-1)*5,0)*1000 -> 452760 | X6: ='Fuel cell'!C6*1000 -> 1143219 | Y6: =OFFSET('H2 turbine'!$B$12,(ROW(Z5)-1)*5,0)*1000 -> 308333.33 | Z6: ='hydrogen storage'!B13 -> 32825.1 | AA6: ='hydrogen storage'!D13 -> 1811.04 | AB6: =2.36*1.1*1.0928 -> 2.8369088 | AC6: =AB6*2 -> 5.6738176 | AD6: =3.89*1.1*1.0928 -> 4.6760912 | AE6: =DAC!$B$19*8760 -> 7357350
A7: 2045 | B7: =OFFSET(battery!$F$15,(ROW(B6)-1)*5,0)*1000 -> 431425.3 | C7: =OFFSET(battery!$C$15,(ROW(C6)-1)*5,0)*1000 -> 126754.17 | D7: =OFFSET(Solar!$C$11,(ROW(D6)-1)*5,0)*1000 -> 339613.21 | E7: =OFFSET(Solar!$F$11,(ROW(Solar!E6)-1)*5,0)*1000 -> 331745.43 | F7: =OFFSET(gas!$C$18,(ROW(gas!C6)-1)*5,0)*1000 -> 300458.21 | G7: =ccs!$H$6*ccs!$B$20*8760 -> 2957746.1 | H7: =OFFSET(gas!$F$18,(ROW(gas!E6)-1)*5,0)*1000 -> 333130.25 | I7: =ccs!$H$6*ccs!$B$20*8760 -> 2957746.1 | J7: =OFFSET(land!$C$12,(ROW(J6)-1)*5,0)*1000 -> 832012.11 | K7: =OFFSET(offshore!$K$13,(ROW(K6)-1)*5,0)*1000 -> 2004930.7 | L7: =OFFSET(coal!$C$20,(ROW(L6)-1)*5,0)*1000 -> 522948.75 | M7: =ccs!$C$6*ccs!$B$20*8760 -> 3086497.8 | N7: =OFFSET(coal!$F$20,(ROW(N6)-1)*5,0)*1000 -> 1040624.4 | O7: =ccs!$F$6*ccs!$B$20*8760 -> 2342606.6 | P7: =OFFSET(nuclear!$B$8,(ROW(P6)-1)*5,0)*1000 -> 1815208.1 | Q7: =5969/6.5*1000 -> 918307.69 | R7: =2240.15384615385*1000 -> 2240153.8 | S7: =SMR!T7 -> 447177.82 | T7: =ccs!$J$6*ccs!B$20*8760 -> 769681.35 | U7: =SMR!V7 -> 2749131.9 | V7: =ccs!$J$6*ccs!B$20*8760 -> 769681.35 | W7: =OFFSET(Electrolyzer!$C$2,(ROW(W6)-1)*5,0)*1000 -> 639833.33 | X7: ='Fuel cell'!C7*1000 -> 1052667 | Y7: =OFFSET('H2 turbine'!$B$12,(ROW(Z6)-1)*5,0)*1000 -> 306722.22 | Z7: ='hydrogen storage'!B14 -> 28863.45 | AA7: ='hydrogen storage'!D14 -> 1629.936 | AB7: =2.36*1.1*1.0928 -> 2.8369088 | AC7: =AB7*2 -> 5.6738176 | AD7: =3.89*1.1*1.0928 -> 4.6760912 | AE7: =DAC!$B$19*8760 -> 7357350
A8: 2050 | B8: =OFFSET(battery!$F$15,(ROW(B7)-1)*5,0)*1000 -> 412034.81 | C8: =OFFSET(battery!$C$15,(ROW(C7)-1)*5,0)*1000 -> 111278.96 | D8: =OFFSET(Solar!$C$11,(ROW(D7)-1)*5,0)*1000 -> 307707.58 | E8: =OFFSET(Solar!$F$11,(ROW(Solar!E7)-1)*5,0)*1000 -> 291893.46 | F8: =OFFSET(gas!$C$18,(ROW(gas!C7)-1)*5,0)*1000 -> 285953.58 | G8: =ccs!$H$6*ccs!$B$20*8760 -> 2957746.1 | H8: =OFFSET(gas!$F$18,(ROW(gas!E7)-1)*5,0)*1000 -> 318222.71 | I8: =ccs!$H$6*ccs!$B$20*8760 -> 2957746.1 | J8: =OFFSET(land!$C$12,(ROW(J7)-1)*5,0)*1000 -> 783952.07 | K8: =OFFSET(offshore!$K$13,(ROW(K7)-1)*5,0)*1000 -> 1946500.3 | L8: =OFFSET(coal!$C$20,(ROW(L7)-1)*5,0)*1000 -> 495210.68 | M8: =ccs!$C$6*ccs!$B$20*8760 -> 3086497.8 | N8: =OFFSET(coal!$F$20,(ROW(N7)-1)*5,0)*1000 -> 1029882.2 | O8: =ccs!$F$6*ccs!$B$20*8760 -> 2342606.6 | P8: =OFFSET(nuclear!$B$8,(ROW(P7)-1)*5,0)*1000 -> 1738729.6 | Q8: =5969/6.5*1000 -> 918307.69 | R8: =2240.15384615385*1000 -> 2240153.8 | S8: =SMR!T8 -> 425590.3 | T8: =ccs!$J$6*ccs!B$20*8760 -> 769681.35 | U8: =SMR!V8 -> 2603313.4 | V8: =ccs!$J$6*ccs!B$20*8760 -> 769681.35 | W8: =OFFSET(Electrolyzer!$C$2,(ROW(W7)-1)*5,0)*1000 -> 311272.5 | X8: ='Fuel cell'!C8*1000 -> 962115 | Y8: =OFFSET('H2 turbine'!$B$12,(ROW(Z7)-1)*5,0)*1000 -> 305111.11 | Z8: ='hydrogen storage'!B15 -> 24901.8 | AA8: ='hydrogen storage'!D15 -> 1448.832 | AB8: =2.36*1.1*1.0928 -> 2.8369088 | AC8: =AB8*2 -> 5.6738176 | AD8: =3.89*1.1*1.0928 -> 4.6760912 | AE8: =DAC!$B$19*8760 -> 7357350

Sheet moderate_hydrogen
A1: Vintage | B1: Battery_Storage | C1: Battery_Storage_energy | D1: Central_PV | E1: Residential_PV | F1: Gas_Combustion_Turbine | G1: Gas_Combustion_Turbine_CCS | H1: Gas_CCGT | I1: Gas_CCGT_CCS | J1: Wind | K1: Offshore_Wind | L1: Coal | M1: Coal_CCS | N1: Coal_IGCC | O1: Coal_IGCC_CCS | P1: Nuclear | Q1: Hydro_Pumped | R1: Hydro_NonPumped | S1: SMR | T1: SMR_CCS | U1: Gasification | V1: Gasification_CCS | W1: Electrolyzer | X1: Fuel_cell | Y1: Hydrogen_turbine | Z1: Tank | AA1: Salt_cavern | AB1: CCS_storage_oil | AC1: CCS_storage_saline | AD1: CCS_storage_offshore | AE1: DAC
A2: 2020 | B2: =OFFSET(battery!$F$15,(ROW(B1)-1)*5,0)*1000 -> 492307.69 | C2: =OFFSET(battery!$C$15,(ROW(C1)-1)*5,0)*1000 -> 246153.85 | D2: =OFFSET(Solar!$C$11,(ROW(D1)-1)*5,0)*1000 -> 628000 | E2: =OFFSET(Solar!$F$11,(ROW(Solar!E1)-1)*5,0)*1000 -> 746000 | F2: =OFFSET(gas!$C$18,(ROW(gas!C1)-1)*5,0)*1000 -> 367230.77 | G2: =ccs!$H$6*ccs!B20*8760 -> 2957746.1 | H2: =OFFSET(gas!$F$18,(ROW(gas!E1)-1)*5,0)*1000 -> 408913.26 | I2: =ccs!$H$6*ccs!B20*8760 -> 2957746.1 | J2: =OFFSET(land!$C$12,(ROW(J1)-1)*5,0)*1000 -> 1157000 | K2: =OFFSET(offshore!$K$13,(ROW(K1)-1)*5,0)*1000 -> 2857000 | L2: =OFFSET(coal!$C$20,(ROW(L1)-1)*5,0)*1000 -> 622461.54 | M2: =ccs!$C$6*ccs!B20*8760 -> 3086497.8 | N2: =OFFSET(coal!$F$20,(ROW(N1)-1)*5,0)*1000 -> 1089999.5 | O2: =ccs!$F$6*ccs!B20*8760 -> 2342606.6 | P2: =OFFSET(nuclear!$B$8,(ROW(P1)-1)*5,0)*1000 -> 2461538.5 | Q2: =5969/6.5*1000 -> 918307.69 | R2: =2240.15384615385*1000 -> 2240153.8 | S2: =SMR!T2 -> 546556.72 | T2: =ccs!$J$6*ccs!B20*8760 -> 769681.35 | U2: =SMR!V2 -> 3272268.8 | V2: =ccs!$J$6*ccs!B20*8760 -> 769681.35 | W2: =OFFSET(Electrolyzer!$C$2,(ROW(W1)-1)*5,0)*1000 -> 1245090 | X2: ='Fuel cell'!C2*1000 -> 1562022 | Y2: =OFFSET('H2 turbine'!$B$12,(ROW(Z1)-1)*5,0)*1000 -> 314777.78 | Z2: ='hydrogen storage'!B9 -> 69045.9 | AA2: ='hydrogen storage'!D9 -> 3610.761 | AB2: =2.36*1.1*1.0928 -> 2.8369088 | AC2: =AB2*2 -> 5.6738176 | AD2: =3.89*1.1*1.0928 -> 4.6760912 | AE2: =DAC!B19*8760 -> 7357350
A3: 2025 | B3: =OFFSET(battery!$F$15,(ROW(B2)-1)*5,0)*1000 -> 474606.98 | C3: =OFFSET(battery!$C$15,(ROW(C2)-1)*5,0)*1000 -> 219340.56 | D3: =OFFSET(Solar!$C$11,(ROW(D2)-1)*5,0)*1000 -> 607009.58 | E3: =OFFSET(Solar!$F$11,(ROW(Solar!E2)-1)*5,0)*1000 -> 686543.83 | F3: =OFFSET(gas!$C$18,(ROW(gas!C2)-1)*5,0)*1000 -> 358513.34 | G3: =ccs!$H$6*ccs!B21*8760 -> 2063543.8 | H3: =OFFSET(gas!$F$18,(ROW(gas!E2)-1)*5,0)*1000 -> 398327.81 | I3: =ccs!$H$6*ccs!B21*8760 -> 2063543.8 | J3: =OFFSET(land!$C$12,(ROW(J2)-1)*5,0)*1000 -> 1076641 | K3: =OFFSET(offshore!$K$13,(ROW(K2)-1)*5,0)*1000 -> 2492044 | L3: =OFFSET(coal!$C$20,(ROW(L2)-1)*5,0)*1000 -> 612285.83 | M3: =ccs!$C$6*ccs!B21*8760 -> 2153370.6 | N3: =OFFSET(coal!$F$20,(ROW(N2)-1)*5,0)*1000 -> 1083549.8 | O3: =ccs!$F$6*ccs!B21*8760 -> 1634376.7 | P3: =OFFSET(nuclear!$B$8,(ROW(P2)-1)*5,0)*1000 -> 2113664.3 | Q3: =5969/6.5*1000 -> 918307.69 | R3: =2240.15384615385*1000 -> 2240153.8 | S3: =SMR!T3 -> 533582.41 | T3: =ccs!$J$6*ccs!B21*8760 -> 536986.99 | U3: =SMR!V3 -> 3218775.3 | V3: =ccs!$J$6*ccs!B21*8760 -> 536986.99 | W3: =OFFSET(Electrolyzer!$C$2,(ROW(W2)-1)*5,0)*1000 -> 905520 | X3: ='Fuel cell'!C3*1000 -> 1443172.5 | Y3: =OFFSET('H2 turbine'!$B$12,(ROW(Z2)-1)*5,0)*1000 -> 313166.67 | Z3: ='hydrogen storage'!B10 -> 61688.55 | AA3: ='hydrogen storage'!D10 -> 3010.854 | AB3: =2.25*1.1*1.0928 -> 2.70468 | AC3: =AB3*2 -> 5.40936 | AD3: =3.7*1.1*1.0928 -> 4.447696 | AE3: =DAC!B20*8760 -> 5433120
A4: 2030 | B4: =OFFSET(battery!$F$15,(ROW(B3)-1)*5,0)*1000 -> 483790.42 | C4: =OFFSET(battery!$C$15,(ROW(C3)-1)*5,0)*1000 -> 173879.95 | D4: =OFFSET(Solar!$C$11,(ROW(D3)-1)*5,0)*1000 -> 505217.02 | E4: =OFFSET(Solar!$F$11,(ROW(Solar!E3)-1)*5,0)*1000 -> 548996.6 | F4: =OFFSET(gas!$C$18,(ROW(gas!C3)-1)*5,0)*1000 -> 344008.72 | G4: =ccs!$H$6*ccs!B22*8760 -> 1719619.8 | H4: =OFFSET(gas!$F$18,(ROW(gas!E3)-1)*5,0)*1000 -> 380673.19 | I4: =ccs!$H$6*ccs!B22*8760 -> 1719619.8 | J4: =OFFSET(land!$C$12,(ROW(J3)-1)*5,0)*1000 -> 976192.22 | K4: =OFFSET(offshore!$K$13,(ROW(K3)-1)*5,0)*1000 -> 2290687.3 | L4: =OFFSET(coal!$C$20,(ROW(L3)-1)*5,0)*1000 -> 595355.36 | M4: =ccs!$C$6*ccs!B22*8760 -> 1794475.5 | N4: =OFFSET(coal!$F$20,(ROW(N3)-1)*5,0)*1000 -> 1072807.6 | O4: =ccs!$F$6*ccs!B22*8760 -> 1361980.6 | P4: =OFFSET(nuclear!$B$8,(ROW(P3)-1)*5,0)*1000 -> 2015508 | Q4: =5969/6.5*1000 -> 918307.69 | R4: =2240.15384615385*1000 -> 2240153.8 | S4: =SMR!T4 -> 511994.89 | T4: =ccs!$J$6*ccs!B22*8760 -> 447489.16 | U4: =SMR!V4 -> 3129772.1 | V4: =ccs!$J$6*ccs!B22*8760 -> 447489.16 | W4: =OFFSET(Electrolyzer!$C$2,(ROW(W3)-1)*5,0)*1000 -> 565950 | X4: ='Fuel cell'!C4*1000 -> 1324323 | Y4: =OFFSET('H2 turbine'!$B$12,(ROW(Z3)-1)*5,0)*1000 -> 311555.56 | Z4: ='hydrogen storage'!B11 -> 54331.2 | AA4: ='hydrogen storage'!D11 -> 2410.947 | AB4: =2.14*1.1*1.0928 -> 2.5724512 | AC4: =AB4*2 -> 5.1449024 | AD4: =3.52*1.1*1.0928 -> 4.2313216 | AE4: =DAC!B21*8760 -> 3395700
A5: 2035 | B5: =OFFSET(battery!$F$15,(ROW(B4)-1)*5,0)*1000 -> 467109.57 | C5: =OFFSET(battery!$C$15,(ROW(C4)-1)*5,0)*1000 -> 158078 | D5: =OFFSET(Solar!$C$11,(ROW(D4)-1)*5,0)*1000 -> 403424.47 | E5: =OFFSET(Solar!$F$11,(ROW(Solar!E4)-1)*5,0)*1000 -> 411449.37 | F5: =OFFSET(gas!$C$18,(ROW(gas!C4)-1)*5,0)*1000 -> 329504.09 | G5: =ccs!$H$6*ccs!B23*8760 -> 1582050.2 | H5: =OFFSET(gas!$F$18,(ROW(gas!E4)-1)*5,0)*1000 -> 363018.57 | I5: =ccs!$H$6*ccs!B23*8760 -> 1582050.2 | J5: =OFFSET(land!$C$12,(ROW(J4)-1)*5,0)*1000 -> 928132.19 | K5: =OFFSET(offshore!$K$13,(ROW(K4)-1)*5,0)*1000 -> 2166215.1 | L5: =OFFSET(coal!$C$20,(ROW(L4)-1)*5,0)*1000 -> 578403.11 | M5: =ccs!$C$6*ccs!B23*8760 -> 1650917.4 | N5: =OFFSET(coal!$F$20,(ROW(N4)-1)*5,0)*1000 -> 1062087.1 | O5: =ccs!$F$6*ccs!B23*8760 -> 1253022.1 | P5: =OFFSET(nuclear!$B$8,(ROW(P4)-1)*5,0)*1000 -> 1948571.2 | Q5: =5969/6.5*1000 -> 918307.69 | R5: =2240.15384615385*1000 -> 2240153.8 | S5: =SMR!T5 -> 490407.37 | T5: =ccs!$J$6*ccs!B23*8760 -> 411690.02 | U5: =SMR!V5 -> 3040654.4 | V5: =ccs!$J$6*ccs!B23*8760 -> 411690.02 | W5: =OFFSET(Electrolyzer!$C$2,(ROW(W4)-1)*5,0)*1000 -> 694166.67 | X5: ='Fuel cell'!C5*1000 -> 1233771 | Y5: =OFFSET('H2 turbine'!$B$12,(ROW(Z4)-1)*5,0)*1000 -> 309944.44 | Z5: ='hydrogen storage'!B12 -> 43578.15 | AA5: ='hydrogen storage'!D12 -> 2110.9935 | AB5: =(AB4+AB6)/2 -> 2.4462328 | AC5: =AB5*2 -> 4.8924656 | AD5: =(AD4+AD6)/2 -> 4.026968 | AE5: =DAC!B22*8760 -> 2886345
A6: 2040 | B6: =OFFSET(battery!$F$15,(ROW(B5)-1)*5,0)*1000 -> 449709.83 | C6: =OFFSET(battery!$C$15,(ROW(C5)-1)*5,0)*1000 -> 142362.74 | D6: =OFFSET(Solar!$C$11,(ROW(D5)-1)*5,0)*1000 -> 371518.84 | E6: =OFFSET(Solar!$F$11,(ROW(Solar!E5)-1)*5,0)*1000 -> 371597.4 | F6: =OFFSET(gas!$C$18,(ROW(gas!C5)-1)*5,0)*1000 -> 314962.84 | G6: =ccs!$H$6*ccs!B24*8760 -> 1444480.6 | H6: =OFFSET(gas!$F$18,(ROW(gas!E5)-1)*5,0)*1000 -> 348074.41 | I6: =ccs!$H$6*ccs!B24*8760 -> 1444480.6 | J6: =OFFSET(land!$C$12,(ROW(J5)-1)*5,0)*1000 -> 880072.15 | K6: =OFFSET(offshore!$K$13,(ROW(K5)-1)*5,0)*1000 -> 2075879.5 | L6: =OFFSET(coal!$C$20,(ROW(L5)-1)*5,0)*1000 -> 550665.03 | M6: =ccs!$C$6*ccs!B24*8760 -> 1507359.4 | N6: =OFFSET(coal!$F$20,(ROW(N5)-1)*5,0)*1000 -> 1051344.9 | O6: =ccs!$F$6*ccs!B24*8760 -> 1144063.7 | P6: =OFFSET(nuclear!$B$8,(ROW(P5)-1)*5,0)*1000 -> 1879782.7 | Q6: =5969/6.5*1000 -> 918307.69 | R6: =2240.15384615385*1000 -> 2240153.8 | S6: =SMR!T6 -> 468765.34 | T6: =ccs!$J$6*ccs!B24*8760 -> 375890.89 | U6: =SMR!V6 -> 2894835.9 | V6: =ccs!$J$6*ccs!B24*8760 -> 375890.89 | W6: =OFFSET(Electrolyzer!$C$2,(ROW(W5)-1)*5,0)*1000 -> 452760 | X6: ='Fuel cell'!C6*1000 -> 1143219 | Y6: =OFFSET('H2 turbine'!$B$12,(ROW(Z5)-1)*5,0)*1000 -> 308333.33 | Z6: ='hydrogen storage'!B13 -> 32825.1 | AA6: ='hydrogen storage'!D13 -> 1811.04 | AB6: =1.93*1.1*1.0928 -> 2.3200144 | AC6: =AB6*2 -> 4.6400288 | AD6: =3.18*1.1*1.0928 -> 3.8226144 | AE6: =DAC!B23*8760 -> 2376990
A7: 2045 | B7: =OFFSET(battery!$F$15,(ROW(B6)-1)*5,0)*1000 -> 431425.3 | C7: =OFFSET(battery!$C$15,(ROW(C6)-1)*5,0)*1000 -> 126754.17 | D7: =OFFSET(Solar!$C$11,(ROW(D6)-1)*5,0)*1000 -> 339613.21 | E7: =OFFSET(Solar!$F$11,(ROW(Solar!E6)-1)*5,0)*1000 -> 331745.43 | F7: =OFFSET(gas!$C$18,(ROW(gas!C6)-1)*5,0)*1000 -> 300458.21 | G7: =ccs!$H$6*ccs!B25*8760 -> 1410088.2 | H7: =OFFSET(gas!$F$18,(ROW(gas!E6)-1)*5,0)*1000 -> 333130.25 | I7: =ccs!$H$6*ccs!B25*8760 -> 1410088.2 | J7: =OFFSET(land!$C$12,(ROW(J6)-1)*5,0)*1000 -> 832012.11 | K7: =OFFSET(offshore!$K$13,(ROW(K6)-1)*5,0)*1000 -> 2004930.7 | L7: =OFFSET(coal!$C$20,(ROW(L6)-1)*5,0)*1000 -> 522948.75 | M7: =ccs!$C$6*ccs!B25*8760 -> 1471469.9 | N7: =OFFSET(coal!$F$20,(ROW(N6)-1)*5,0)*1000 -> 1040624.4 | O7: =ccs!$F$6*ccs!B25*8760 -> 1116824.1 | P7: =OFFSET(nuclear!$B$8,(ROW(P6)-1)*5,0)*1000 -> 1815208.1 | Q7: =5969/6.5*1000 -> 918307.69 | R7: =2240.15384615385*1000 -> 2240153.8 | S7: =SMR!T7 -> 447177.82 | T7: =ccs!$J$6*ccs!B25*8760 -> 366941.11 | U7: =SMR!V7 -> 2749131.9 | V7: =ccs!$J$6*ccs!B25*8760 -> 366941.11 | W7: =OFFSET(Electrolyzer!$C$2,(ROW(W6)-1)*5,0)*1000 -> 639833.33 | X7: ='Fuel cell'!C7*1000 -> 1052667 | Y7: =OFFSET('H2 turbine'!$B$12,(ROW(Z6)-1)*5,0)*1000 -> 306722.22 | Z7: ='hydrogen storage'!B14 -> 28863.45 | AA7: ='hydrogen storage'!D14 -> 1629.936 | AB7: =1.93*1.1*1.0928 -> 2.3200144 | AC7: =AB7*2 -> 4.6400288 | AD7: =3.18*1.1*1.0928 -> 3.8226144 | AE7: =DAC!B24*8760 -> 2207205
A8: 2050 | B8: =OFFSET(battery!$F$15,(ROW(B7)-1)*5,0)*1000 -> 412034.81 | C8: =OFFSET(battery!$C$15,(ROW(C7)-1)*5,0)*1000 -> 111278.96 | D8: =OFFSET(Solar!$C$11,(ROW(D7)-1)*5,0)*1000 -> 307707.58 | E8: =OFFSET(Solar!$F$11,(ROW(Solar!E7)-1)*5,0)*1000 -> 291893.46 | F8: =OFFSET(gas!$C$18,(ROW(gas!C7)-1)*5,0)*1000 -> 285953.58 | G8: =ccs!$H$6*ccs!B26*8760 -> 1375695.8 | H8: =OFFSET(gas!$F$18,(ROW(gas!E7)-1)*5,0)*1000 -> 318222.71 | I8: =ccs!$H$6*ccs!B26*8760 -> 1375695.8 | J8: =OFFSET(land!$C$12,(ROW(J7)-1)*5,0)*1000 -> 783952.07 | K8: =OFFSET(offshore!$K$13,(ROW(K7)-1)*5,0)*1000 -> 1946500.3 | L8: =OFFSET(coal!$C$20,(ROW(L7)-1)*5,0)*1000 -> 495210.68 | M8: =ccs!$C$6*ccs!B26*8760 -> 1435580.4 | N8: =OFFSET(coal!$F$20,(ROW(N7)-1)*5,0)*1000 -> 1029882.2 | O8: =ccs!$F$6*ccs!B26*8760 -> 1089584.5 | P8: =OFFSET(nuclear!$B$8,(ROW(P7)-1)*5,0)*1000 -> 1738729.6 | Q8: =5969/6.5*1000 -> 918307.69 | R8: =2240.15384615385*1000 -> 2240153.8 | S8: =SMR!T8 -> 425590.3 | T8: =ccs!$J$6*ccs!B26*8760 -> 357991.33 | U8: =SMR!V8 -> 2603313.4 | V8: =ccs!$J$6*ccs!B26*8760 -> 357991.33 | W8: =OFFSET(Electrolyzer!$C$2,(ROW(W7)-1)*5,0)*1000 -> 311272.5 | X8: ='Fuel cell'!C8*1000 -> 962115 | Y8: =OFFSET('H2 turbine'!$B$12,(ROW(Z7)-1)*5,0)*1000 -> 305111.11 | Z8: ='hydrogen storage'!B15 -> 24901.8 | AA8: ='hydrogen storage'!D15 -> 1448.832 | AB8: =1.93*1.1*1.0928 -> 2.3200144 | AC8: =AB8*2 -> 4.6400288 | AD8: =3.18*1.1*1.0928 -> 3.8226144 | AE8: =DAC!B25*8760 -> 2037420

Sheet advance_hydrogen
A1: Vintage | B1: Battery_Storage | C1: Battery_Storage_energy | D1: Central_PV | E1: Residential_PV | F1: Gas_Combustion_Turbine | G1: Gas_Combustion_Turbine_CCS | H1: Gas_CCGT | I1: Gas_CCGT_CCS | J1: Wind | K1: Offshore_Wind | L1: Coal | M1: Coal_CCS | N1: Coal_IGCC | O1: Coal_IGCC_CCS | P1: Nuclear | Q1: Hydro_Pumped | R1: Hydro_NonPumped | S1: SMR | T1: SMR_CCS | U1: Gasification | V1: Gasification_CCS | W1: Electrolyzer | X1: Fuel_cell | Y1: Hydrogen_turbine | Z1: Tank | AA1: Salt_cavern | AB1: CCS_storage_oil | AC1: CCS_storage_saline | AD1: CCS_storage_offshore | AE1: DAC
A2: 2020 | B2: =OFFSET(battery!$F$15,(ROW(B1)-1)*5,0)*1000 -> 492307.69 | C2: =OFFSET(battery!$C$15,(ROW(C1)-1)*5,0)*1000 -> 246153.85 | D2: =OFFSET(Solar!$C$11,(ROW(D1)-1)*5,0)*1000 -> 628000 | E2: =OFFSET(Solar!$F$11,(ROW(Solar!E1)-1)*5,0)*1000 -> 746000 | F2: =OFFSET(gas!$C$18,(ROW(gas!C1)-1)*5,0)*1000 -> 367230.77 | G2: =ccs!$H$6*ccs!B20*8760 -> 2957746.1 | H2: =OFFSET(gas!$F$18,(ROW(gas!E1)-1)*5,0)*1000 -> 408913.26 | I2: =ccs!$H$6*ccs!B20*8760 -> 2957746.1 | J2: =OFFSET(land!$C$12,(ROW(J1)-1)*5,0)*1000 -> 1157000 | K2: =OFFSET(offshore!$K$13,(ROW(K1)-1)*5,0)*1000 -> 2857000 | L2: =OFFSET(coal!$C$20,(ROW(L1)-1)*5,0)*1000 -> 622461.54 | M2: =ccs!$C$6*ccs!B20*8760 -> 3086497.8 | N2: =OFFSET(coal!$F$20,(ROW(N1)-1)*5,0)*1000 -> 1089999.5 | O2: =ccs!$F$6*ccs!B20*8760 -> 2342606.6 | P2: =OFFSET(nuclear!$B$8,(ROW(P1)-1)*5,0)*1000 -> 2461538.5 | Q2: =5969/6.5*1000 -> 918307.69 | R2: =2240.15384615385*1000 -> 2240153.8 | S2: =SMR!T2 -> 546556.72 | T2: =ccs!$J$6*ccs!B20*8760 -> 769681.35 | U2: =SMR!V2 -> 3272268.8 | V2: =ccs!$J$6*ccs!B20 -> 87.863168 | W2: =OFFSET(Electrolyzer!$C$2,(ROW(W1)-1)*5,0)*1000 -> 1245090 | X2: ='Fuel cell'!C2*1000 -> 1562022 | Y2: =OFFSET('H2 turbine'!$B$12,(ROW(Z1)-1)*5,0)*1000 -> 314777.78 | Z2: ='hydrogen storage'!B9 -> 69045.9 | AA2: ='hydrogen storage'!D9 -> 3610.761 | AB2: =2.36*1.1*1.0928 -> 2.8369088 | AC2: =AB2*2 -> 5.6738176 | AD2: =3.89*1.1*1.0928 -> 4.6760912 | AE2: =DAC!B19*8760 -> 7357350
A3: 2025 | B3: =OFFSET(battery!$F$15,(ROW(B2)-1)*5,0)*1000 -> 474606.98 | C3: =OFFSET(battery!$C$15,(ROW(C2)-1)*5,0)*1000 -> 219340.56 | D3: =OFFSET(Solar!$C$11,(ROW(D2)-1)*5,0)*1000 -> 607009.58 | E3: =OFFSET(Solar!$F$11,(ROW(Solar!E2)-1)*5,0)*1000 -> 686543.83 | F3: =OFFSET(gas!$C$18,(ROW(gas!C2)-1)*5,0)*1000 -> 358513.34 | G3: =ccs!$H$6*ccs!B21*8760 -> 2063543.8 | H3: =OFFSET(gas!$F$18,(ROW(gas!E2)-1)*5,0)*1000 -> 398327.81 | I3: =ccs!$H$6*ccs!B21*8760 -> 2063543.8 | J3: =OFFSET(land!$C$12,(ROW(J2)-1)*5,0)*1000 -> 1076641 | K3: =OFFSET(offshore!$K$13,(ROW(K2)-1)*5,0)*1000 -> 2492044 | L3: =OFFSET(coal!$C$20,(ROW(L2)-1)*5,0)*1000 -> 612285.83 | M3: =ccs!$C$6*ccs!B21*8760 -> 2153370.6 | N3: =OFFSET(coal!$F$20,(ROW(N2)-1)*5,0)*1000 -> 1083549.8 | O3: =ccs!$F$6*ccs!B21*8760 -> 1634376.7 | P3: =OFFSET(nuclear!$B$8,(ROW(P2)-1)*5,0)*1000 -> 2113664.3 | Q3: =5969/6.5*1000 -> 918307.69 | R3: =2240.15384615385*1000 -> 2240153.8 | S3: =SMR!T3 -> 533582.41 | T3: =ccs!$J$6*ccs!B21*8760 -> 536986.99 | U3: =SMR!V3 -> 3218775.3 | V3: =ccs!$J$6*ccs!B21 -> 61.299884 | W3: =OFFSET(Electrolyzer!$C$2,(ROW(W2)-1)*5,0)*1000 -> 905520 | X3: ='Fuel cell'!C3*1000 -> 1443172.5 | Y3: =OFFSET('H2 turbine'!$B$12,(ROW(Z2)-1)*5,0)*1000 -> 313166.67 | Z3: ='hydrogen storage'!B10 -> 61688.55 | AA3: ='hydrogen storage'!D10 -> 3010.854 | AB3: =2.25*1.1*1.0928 -> 2.70468 | AC3: =AB3*2 -> 5.40936 | AD3: =3.7*1.1*1.0928 -> 4.447696 | AE3: =DAC!B20*8760 -> 5433120
A4: 2030 | B4: =OFFSET(battery!$F$15,(ROW(B3)-1)*5,0)*1000 -> 483790.42 | C4: =OFFSET(battery!$C$15,(ROW(C3)-1)*5,0)*1000 -> 173879.95 | D4: =OFFSET(Solar!$C$11,(ROW(D3)-1)*5,0)*1000 -> 505217.02 | E4: =OFFSET(Solar!$F$11,(ROW(Solar!E3)-1)*5,0)*1000 -> 548996.6 | F4: =OFFSET(gas!$C$18,(ROW(gas!C3)-1)*5,0)*1000 -> 344008.72 | G4: =ccs!$H$6*ccs!B22*8760 -> 1719619.8 | H4: =OFFSET(gas!$F$18,(ROW(gas!E3)-1)*5,0)*1000 -> 380673.19 | I4: =ccs!$H$6*ccs!B22*8760 -> 1719619.8 | J4: =OFFSET(land!$C$12,(ROW(J3)-1)*5,0)*1000 -> 976192.22 | K4: =OFFSET(offshore!$K$13,(ROW(K3)-1)*5,0)*1000 -> 2290687.3 | L4: =OFFSET(coal!$C$20,(ROW(L3)-1)*5,0)*1000 -> 595355.36 | M4: =ccs!$C$6*ccs!B22*8760 -> 1794475.5 | N4: =OFFSET(coal!$F$20,(ROW(N3)-1)*5,0)*1000 -> 1072807.6 | O4: =ccs!$F$6*ccs!B22*8760 -> 1361980.6 | P4: =OFFSET(nuclear!$B$8,(ROW(P3)-1)*5,0)*1000 -> 2015508 | Q4: =5969/6.5*1000 -> 918307.69 | R4: =2240.15384615385*1000 -> 2240153.8 | S4: =SMR!T4 -> 511994.89 | T4: =ccs!$J$6*ccs!B22*8760 -> 447489.16 | U4: =SMR!V4 -> 3129772.1 | V4: =ccs!$J$6*ccs!B22 -> 51.083237 | W4: =OFFSET(Electrolyzer!$C$2,(ROW(W3)-1)*5,0)*1000 -> 565950 | X4: ='Fuel cell'!C4*1000 -> 1324323 | Y4: =OFFSET('H2 turbine'!$B$12,(ROW(Z3)-1)*5,0)*1000 -> 311555.56 | Z4: ='hydrogen storage'!B11 -> 54331.2 | AA4: ='hydrogen storage'!D11 -> 2410.947 | AB4: =2.14*1.1*1.0928 -> 2.5724512 | AC4: =AB4*2 -> 5.1449024 | AD4: =3.52*1.1*1.0928 -> 4.2313216 | AE4: =DAC!B21*8760 -> 3395700
A5: 2035 | B5: =OFFSET(battery!$F$15,(ROW(B4)-1)*5,0)*1000 -> 467109.57 | C5: =OFFSET(battery!$C$15,(ROW(C4)-1)*5,0)*1000 -> 158078 | D5: =OFFSET(Solar!$C$11,(ROW(D4)-1)*5,0)*1000 -> 403424.47 | E5: =OFFSET(Solar!$F$11,(ROW(Solar!E4)-1)*5,0)*1000 -> 411449.37 | F5: =OFFSET(gas!$C$18,(ROW(gas!C4)-1)*5,0)*1000 -> 329504.09 | G5: =ccs!$H$6*ccs!B23*8760 -> 1582050.2 | H5: =OFFSET(gas!$F$18,(ROW(gas!E4)-1)*5,0)*1000 -> 363018.57 | I5: =ccs!$H$6*ccs!B23*8760 -> 1582050.2 | J5: =OFFSET(land!$C$12,(ROW(J4)-1)*5,0)*1000 -> 928132.19 | K5: =OFFSET(offshore!$K$13,(ROW(K4)-1)*5,0)*1000 -> 2166215.1 | L5: =OFFSET(coal!$C$20,(ROW(L4)-1)*5,0)*1000 -> 578403.11 | M5: =ccs!$C$6*ccs!B23*8760 -> 1650917.4 | N5: =OFFSET(coal!$F$20,(ROW(N4)-1)*5,0)*1000 -> 1062087.1 | O5: =ccs!$F$6*ccs!B23*8760 -> 1253022.1 | P5: =OFFSET(nuclear!$B$8,(ROW(P4)-1)*5,0)*1000 -> 1948571.2 | Q5: =5969/6.5*1000 -> 918307.69 | R5: =2240.15384615385*1000 -> 2240153.8 | S5: =SMR!T5 -> 490407.37 | T5: =ccs!$J$6*ccs!B23*8760 -> 411690.02 | U5: =SMR!V5 -> 3040654.4 | V5: =ccs!$J$6*ccs!B23 -> 46.996578 | W5: =OFFSET(Electrolyzer!$C$2,(ROW(W4)-1)*5,0)*1000 -> 694166.67 | X5: ='Fuel cell'!C5*1000 -> 1233771 | Y5: =OFFSET('H2 turbine'!$B$12,(ROW(Z4)-1)*5,0)*1000 -> 309944.44 | Z5: ='hydrogen storage'!B12 -> 43578.15 | AA5: ='hydrogen storage'!D12 -> 2110.9935 | AB5: =(AB4+AB6)/2 -> 2.4462328 | AC5: =AB5*2 -> 4.8924656 | AD5: =(AD4+AD6)/2 -> 4.026968 | AE5: =DAC!B22*8760 -> 2886345
A6: 2040 | B6: =OFFSET(battery!$F$15,(ROW(B5)-1)*5,0)*1000 -> 449709.83 | C6: =OFFSET(battery!$C$15,(ROW(C5)-1)*5,0)*1000 -> 142362.74 | D6: =OFFSET(Solar!$C$11,(ROW(D5)-1)*5,0)*1000 -> 371518.84 | E6: =OFFSET(Solar!$F$11,(ROW(Solar!E5)-1)*5,0)*1000 -> 371597.4 | F6: =OFFSET(gas!$C$18,(ROW(gas!C5)-1)*5,0)*1000 -> 314962.84 | G6: =ccs!$H$6*ccs!B24*8760 -> 1444480.6 | H6: =OFFSET(gas!$F$18,(ROW(gas!E5)-1)*5,0)*1000 -> 348074.41 | I6: =ccs!$H$6*ccs!B24*8760 -> 1444480.6 | J6: =OFFSET(land!$C$12,(ROW(J5)-1)*5,0)*1000 -> 880072.15 | K6: =OFFSET(offshore!$K$13,(ROW(K5)-1)*5,0)*1000 -> 2075879.5 | L6: =OFFSET(coal!$C$20,(ROW(L5)-1)*5,0)*1000 -> 550665.03 | M6: =ccs!$C$6*ccs!B24*8760 -> 1507359.4 | N6: =OFFSET(coal!$F$20,(ROW(N5)-1)*5,0)*1000 -> 1051344.9 | O6: =ccs!$F$6*ccs!B24*8760 -> 1144063.7 | P6: =OFFSET(nuclear!$B$8,(ROW(P5)-1)*5,0)*1000 -> 1879782.7 | Q6: =5969/6.5*1000 -> 918307.69 | R6: =2240.15384615385*1000 -> 2240153.8 | S6: =SMR!T6 -> 468765.34 | T6: =ccs!$J$6*ccs!B24*8760 -> 375890.89 | U6: =SMR!V6 -> 2894835.9 | V6: =ccs!$J$6*ccs!B24 -> 42.909919 | W6: =OFFSET(Electrolyzer!$C$2,(ROW(W5)-1)*5,0)*1000 -> 452760 | X6: ='Fuel cell'!C6*1000 -> 1143219 | Y6: =OFFSET('H2 turbine'!$B$12,(ROW(Z5)-1)*5,0)*1000 -> 308333.33 | Z6: ='hydrogen storage'!B13 -> 32825.1 | AA6: ='hydrogen storage'!D13 -> 1811.04 | AB6: =1.93*1.1*1.0928 -> 2.3200144 | AC6: =AB6*2 -> 4.6400288 | AD6: =3.18*1.1*1.0928 -> 3.8226144 | AE6: =DAC!B23*8760 -> 2376990
A7: 2045 | B7: =OFFSET(battery!$F$15,(ROW(B6)-1)*5,0)*1000 -> 431425.3 | C7: =OFFSET(battery!$C$15,(ROW(C6)-1)*5,0)*1000 -> 126754.17 | D7: =OFFSET(Solar!$C$11,(ROW(D6)-1)*5,0)*1000 -> 339613.21 | E7: =OFFSET(Solar!$F$11,(ROW(Solar!E6)-1)*5,0)*1000 -> 331745.43 | F7: =OFFSET(gas!$C$18,(ROW(gas!C6)-1)*5,0)*1000 -> 300458.21 | G7: =ccs!$H$6*ccs!B25*8760 -> 1410088.2 | H7: =OFFSET(gas!$F$18,(ROW(gas!E6)-1)*5,0)*1000 -> 333130.25 | I7: =ccs!$H$6*ccs!B25*8760 -> 1410088.2 | J7: =OFFSET(land!$C$12,(ROW(J6)-1)*5,0)*1000 -> 832012.11 | K7: =OFFSET(offshore!$K$13,(ROW(K6)-1)*5,0)*1000 -> 2004930.7 | L7: =OFFSET(coal!$C$20,(ROW(L6)-1)*5,0)*1000 -> 522948.75 | M7: =ccs!$C$6*ccs!B25*8760 -> 1471469.9 | N7: =OFFSET(coal!$F$20,(ROW(N6)-1)*5,0)*1000 -> 1040624.4 | O7: =ccs!$F$6*ccs!B25*8760 -> 1116824.1 | P7: =OFFSET(nuclear!$B$8,(ROW(P6)-1)*5,0)*1000 -> 1815208.1 | Q7: =5969/6.5*1000 -> 918307.69 | R7: =2240.15384615385*1000 -> 2240153.8 | S7: =SMR!T7 -> 447177.82 | T7: =ccs!$J$6*ccs!B25*8760 -> 366941.11 | U7: =SMR!V7 -> 2749131.9 | V7: =ccs!$J$6*ccs!B25 -> 41.888254 | W7: =OFFSET(Electrolyzer!$C$2,(ROW(W6)-1)*5,0)*1000 -> 639833.33 | X7: ='Fuel cell'!C7*1000 -> 1052667 | Y7: =OFFSET('H2 turbine'!$B$12,(ROW(Z6)-1)*5,0)*1000 -> 306722.22 | Z7: ='hydrogen storage'!B14 -> 28863.45 | AA7: ='hydrogen storage'!D14 -> 1629.936 | AB7: =1.93*1.1*1.0928 -> 2.3200144 | AC7: =AB7*2 -> 4.6400288 | AD7: =3.18*1.1*1.0928 -> 3.8226144 | AE7: =DAC!B24*8760 -> 2207205
A8: 2050 | B8: =OFFSET(battery!$F$15,(ROW(B7)-1)*5,0)*1000 -> 412034.81 | C8: =OFFSET(battery!$C$15,(ROW(C7)-1)*5,0)*1000 -> 111278.96 | D8: =OFFSET(Solar!$C$11,(ROW(D7)-1)*5,0)*1000 -> 307707.58 | E8: =OFFSET(Solar!$F$11,(ROW(Solar!E7)-1)*5,0)*1000 -> 291893.46 | F8: =OFFSET(gas!$C$18,(ROW(gas!C7)-1)*5,0)*1000 -> 285953.58 | G8: =ccs!$H$6*ccs!B26*8760 -> 1375695.8 | H8: =OFFSET(gas!$F$18,(ROW(gas!E7)-1)*5,0)*1000 -> 318222.71 | I8: =ccs!$H$6*ccs!B26*8760 -> 1375695.8 | J8: =OFFSET(land!$C$12,(ROW(J7)-1)*5,0)*1000 -> 783952.07 | K8: =OFFSET(offshore!$K$13,(ROW(K7)-1)*5,0)*1000 -> 1946500.3 | L8: =OFFSET(coal!$C$20,(ROW(L7)-1)*5,0)*1000 -> 495210.68 | M8: =ccs!$C$6*ccs!B26*8760 -> 1435580.4 | N8: =OFFSET(coal!$F$20,(ROW(N7)-1)*5,0)*1000 -> 1029882.2 | O8: =ccs!$F$6*ccs!B26*8760 -> 1089584.5 | P8: =OFFSET(nuclear!$B$8,(ROW(P7)-1)*5,0)*1000 -> 1738729.6 | Q8: =5969/6.5*1000 -> 918307.69 | R8: =2240.15384615385*1000 -> 2240153.8 | S8: =SMR!T8 -> 425590.3 | T8: =ccs!$J$6*ccs!B26*8760 -> 357991.33 | U8: =SMR!V8 -> 2603313.4 | V8: =ccs!$J$6*ccs!B26 -> 40.86659 | W8: =OFFSET(Electrolyzer!$B$2,(ROW(W7)-1)*5,0)*1000 -> 282975 | X8: ='Fuel cell'!B8*1000 -> 599907 | Y8: =OFFSET('H2 turbine'!$B$12,(ROW(Z7)-1)*5,0)*1000 -> 305111.11 | Z8: ='hydrogen storage'!B16 -> 24901.8 | AA8: ='hydrogen storage'!E15 -> 1199.814 | AB8: =1.93*1.1*1.0928 -> 2.3200144 | AC8: =AB8*2 -> 4.6400288 | AD8: =3.18*1.1*1.0928 -> 3.8226144 | AE8: =DAC!B25*8760 -> 2037420

Sheet conservative_hydrogen
A1: Vintage | B1: Battery_Storage | C1: Battery_Storage_energy | D1: Central_PV | E1: Residential_PV | F1: Gas_Combustion_Turbine | G1: Gas_Combustion_Turbine_CCS | H1: Gas_CCGT | I1: Gas_CCGT_CCS | J1: Wind | K1: Offshore_Wind | L1: Coal | M1: Coal_CCS | N1: Coal_IGCC | O1: Coal_IGCC_CCS | P1: Nuclear | Q1: Hydro_Pumped | R1: Hydro_NonPumped | S1: SMR | T1: SMR_CCS | U1: Gasification | V1: Gasification_CCS | W1: Electrolyzer | X1: Fuel_cell | Y1: Hydrogen_turbine | Z1: Tank | AA1: Salt_cavern | AB1: CCS_storage_oil | AC1: CCS_storage_saline | AD1: CCS_storage_offshore | AE1: DAC
A2: 2020 | B2: =OFFSET(battery!$F$15,(ROW(B1)-1)*5,0)*1000 -> 492307.69 | C2: =OFFSET(battery!$C$15,(ROW(C1)-1)*5,0)*1000 -> 246153.85 | D2: =OFFSET(Solar!$C$11,(ROW(D1)-1)*5,0)*1000 -> 628000 | E2: =OFFSET(Solar!$F$11,(ROW(Solar!E1)-1)*5,0)*1000 -> 746000 | F2: =OFFSET(gas!$C$18,(ROW(gas!C1)-1)*5,0)*1000 -> 367230.77 | G2: =ccs!$H$6*ccs!B20*8760 -> 2957746.1 | H2: =OFFSET(gas!$F$18,(ROW(gas!E1)-1)*5,0)*1000 -> 408913.26 | I2: =ccs!$H$6*ccs!B20*8760 -> 2957746.1 | J2: =OFFSET(land!$C$12,(ROW(J1)-1)*5,0)*1000 -> 1157000 | K2: =OFFSET(offshore!$K$13,(ROW(K1)-1)*5,0)*1000 -> 2857000 | L2: =OFFSET(coal!$C$20,(ROW(L1)-1)*5,0)*1000 -> 622461.54 | M2: =ccs!$C$6*ccs!B20*8760 -> 3086497.8 | N2: =OFFSET(coal!$F$20,(ROW(N1)-1)*5,0)*1000 -> 1089999.5 | O2: =ccs!$F$6*ccs!B20*8760 -> 2342606.6 | P2: =OFFSET(nuclear!$C$8,(ROW(P1)-1)*5,0)*1000 -> 2461538.5 | Q2: =5969/6.5*1000 -> 918307.69 | R2: =2240.15384615385*1000 -> 2240153.8 | S2: =SMR!T2 -> 546556.72 | T2: =ccs!$J$6*ccs!B20*8760 -> 769681.35 | U2: =SMR!V2 -> 3272268.8 | V2: =ccs!$J$6*ccs!B20 -> 87.863168 | W2: =OFFSET(Electrolyzer!$C$2,(ROW(W1)-1)*5,0)*1000 -> 1245090 | X2: ='Fuel cell'!C2*1000 -> 1562022 | Y2: =OFFSET('H2 turbine'!$B$12,(ROW(Z1)-1)*5,0)*1000 -> 314777.78 | Z2: ='hydrogen storage'!B9 -> 69045.9 | AA2: ='hydrogen storage'!D9 -> 3610.761 | AB2: =2.36*1.1*1.0928 -> 2.8369088 | AC2: =AB2*2 -> 5.6738176 | AD2: =3.89*1.1*1.0928 -> 4.6760912 | AE2: =DAC!B19*8760 -> 7357350
A3: 2025 | B3: =OFFSET(battery!$F$15,(ROW(B2)-1)*5,0)*1000 -> 474606.98 | C3: =OFFSET(battery!$C$15,(ROW(C2)-1)*5,0)*1000 -> 219340.56 | D3: =OFFSET(Solar!$C$11,(ROW(D2)-1)*5,0)*1000 -> 607009.58 | E3: =OFFSET(Solar!$F$11,(ROW(Solar!E2)-1)*5,0)*1000 -> 686543.83 | F3: =OFFSET(gas!$C$18,(ROW(gas!C2)-1)*5,0)*1000 -> 358513.34 | G3: =ccs!$H$6*ccs!B21*8760 -> 2063543.8 | H3: =OFFSET(gas!$F$18,(ROW(gas!E2)-1)*5,0)*1000 -> 398327.81 | I3: =ccs!$H$6*ccs!B21*8760 -> 2063543.8 | J3: =OFFSET(land!$C$12,(ROW(J2)-1)*5,0)*1000 -> 1076641 | K3: =OFFSET(offshore!$K$13,(ROW(K2)-1)*5,0)*1000 -> 2492044 | L3: =OFFSET(coal!$C$20,(ROW(L2)-1)*5,0)*1000 -> 612285.83 | M3: =ccs!$C$6*ccs!B21*8760 -> 2153370.6 | N3: =OFFSET(coal!$F$20,(ROW(N2)-1)*5,0)*1000 -> 1083549.8 | O3: =ccs!$F$6*ccs!B21*8760 -> 1634376.7 | P3: =OFFSET(nuclear!$C$8,(ROW(P2)-1)*5,0)*1000 -> 2297494.5 | Q3: =5969/6.5*1000 -> 918307.69 | R3: =2240.15384615385*1000 -> 2240153.8 | S3: =SMR!T3 -> 533582.41 | T3: =ccs!$J$6*ccs!B21*8760 -> 536986.99 | U3: =SMR!V3 -> 3218775.3 | V3: =ccs!$J$6*ccs!B21 -> 61.299884 | W3: =OFFSET(Electrolyzer!$C$2,(ROW(W2)-1)*5,0)*1000 -> 905520 | X3: ='Fuel cell'!C3*1000 -> 1443172.5 | Y3: =OFFSET('H2 turbine'!$B$12,(ROW(Z2)-1)*5,0)*1000 -> 313166.67 | Z3: ='hydrogen storage'!B10 -> 61688.55 | AA3: ='hydrogen storage'!D10 -> 3010.854 | AB3: =2.25*1.1*1.0928 -> 2.70468 | AC3: =AB3*2 -> 5.40936 | AD3: =3.7*1.1*1.0928 -> 4.447696 | AE3: =DAC!B20*8760 -> 5433120
A4: 2030 | B4: =OFFSET(battery!$F$15,(ROW(B3)-1)*5,0)*1000 -> 483790.42 | C4: =OFFSET(battery!$C$15,(ROW(C3)-1)*5,0)*1000 -> 173879.95 | D4: =OFFSET(Solar!$C$11,(ROW(D3)-1)*5,0)*1000 -> 505217.02 | E4: =OFFSET(Solar!$F$11,(ROW(Solar!E3)-1)*5,0)*1000 -> 548996.6 | F4: =OFFSET(gas!$C$18,(ROW(gas!C3)-1)*5,0)*1000 -> 344008.72 | G4: =ccs!$H$6*ccs!B22*8760 -> 1719619.8 | H4: =OFFSET(gas!$F$18,(ROW(gas!E3)-1)*5,0)*1000 -> 380673.19 | I4: =ccs!$H$6*ccs!B22*8760 -> 1719619.8 | J4: =OFFSET(land!$C$12,(ROW(J3)-1)*5,0)*1000 -> 976192.22 | K4: =OFFSET(offshore!$K$13,(ROW(K3)-1)*5,0)*1000 -> 2290687.3 | L4: =OFFSET(coal!$C$20,(ROW(L3)-1)*5,0)*1000 -> 595355.36 | M4: =ccs!$C$6*ccs!B22*8760 -> 1794475.5 | N4: =OFFSET(coal!$F$20,(ROW(N3)-1)*5,0)*1000 -> 1072807.6 | O4: =ccs!$F$6*ccs!B22*8760 -> 1361980.6 | P4: =OFFSET(nuclear!$C$8,(ROW(P3)-1)*5,0)*1000 -> 2297494.5 | Q4: =5969/6.5*1000 -> 918307.69 | R4: =2240.15384615385*1000 -> 2240153.8 | S4: =SMR!T4 -> 511994.89 | T4: =ccs!$J$6*ccs!B22*8760 -> 447489.16 | U4: =SMR!V4 -> 3129772.1 | V4: =ccs!$J$6*ccs!B22 -> 51.083237 | W4: =OFFSET(Electrolyzer!$C$2,(ROW(W3)-1)*5,0)*1000 -> 565950 | X4: ='Fuel cell'!C4*1000 -> 1324323 | Y4: =OFFSET('H2 turbine'!$B$12,(ROW(Z3)-1)*5,0)*1000 -> 311555.56 | Z4: ='hydrogen storage'!B11 -> 54331.2 | AA4: ='hydrogen storage'!D11 -> 2410.947 | AB4: =2.14*1.1*1.0928 -> 2.5724512 | AC4: =AB4*2 -> 5.1449024 | AD4: =3.52*1.1*1.0928 -> 4.2313216 | AE4: =DAC!B21*8760 -> 3395700
A5: 2035 | B5: =OFFSET(battery!$F$15,(ROW(B4)-1)*5,0)*1000 -> 467109.57 | C5: =OFFSET(battery!$C$15,(ROW(C4)-1)*5,0)*1000 -> 158078 | D5: =OFFSET(Solar!$C$11,(ROW(D4)-1)*5,0)*1000 -> 403424.47 | E5: =OFFSET(Solar!$F$11,(ROW(Solar!E4)-1)*5,0)*1000 -> 411449.37 | F5: =OFFSET(gas!$C$18,(ROW(gas!C4)-1)*5,0)*1000 -> 329504.09 | G5: =ccs!$H$6*ccs!B23*8760 -> 1582050.2 | H5: =OFFSET(gas!$F$18,(ROW(gas!E4)-1)*5,0)*1000 -> 363018.57 | I5: =ccs!$H$6*ccs!B23*8760 -> 1582050.2 | J5: =OFFSET(land!$C$12,(ROW(J4)-1)*5,0)*1000 -> 928132.19 | K5: =OFFSET(offshore!$K$13,(ROW(K4)-1)*5,0)*1000 -> 2166215.1 | L5: =OFFSET(coal!$C$20,(ROW(L4)-1)*5,0)*1000 -> 578403.11 | M5: =ccs!$C$6*ccs!B23*8760 -> 1650917.4 | N5: =OFFSET(coal!$F$20,(ROW(N4)-1)*5,0)*1000 -> 1062087.1 | O5: =ccs!$F$6*ccs!B23*8760 -> 1253022.1 | P5: =OFFSET(nuclear!$C$8,(ROW(P4)-1)*5,0)*1000 -> 2297494.5 | Q5: =5969/6.5*1000 -> 918307.69 | R5: =2240.15384615385*1000 -> 2240153.8 | S5: =SMR!T5 -> 490407.37 | T5: =ccs!$J$6*ccs!B23*8760 -> 411690.02 | U5: =SMR!V5 -> 3040654.4 | V5: =ccs!$J$6*ccs!B23 -> 46.996578 | W5: =OFFSET(Electrolyzer!$C$2,(ROW(W4)-1)*5,0)*1000 -> 694166.67 | X5: ='Fuel cell'!C5*1000 -> 1233771 | Y5: =OFFSET('H2 turbine'!$B$12,(ROW(Z4)-1)*5,0)*1000 -> 309944.44 | Z5: ='hydrogen storage'!B12 -> 43578.15 | AA5: ='hydrogen storage'!D12 -> 2110.9935 | AB5: =(AB4+AB6)/2 -> 2.4462328 | AC5: =AB5*2 -> 4.8924656 | AD5: =(AD4+AD6)/2 -> 4.026968 | AE5: =DAC!B22*8760 -> 2886345
A6: 2040 | B6: =OFFSET(battery!$F$15,(ROW(B5)-1)*5,0)*1000 -> 449709.83 | C6: =OFFSET(battery!$C$15,(ROW(C5)-1)*5,0)*1000 -> 142362.74 | D6: =OFFSET(Solar!$C$11,(ROW(D5)-1)*5,0)*1000 -> 371518.84 | E6: =OFFSET(Solar!$F$11,(ROW(Solar!E5)-1)*5,0)*1000 -> 371597.4 | F6: =OFFSET(gas!$C$18,(ROW(gas!C5)-1)*5,0)*1000 -> 314962.84 | G6: =ccs!$H$6*ccs!B24*8760 -> 1444480.6 | H6: =OFFSET(gas!$F$18,(ROW(gas!E5)-1)*5,0)*1000 -> 348074.41 | I6: =ccs!$H$6*ccs!B24*8760 -> 1444480.6 | J6: =OFFSET(land!$C$12,(ROW(J5)-1)*5,0)*1000 -> 880072.15 | K6: =OFFSET(offshore!$K$13,(ROW(K5)-1)*5,0)*1000 -> 2075879.5 | L6: =OFFSET(coal!$C$20,(ROW(L5)-1)*5,0)*1000 -> 550665.03 | M6: =ccs!$C$6*ccs!B24*8760 -> 1507359.4 | N6: =OFFSET(coal!$F$20,(ROW(N5)-1)*5,0)*1000 -> 1051344.9 | O6: =ccs!$F$6*ccs!B24*8760 -> 1144063.7 | P6: =OFFSET(nuclear!$C$8,(ROW(P5)-1)*5,0)*1000 -> 2297494.5 | Q6: =5969/6.5*1000 -> 918307.69 | R6: =2240.15384615385*1000 -> 2240153.8 | S6: =SMR!T6 -> 468765.34 | T6: =ccs!$J$6*ccs!B24*8760 -> 375890.89 | U6: =SMR!V6 -> 2894835.9 | V6: =ccs!$J$6*ccs!B24 -> 42.909919 | W6: =OFFSET(Electrolyzer!$C$2,(ROW(W5)-1)*5,0)*1000 -> 452760 | X6: ='Fuel cell'!C6*1000 -> 1143219 | Y6: =OFFSET('H2 turbine'!$B$12,(ROW(Z5)-1)*5,0)*1000 -> 308333.33 | Z6: ='hydrogen storage'!B13 -> 32825.1 | AA6: ='hydrogen storage'!D13 -> 1811.04 | AB6: =1.93*1.1*1.0928 -> 2.3200144 | AC6: =AB6*2 -> 4.6400288 | AD6: =3.18*1.1*1.0928 -> 3.8226144 | AE6: =DAC!B23*8760 -> 2376990
A7: 2045 | B7: =OFFSET(battery!$F$15,(ROW(B6)-1)*5,0)*1000 -> 431425.3 | C7: =OFFSET(battery!$C$15,(ROW(C6)-1)*5,0)*1000 -> 126754.17 | D7: =OFFSET(Solar!$C$11,(ROW(D6)-1)*5,0)*1000 -> 339613.21 | E7: =OFFSET(Solar!$F$11,(ROW(Solar!E6)-1)*5,0)*1000 -> 331745.43 | F7: =OFFSET(gas!$C$18,(ROW(gas!C6)-1)*5,0)*1000 -> 300458.21 | G7: =ccs!$H$6*ccs!B25*8760 -> 1410088.2 | H7: =OFFSET(gas!$F$18,(ROW(gas!E6)-1)*5,0)*1000 -> 333130.25 | I7: =ccs!$H$6*ccs!B25*8760 -> 1410088.2 | J7: =OFFSET(land!$C$12,(ROW(J6)-1)*5,0)*1000 -> 832012.11 | K7: =OFFSET(offshore!$K$13,(ROW(K6)-1)*5,0)*1000 -> 2004930.7 | L7: =OFFSET(coal!$C$20,(ROW(L6)-1)*5,0)*1000 -> 522948.75 | M7: =ccs!$C$6*ccs!B25*8760 -> 1471469.9 | N7: =OFFSET(coal!$F$20,(ROW(N6)-1)*5,0)*1000 -> 1040624.4 | O7: =ccs!$F$6*ccs!B25*8760 -> 1116824.1 | P7: =OFFSET(nuclear!$C$8,(ROW(P6)-1)*5,0)*1000 -> 2297494.5 | Q7: =5969/6.5*1000 -> 918307.69 | R7: =2240.15384615385*1000 -> 2240153.8 | S7: =SMR!T7 -> 447177.82 | T7: =ccs!$J$6*ccs!B25*8760 -> 366941.11 | U7: =SMR!V7 -> 2749131.9 | V7: =ccs!$J$6*ccs!B25 -> 41.888254 | W7: =OFFSET(Electrolyzer!$C$2,(ROW(W6)-1)*5,0)*1000 -> 639833.33 | X7: ='Fuel cell'!C7*1000 -> 1052667 | Y7: =OFFSET('H2 turbine'!$B$12,(ROW(Z6)-1)*5,0)*1000 -> 306722.22 | Z7: ='hydrogen storage'!B14 -> 28863.45 | AA7: ='hydrogen storage'!D14 -> 1629.936 | AB7: =1.93*1.1*1.0928 -> 2.3200144 | AC7: =AB7*2 -> 4.6400288 | AD7: =3.18*1.1*1.0928 -> 3.8226144 | AE7: =DAC!B24*8760 -> 2207205
A8: 2050 | B8: =OFFSET(battery!$F$15,(ROW(B7)-1)*5,0)*1000 -> 412034.81 | C8: =OFFSET(battery!$C$15,(ROW(C7)-1)*5,0)*1000 -> 111278.96 | D8: =OFFSET(Solar!$C$11,(ROW(D7)-1)*5,0)*1000 -> 307707.58 | E8: =OFFSET(Solar!$F$11,(ROW(Solar!E7)-1)*5,0)*1000 -> 291893.46 | F8: =OFFSET(gas!$C$18,(ROW(gas!C7)-1)*5,0)*1000 -> 285953.58 | G8: =ccs!$H$6*ccs!B26*8760 -> 1375695.8 | H8: =OFFSET(gas!$F$18,(ROW(gas!E7)-1)*5,0)*1000 -> 318222.71 | I8: =ccs!$H$6*ccs!B26*8760 -> 1375695.8 | J8: =OFFSET(land!$C$12,(ROW(J7)-1)*5,0)*1000 -> 783952.07 | K8: =OFFSET(offshore!$K$13,(ROW(K7)-1)*5,0)*1000 -> 1946500.3 | L8: =OFFSET(coal!$C$20,(ROW(L7)-1)*5,0)*1000 -> 495210.68 | M8: =ccs!$C$6*ccs!B26*8760 -> 1435580.4 | N8: =OFFSET(coal!$F$20,(ROW(N7)-1)*5,0)*1000 -> 1029882.2 | O8: =ccs!$F$6*ccs!B26*8760 -> 1089584.5 | P8: =OFFSET(nuclear!$C$8,(ROW(P7)-1)*5,0)*1000 -> 2297494.5 | Q8: =5969/6.5*1000 -> 918307.69 | R8: =2240.15384615385*1000 -> 2240153.8 | S8: =SMR!T8 -> 425590.3 | T8: =ccs!$J$6*ccs!B26*8760 -> 357991.33 | U8: =SMR!V8 -> 2603313.4 | V8: =ccs!$J$6*ccs!B26 -> 40.86659 | W8: =OFFSET(Electrolyzer!$D$2,(ROW(W7)-1)*5,0)*1000 -> 385000 | X8: ='Fuel cell'!D8*1000 -> 1086624 | Y8: =OFFSET('H2 turbine'!$B$12,(ROW(Z7)-1)*5,0)*1000 -> 305111.11 | Z8: ='hydrogen storage'!B17 -> 41880.3 | AA8: ='hydrogen storage'!F15 -> 2161.929 | AB8: =1.93*1.1*1.0928 -> 2.3200144 | AC8: =AB8*2 -> 4.6400288 | AD8: =3.18*1.1*1.0928 -> 3.8226144 | AE8: =DAC!B25*8760 -> 2037420

Sheet High_cost_PV
A1: Vintage | B1: Battery_Storage | C1: Battery_Storage_energy | D1: Central_PV | E1: Residential_PV | F1: Gas_Combustion_Turbine | G1: Gas_Combustion_Turbine_CCS | H1: Gas_CCGT | I1: Gas_CCGT_CCS | J1: Wind | K1: Offshore_Wind | L1: Coal | M1: Coal_CCS | N1: Coal_IGCC | O1: Coal_IGCC_CCS | P1: Nuclear | Q1: Hydro_Pumped | R1: Hydro_NonPumped | S1: SMR | T1: SMR_CCS | U1: Gasification | V1: Gasification_CCS | W1: Electrolyzer | X1: Fuel_cell | Y1: Hydrogen_turbine | Z1: Tank | AA1: Salt_cavern | AB1: CCS_storage_oil | AC1: CCS_storage_saline | AD1: CCS_storage_offshore | AE1: DAC
A2: 2020 | B2: =OFFSET(battery!$F$15,(ROW(B1)-1)*5,0)*1000 -> 492307.69 | C2: =OFFSET(battery!$C$15,(ROW(C1)-1)*5,0)*1000 -> 246153.85 | D2: =OFFSET(Solar!$C$11,(ROW(D1)-1)*5,0)*1000 -> 628000 | E2: =OFFSET(Solar!$F$11,(ROW(Solar!E1)-1)*5,0)*1000 -> 746000 | F2: =OFFSET(gas!$C$18,(ROW(gas!C1)-1)*5,0)*1000 -> 367230.77 | G2: =ccs!$H$6*ccs!B20 -> 337.64225 | H2: =OFFSET(gas!$F$18,(ROW(gas!E1)-1)*5,0)*1000 -> 408913.26 | I2: =ccs!$H$6*ccs!B20 -> 337.64225 | J2: =OFFSET(land!$C$12,(ROW(J1)-1)*5,0)*1000 -> 1157000 | K2: =OFFSET(offshore!$K$13,(ROW(K1)-1)*5,0)*1000 -> 2857000 | L2: =OFFSET(coal!$C$20,(ROW(L1)-1)*5,0)*1000 -> 622461.54 | M2: =ccs!$C$6*ccs!B20 -> 352.33994 | N2: =OFFSET(coal!$F$20,(ROW(N1)-1)*5,0)*1000 -> 1089999.5 | O2: =ccs!$F$6*ccs!B20 -> 267.42084 | P2: =OFFSET(nuclear!$B$8,(ROW(P1)-1)*5,0)*1000 -> 2461538.5 | Q2: =5969/6.5*1000 -> 918307.69 | R2: =2240.15384615385*1000 -> 2240153.8 | S2: =SMR!T2 -> 546556.72 | T2: =ccs!$J$6*ccs!B20 -> 87.863168 | U2: =SMR!V2 -> 3272268.8 | V2: =ccs!$J$6*ccs!B20 -> 87.863168 | W2: =OFFSET(Electrolyzer!$C$2,(ROW(W1)-1)*5,0)*1000 -> 1245090 | X2: ='Fuel cell'!C2*1000 -> 1562022 | Y2: =OFFSET('H2 turbine'!$B$12,(ROW(Z1)-1)*5,0)*1000 -> 314777.78 | Z2: ='hydrogen storage'!B9 -> 69045.9 | AA2: ='hydrogen storage'!D9 -> 3610.761 | AB2: =2.36*1.1*1.0928 -> 2.8369088 | AC2: =AB2*2 -> 5.6738176 | AD2: =3.89*1.1*1.0928 -> 4.6760912 | AE2: =DAC!B19 -> 839.88014
A3: 2025 | B3: =OFFSET(battery!$F$15,(ROW(B2)-1)*5,0)*1000 -> 474606.98 | C3: =OFFSET(battery!$C$15,(ROW(C2)-1)*5,0)*1000 -> 219340.56 | D3: 628000 | E3: 746000 | F3: =OFFSET(gas!$C$18,(ROW(gas!C2)-1)*5,0)*1000 -> 358513.34 | G3: =ccs!$H$6*ccs!B21 -> 235.56436 | H3: =OFFSET(gas!$F$18,(ROW(gas!E2)-1)*5,0)*1000 -> 398327.81 | I3: =ccs!$H$6*ccs!B21 -> 235.56436 | J3: =OFFSET(land!$C$12,(ROW(J2)-1)*5,0)*1000 -> 1076641 | K3: =OFFSET(offshore!$K$13,(ROW(K2)-1)*5,0)*1000 -> 2492044 | L3: =OFFSET(coal!$C$20,(ROW(L2)-1)*5,0)*1000 -> 612285.83 | M3: =ccs!$C$6*ccs!B21 -> 245.81856 | N3: =OFFSET(coal!$F$20,(ROW(N2)-1)*5,0)*1000 -> 1083549.8 | O3: =ccs!$F$6*ccs!B21 -> 186.57268 | P3: =OFFSET(nuclear!$B$8,(ROW(P2)-1)*5,0)*1000 -> 2113664.3 | Q3: =5969/6.5*1000 -> 918307.69 | R3: =2240.15384615385*1000 -> 2240153.8 | S3: =SMR!T3 -> 533582.41 | T3: =ccs!$J$6*ccs!B21 -> 61.299884 | U3: =SMR!V3 -> 3218775.3 | V3: =ccs!$J$6*ccs!B21 -> 61.299884 | W3: 1245090 | X3: 1562022 | Y3: =OFFSET('H2 turbine'!$B$12,(ROW(Z2)-1)*5,0)*1000 -> 313166.67 | Z3: 69045.9 | AA3: ='hydrogen storage'!D10 -> 3010.854 | AB3: =2.25*1.1*1.0928 -> 2.70468 | AC3: =AB3*2 -> 5.40936 | AD3: =3.7*1.1*1.0928 -> 4.447696 | AE3: =DAC!B20 -> 620.21918
A4: 2030 | B4: =OFFSET(battery!$F$15,(ROW(B3)-1)*5,0)*1000 -> 483790.42 | C4: =OFFSET(battery!$C$15,(ROW(C3)-1)*5,0)*1000 -> 173879.95 | D4: 628000 | E4: 746000 | F4: =OFFSET(gas!$C$18,(ROW(gas!C3)-1)*5,0)*1000 -> 344008.72 | G4: =ccs!$H$6*ccs!B22 -> 196.30363 | H4: =OFFSET(gas!$F$18,(ROW(gas!E3)-1)*5,0)*1000 -> 380673.19 | I4: =ccs!$H$6*ccs!B22 -> 196.30363 | J4: =OFFSET(land!$C$12,(ROW(J3)-1)*5,0)*1000 -> 976192.22 | K4: =OFFSET(offshore!$K$13,(ROW(K3)-1)*5,0)*1000 -> 2290687.3 | L4: =OFFSET(coal!$C$20,(ROW(L3)-1)*5,0)*1000 -> 595355.36 | M4: =ccs!$C$6*ccs!B22 -> 204.8488 | N4: =OFFSET(coal!$F$20,(ROW(N3)-1)*5,0)*1000 -> 1072807.6 | O4: =ccs!$F$6*ccs!B22 -> 155.47723 | P4: =OFFSET(nuclear!$B$8,(ROW(P3)-1)*5,0)*1000 -> 2015508 | Q4: =5969/6.5*1000 -> 918307.69 | R4: =2240.15384615385*1000 -> 2240153.8 | S4: =SMR!T4 -> 511994.89 | T4: =ccs!$J$6*ccs!B22 -> 51.083237 | U4: =SMR!V4 -> 3129772.1 | V4: =ccs!$J$6*ccs!B22 -> 51.083237 | W4: 1245090 | X4: 1562022 | Y4: =OFFSET('H2 turbine'!$B$12,(ROW(Z3)-1)*5,0)*1000 -> 311555.56 | Z4: 69045.9 | AA4: ='hydrogen storage'!D11 -> 2410.947 | AB4: =2.14*1.1*1.0928 -> 2.5724512 | AC4: =AB4*2 -> 5.1449024 | AD4: =3.52*1.1*1.0928 -> 4.2313216 | AE4: =DAC!B21 -> 387.63699
A5: 2035 | B5: =OFFSET(battery!$F$15,(ROW(B4)-1)*5,0)*1000 -> 467109.57 | C5: =OFFSET(battery!$C$15,(ROW(C4)-1)*5,0)*1000 -> 158078 | D5: 628000 | E5: 746000 | F5: =OFFSET(gas!$C$18,(ROW(gas!C4)-1)*5,0)*1000 -> 329504.09 | G5: =ccs!$H$6*ccs!B23 -> 180.59934 | H5: =OFFSET(gas!$F$18,(ROW(gas!E4)-1)*5,0)*1000 -> 363018.57 | I5: =ccs!$H$6*ccs!B23 -> 180.59934 | J5: =OFFSET(land!$C$12,(ROW(J4)-1)*5,0)*1000 -> 928132.19 | K5: =OFFSET(offshore!$K$13,(ROW(K4)-1)*5,0)*1000 -> 2166215.1 | L5: =OFFSET(coal!$C$20,(ROW(L4)-1)*5,0)*1000 -> 578403.11 | M5: =ccs!$C$6*ccs!B23 -> 188.4609 | N5: =OFFSET(coal!$F$20,(ROW(N4)-1)*5,0)*1000 -> 1062087.1 | O5: =ccs!$F$6*ccs!B23 -> 143.03906 | P5: =OFFSET(nuclear!$B$8,(ROW(P4)-1)*5,0)*1000 -> 1948571.2 | Q5: =5969/6.5*1000 -> 918307.69 | R5: =2240.15384615385*1000 -> 2240153.8 | S5: =SMR!T5 -> 490407.37 | T5: =ccs!$J$6*ccs!B23 -> 46.996578 | U5: =SMR!V5 -> 3040654.4 | V5: =ccs!$J$6*ccs!B23 -> 46.996578 | W5: 1245090 | X5: 1562022 | Y5: =OFFSET('H2 turbine'!$B$12,(ROW(Z4)-1)*5,0)*1000 -> 309944.44 | Z5: 69045.9 | AA5: ='hydrogen storage'!D12 -> 2110.9935 | AB5: =(AB4+AB6)/2 -> 2.4462328 | AC5: =AB5*2 -> 4.8924656 | AD5: =(AD4+AD6)/2 -> 4.026968 | AE5: =DAC!B22 -> 329.49144
A6: 2040 | B6: =OFFSET(battery!$F$15,(ROW(B5)-1)*5,0)*1000 -> 449709.83 | C6: =OFFSET(battery!$C$15,(ROW(C5)-1)*5,0)*1000 -> 142362.74 | D6: 628000 | E6: 746000 | F6: =OFFSET(gas!$C$18,(ROW(gas!C5)-1)*5,0)*1000 -> 314962.84 | G6: =ccs!$H$6*ccs!B24 -> 164.89505 | H6: =OFFSET(gas!$F$18,(ROW(gas!E5)-1)*5,0)*1000 -> 348074.41 | I6: =ccs!$H$6*ccs!B24 -> 164.89505 | J6: =OFFSET(land!$C$12,(ROW(J5)-1)*5,0)*1000 -> 880072.15 | K6: =OFFSET(offshore!$K$13,(ROW(K5)-1)*5,0)*1000 -> 2075879.5 | L6: =OFFSET(coal!$C$20,(ROW(L5)-1)*5,0)*1000 -> 550665.03 | M6: =ccs!$C$6*ccs!B24 -> 172.07299 | N6: =OFFSET(coal!$F$20,(ROW(N5)-1)*5,0)*1000 -> 1051344.9 | O6: =ccs!$F$6*ccs!B24 -> 130.60088 | P6: =OFFSET(nuclear!$B$8,(ROW(P5)-1)*5,0)*1000 -> 1879782.7 | Q6: =5969/6.5*1000 -> 918307.69 | R6: =2240.15384615385*1000 -> 2240153.8 | S6: =SMR!T6 -> 468765.34 | T6: =ccs!$J$6*ccs!B24 -> 42.909919 | U6: =SMR!V6 -> 2894835.9 | V6: =ccs!$J$6*ccs!B24 -> 42.909919 | W6: 1245090 | X6: 1562022 | Y6: =OFFSET('H2 turbine'!$B$12,(ROW(Z5)-1)*5,0)*1000 -> 308333.33 | Z6: 69045.9 | AA6: ='hydrogen storage'!D13 -> 1811.04 | AB6: =1.93*1.1*1.0928 -> 2.3200144 | AC6: =AB6*2 -> 4.6400288 | AD6: =3.18*1.1*1.0928 -> 3.8226144 | AE6: =DAC!B23 -> 271.34589
A7: 2045 | B7: =OFFSET(battery!$F$15,(ROW(B6)-1)*5,0)*1000 -> 431425.3 | C7: =OFFSET(battery!$C$15,(ROW(C6)-1)*5,0)*1000 -> 126754.17 | D7: 628000 | E7: 746000 | F7: =OFFSET(gas!$C$18,(ROW(gas!C6)-1)*5,0)*1000 -> 300458.21 | G7: =ccs!$H$6*ccs!B25 -> 160.96898 | H7: =OFFSET(gas!$F$18,(ROW(gas!E6)-1)*5,0)*1000 -> 333130.25 | I7: =ccs!$H$6*ccs!B25 -> 160.96898 | J7: =OFFSET(land!$C$12,(ROW(J6)-1)*5,0)*1000 -> 832012.11 | K7: =OFFSET(offshore!$K$13,(ROW(K6)-1)*5,0)*1000 -> 2004930.7 | L7: =OFFSET(coal!$C$20,(ROW(L6)-1)*5,0)*1000 -> 522948.75 | M7: =ccs!$C$6*ccs!B25 -> 167.97602 | N7: =OFFSET(coal!$F$20,(ROW(N6)-1)*5,0)*1000 -> 1040624.4 | O7: =ccs!$F$6*ccs!B25 -> 127.49133 | P7: =OFFSET(nuclear!$B$8,(ROW(P6)-1)*5,0)*1000 -> 1815208.1 | Q7: =5969/6.5*1000 -> 918307.69 | R7: =2240.15384615385*1000 -> 2240153.8 | S7: =SMR!T7 -> 447177.82 | T7: =ccs!$J$6*ccs!B25 -> 41.888254 | U7: =SMR!V7 -> 2749131.9 | V7: =ccs!$J$6*ccs!B25 -> 41.888254 | W7: 1245090 | X7: 1562022 | Y7: =OFFSET('H2 turbine'!$B$12,(ROW(Z6)-1)*5,0)*1000 -> 306722.22 | Z7: 69045.9 | AA7: ='hydrogen storage'!D14 -> 1629.936 | AB7: =1.93*1.1*1.0928 -> 2.3200144 | AC7: =AB7*2 -> 4.6400288 | AD7: =3.18*1.1*1.0928 -> 3.8226144 | AE7: =DAC!B24 -> 251.96404
A8: 2050 | B8: =OFFSET(battery!$F$15,(ROW(B7)-1)*5,0)*1000 -> 412034.81 | C8: =OFFSET(battery!$C$15,(ROW(C7)-1)*5,0)*1000 -> 111278.96 | D8: 628000 | E8: 746000 | F8: =OFFSET(gas!$C$18,(ROW(gas!C7)-1)*5,0)*1000 -> 285953.58 | G8: =ccs!$H$6*ccs!B26 -> 157.0429 | H8: =OFFSET(gas!$F$18,(ROW(gas!E7)-1)*5,0)*1000 -> 318222.71 | I8: =ccs!$H$6*ccs!B26 -> 157.0429 | J8: =OFFSET(land!$C$12,(ROW(J7)-1)*5,0)*1000 -> 783952.07 | K8: =OFFSET(offshore!$K$13,(ROW(K7)-1)*5,0)*1000 -> 1946500.3 | L8: =OFFSET(coal!$C$20,(ROW(L7)-1)*5,0)*1000 -> 495210.68 | M8: =ccs!$C$6*ccs!B26 -> 163.87904 | N8: =OFFSET(coal!$F$20,(ROW(N7)-1)*5,0)*1000 -> 1029882.2 | O8: =ccs!$F$6*ccs!B26 -> 124.38179 | P8: =OFFSET(nuclear!$B$8,(ROW(P7)-1)*5,0)*1000 -> 1738729.6 | Q8: =5969/6.5*1000 -> 918307.69 | R8: =2240.15384615385*1000 -> 2240153.8 | S8: =SMR!T8 -> 425590.3 | T8: =ccs!$J$6*ccs!B26 -> 40.86659 | U8: =SMR!V8 -> 2603313.4 | V8: =ccs!$J$6*ccs!B26 -> 40.86659 | W8: 1245090 | X8: 1562022 | Y8: =OFFSET('H2 turbine'!$B$12,(ROW(Z7)-1)*5,0)*1000 -> 305111.11 | Z8: 69045.9 | AA8: ='hydrogen storage'!D15 -> 1448.832 | AB8: =1.93*1.1*1.0928 -> 2.3200144 | AC8: =AB8*2 -> 4.6400288 | AD8: =3.18*1.1*1.0928 -> 3.8226144 | AE8: =DAC!B25 -> 232.58219

Sheet High_cost_wind
A1: Vintage | B1: Battery_Storage | C1: Battery_Storage_energy | D1: Central_PV | E1: Residential_PV | F1: Gas_Combustion_Turbine | G1: Gas_Combustion_Turbine_CCS | H1: Gas_CCGT | I1: Gas_CCGT_CCS | J1: Wind | K1: Offshore_Wind | L1: Coal | M1: Coal_CCS | N1: Coal_IGCC | O1: Coal_IGCC_CCS | P1: Nuclear | Q1: Hydro_Pumped | R1: Hydro_NonPumped | S1: SMR | T1: SMR_CCS | U1: Gasification | V1: Gasification_CCS | W1: Electrolyzer | X1: Fuel_cell | Y1: Hydrogen_turbine | Z1: Tank | AA1: Salt_cavern | AB1: CCS_storage_oil | AC1: CCS_storage_saline | AD1: CCS_storage_offshore | AE1: DAC
A2: 2020 | B2: =OFFSET(battery!$F$15,(ROW(B1)-1)*5,0)*1000 -> 492307.69 | C2: =OFFSET(battery!$C$15,(ROW(C1)-1)*5,0)*1000 -> 246153.85 | D2: =OFFSET(Solar!$C$11,(ROW(D1)-1)*5,0)*1000 -> 628000 | E2: =OFFSET(Solar!$F$11,(ROW(Solar!E1)-1)*5,0)*1000 -> 746000 | F2: =OFFSET(gas!$C$18,(ROW(gas!C1)-1)*5,0)*1000 -> 367230.77 | G2: =ccs!$H$6*ccs!B20 -> 337.64225 | H2: =OFFSET(gas!$F$18,(ROW(gas!E1)-1)*5,0)*1000 -> 408913.26 | I2: =ccs!$H$6*ccs!B20 -> 337.64225 | J2: =OFFSET(land!$C$12,(ROW(J1)-1)*5,0)*1000 -> 1157000 | K2: =OFFSET(offshore!$K$13,(ROW(K1)-1)*5,0)*1000 -> 2857000 | L2: =OFFSET(coal!$C$20,(ROW(L1)-1)*5,0)*1000 -> 622461.54 | M2: =ccs!$C$6*ccs!B20 -> 352.33994 | N2: =OFFSET(coal!$F$20,(ROW(N1)-1)*5,0)*1000 -> 1089999.5 | O2: =ccs!$F$6*ccs!B20 -> 267.42084 | P2: =OFFSET(nuclear!$B$8,(ROW(P1)-1)*5,0)*1000 -> 2461538.5 | Q2: =5969/6.5*1000 -> 918307.69 | R2: =2240.15384615385*1000 -> 2240153.8 | S2: =SMR!T2 -> 546556.72 | T2: =ccs!$J$6*ccs!B20 -> 87.863168 | U2: =SMR!V2 -> 3272268.8 | V2: =ccs!$J$6*ccs!B20 -> 87.863168 | W2: =OFFSET(Electrolyzer!$C$2,(ROW(W1)-1)*5,0)*1000 -> 1245090 | X2: ='Fuel cell'!C2*1000 -> 1562022 | Y2: =OFFSET('H2 turbine'!$B$12,(ROW(Z1)-1)*5,0)*1000 -> 314777.78 | Z2: ='hydrogen storage'!B9 -> 69045.9 | AA2: ='hydrogen storage'!D9 -> 3610.761 | AB2: =2.36*1.1*1.0928 -> 2.8369088 | AC2: =AB2*2 -> 5.6738176 | AD2: =3.89*1.1*1.0928 -> 4.6760912 | AE2: =DAC!B19 -> 839.88014
A3: 2025 | B3: =OFFSET(battery!$F$15,(ROW(B2)-1)*5,0)*1000 -> 474606.98 | C3: =OFFSET(battery!$C$15,(ROW(C2)-1)*5,0)*1000 -> 219340.56 | D3: =OFFSET(Solar!$C$11,(ROW(D2)-1)*5,0)*1000 -> 607009.58 | E3: =OFFSET(Solar!$F$11,(ROW(Solar!E2)-1)*5,0)*1000 -> 686543.83 | F3: =OFFSET(gas!$C$18,(ROW(gas!C2)-1)*5,0)*1000 -> 358513.34 | G3: =ccs!$H$6*ccs!B21 -> 235.56436 | H3: =OFFSET(gas!$F$18,(ROW(gas!E2)-1)*5,0)*1000 -> 398327.81 | I3: =ccs!$H$6*ccs!B21 -> 235.56436 | J3: 1157000 | K3: 2857000 | L3: =OFFSET(coal!$C$20,(ROW(L2)-1)*5,0)*1000 -> 612285.83 | M3: =ccs!$C$6*ccs!B21 -> 245.81856 | N3: =OFFSET(coal!$F$20,(ROW(N2)-1)*5,0)*1000 -> 1083549.8 | O3: =ccs!$F$6*ccs!B21 -> 186.57268 | P3: =OFFSET(nuclear!$B$8,(ROW(P2)-1)*5,0)*1000 -> 2113664.3 | Q3: =5969/6.5*1000 -> 918307.69 | R3: =2240.15384615385*1000 -> 2240153.8 | S3: =SMR!T3 -> 533582.41 | T3: =ccs!$J$6*ccs!B21 -> 61.299884 | U3: =SMR!V3 -> 3218775.3 | V3: =ccs!$J$6*ccs!B21 -> 61.299884 | W3: 1245090 | X3: 1562022 | Y3: =OFFSET('H2 turbine'!$B$12,(ROW(Z2)-1)*5,0)*1000 -> 313166.67 | Z3: 69045.9 | AA3: ='hydrogen storage'!D10 -> 3010.854 | AB3: =2.25*1.1*1.0928 -> 2.70468 | AC3: =AB3*2 -> 5.40936 | AD3: =3.7*1.1*1.0928 -> 4.447696 | AE3: =DAC!B20 -> 620.21918
A4: 2030 | B4: =OFFSET(battery!$F$15,(ROW(B3)-1)*5,0)*1000 -> 483790.42 | C4: =OFFSET(battery!$C$15,(ROW(C3)-1)*5,0)*1000 -> 173879.95 | D4: =OFFSET(Solar!$C$11,(ROW(D3)-1)*5,0)*1000 -> 505217.02 | E4: =OFFSET(Solar!$F$11,(ROW(Solar!E3)-1)*5,0)*1000 -> 548996.6 | F4: =OFFSET(gas!$C$18,(ROW(gas!C3)-1)*5,0)*1000 -> 344008.72 | G4: =ccs!$H$6*ccs!B22 -> 196.30363 | H4: =OFFSET(gas!$F$18,(ROW(gas!E3)-1)*5,0)*1000 -> 380673.19 | I4: =ccs!$H$6*ccs!B22 -> 196.30363 | J4: 1157000 | K4: 2857000 | L4: =OFFSET(coal!$C$20,(ROW(L3)-1)*5,0)*1000 -> 595355.36 | M4: =ccs!$C$6*ccs!B22 -> 204.8488 | N4: =OFFSET(coal!$F$20,(ROW(N3)-1)*5,0)*1000 -> 1072807.6 | O4: =ccs!$F$6*ccs!B22 -> 155.47723 | P4: =OFFSET(nuclear!$B$8,(ROW(P3)-1)*5,0)*1000 -> 2015508 | Q4: =5969/6.5*1000 -> 918307.69 | R4: =2240.15384615385*1000 -> 2240153.8 | S4: =SMR!T4 -> 511994.89 | T4: =ccs!$J$6*ccs!B22 -> 51.083237 | U4: =SMR!V4 -> 3129772.1 | V4: =ccs!$J$6*ccs!B22 -> 51.083237 | W4: 1245090 | X4: 1562022 | Y4: =OFFSET('H2 turbine'!$B$12,(ROW(Z3)-1)*5,0)*1000 -> 311555.56 | Z4: 69045.9 | AA4: ='hydrogen storage'!D11 -> 2410.947 | AB4: =2.14*1.1*1.0928 -> 2.5724512 | AC4: =AB4*2 -> 5.1449024 | AD4: =3.52*1.1*1.0928 -> 4.2313216 | AE4: =DAC!B21 -> 387.63699
A5: 2035 | B5: =OFFSET(battery!$F$15,(ROW(B4)-1)*5,0)*1000 -> 467109.57 | C5: =OFFSET(battery!$C$15,(ROW(C4)-1)*5,0)*1000 -> 158078 | D5: =OFFSET(Solar!$C$11,(ROW(D4)-1)*5,0)*1000 -> 403424.47 | E5: =OFFSET(Solar!$F$11,(ROW(Solar!E4)-1)*5,0)*1000 -> 411449.37 | F5: =OFFSET(gas!$C$18,(ROW(gas!C4)-1)*5,0)*1000 -> 329504.09 | G5: =ccs!$H$6*ccs!B23 -> 180.59934 | H5: =OFFSET(gas!$F$18,(ROW(gas!E4)-1)*5,0)*1000 -> 363018.57 | I5: =ccs!$H$6*ccs!B23 -> 180.59934 | J5: 1157000 | K5: 2857000 | L5: =OFFSET(coal!$C$20,(ROW(L4)-1)*5,0)*1000 -> 578403.11 | M5: =ccs!$C$6*ccs!B23 -> 188.4609 | N5: =OFFSET(coal!$F$20,(ROW(N4)-1)*5,0)*1000 -> 1062087.1 | O5: =ccs!$F$6*ccs!B23 -> 143.03906 | P5: =OFFSET(nuclear!$B$8,(ROW(P4)-1)*5,0)*1000 -> 1948571.2 | Q5: =5969/6.5*1000 -> 918307.69 | R5: =2240.15384615385*1000 -> 2240153.8 | S5: =SMR!T5 -> 490407.37 | T5: =ccs!$J$6*ccs!B23 -> 46.996578 | U5: =SMR!V5 -> 3040654.4 | V5: =ccs!$J$6*ccs!B23 -> 46.996578 | W5: 1245090 | X5: 1562022 | Y5: =OFFSET('H2 turbine'!$B$12,(ROW(Z4)-1)*5,0)*1000 -> 309944.44 | Z5: 69045.9 | AA5: ='hydrogen storage'!D12 -> 2110.9935 | AB5: =(AB4+AB6)/2 -> 2.4462328 | AC5: =AB5*2 -> 4.8924656 | AD5: =(AD4+AD6)/2 -> 4.026968 | AE5: =DAC!B22 -> 329.49144
A6: 2040 | B6: =OFFSET(battery!$F$15,(ROW(B5)-1)*5,0)*1000 -> 449709.83 | C6: =OFFSET(battery!$C$15,(ROW(C5)-1)*5,0)*1000 -> 142362.74 | D6: =OFFSET(Solar!$C$11,(ROW(D5)-1)*5,0)*1000 -> 371518.84 | E6: =OFFSET(Solar!$F$11,(ROW(Solar!E5)-1)*5,0)*1000 -> 371597.4 | F6: =OFFSET(gas!$C$18,(ROW(gas!C5)-1)*5,0)*1000 -> 314962.84 | G6: =ccs!$H$6*ccs!B24 -> 164.89505 | H6: =OFFSET(gas!$F$18,(ROW(gas!E5)-1)*5,0)*1000 -> 348074.41 | I6: =ccs!$H$6*ccs!B24 -> 164.89505 | J6: 1157000 | K6: 2857000 | L6: =OFFSET(coal!$C$20,(ROW(L5)-1)*5,0)*1000 -> 550665.03 | M6: =ccs!$C$6*ccs!B24 -> 172.07299 | N6: =OFFSET(coal!$F$20,(ROW(N5)-1)*5,0)*1000 -> 1051344.9 | O6: =ccs!$F$6*ccs!B24 -> 130.60088 | P6: =OFFSET(nuclear!$B$8,(ROW(P5)-1)*5,0)*1000 -> 1879782.7 | Q6: =5969/6.5*1000 -> 918307.69 | R6: =2240.15384615385*1000 -> 2240153.8 | S6: =SMR!T6 -> 468765.34 | T6: =ccs!$J$6*ccs!B24 -> 42.909919 | U6: =SMR!V6 -> 2894835.9 | V6: =ccs!$J$6*ccs!B24 -> 42.909919 | W6: 1245090 | X6: 1562022 | Y6: =OFFSET('H2 turbine'!$B$12,(ROW(Z5)-1)*5,0)*1000 -> 308333.33 | Z6: 69045.9 | AA6: ='hydrogen storage'!D13 -> 1811.04 | AB6: =1.93*1.1*1.0928 -> 2.3200144 | AC6: =AB6*2 -> 4.6400288 | AD6: =3.18*1.1*1.0928 -> 3.8226144 | AE6: =DAC!B23 -> 271.34589
A7: 2045 | B7: =OFFSET(battery!$F$15,(ROW(B6)-1)*5,0)*1000 -> 431425.3 | C7: =OFFSET(battery!$C$15,(ROW(C6)-1)*5,0)*1000 -> 126754.17 | D7: =OFFSET(Solar!$C$11,(ROW(D6)-1)*5,0)*1000 -> 339613.21 | E7: =OFFSET(Solar!$F$11,(ROW(Solar!E6)-1)*5,0)*1000 -> 331745.43 | F7: =OFFSET(gas!$C$18,(ROW(gas!C6)-1)*5,0)*1000 -> 300458.21 | G7: =ccs!$H$6*ccs!B25 -> 160.96898 | H7: =OFFSET(gas!$F$18,(ROW(gas!E6)-1)*5,0)*1000 -> 333130.25 | I7: =ccs!$H$6*ccs!B25 -> 160.96898 | J7: 1157000 | K7: 2857000 | L7: =OFFSET(coal!$C$20,(ROW(L6)-1)*5,0)*1000 -> 522948.75 | M7: =ccs!$C$6*ccs!B25 -> 167.97602 | N7: =OFFSET(coal!$F$20,(ROW(N6)-1)*5,0)*1000 -> 1040624.4 | O7: =ccs!$F$6*ccs!B25 -> 127.49133 | P7: =OFFSET(nuclear!$B$8,(ROW(P6)-1)*5,0)*1000 -> 1815208.1 | Q7: =5969/6.5*1000 -> 918307.69 | R7: =2240.15384615385*1000 -> 2240153.8 | S7: =SMR!T7 -> 447177.82 | T7: =ccs!$J$6*ccs!B25 -> 41.888254 | U7: =SMR!V7 -> 2749131.9 | V7: =ccs!$J$6*ccs!B25 -> 41.888254 | W7: 1245090 | X7: 1562022 | Y7: =OFFSET('H2 turbine'!$B$12,(ROW(Z6)-1)*5,0)*1000 -> 306722.22 | Z7: 69045.9 | AA7: ='hydrogen storage'!D14 -> 1629.936 | AB7: =1.93*1.1*1.0928 -> 2.3200144 | AC7: =AB7*2 -> 4.6400288 | AD7: =3.18*1.1*1.0928 -> 3.8226144 | AE7: =DAC!B24 -> 251.96404
A8: 2050 | B8: =OFFSET(battery!$F$15,(ROW(B7)-1)*5,0)*1000 -> 412034.81 | C8: =OFFSET(battery!$C$15,(ROW(C7)-1)*5,0)*1000 -> 111278.96 | D8: =OFFSET(Solar!$C$11,(ROW(D7)-1)*5,0)*1000 -> 307707.58 | E8: =OFFSET(Solar!$F$11,(ROW(Solar!E7)-1)*5,0)*1000 -> 291893.46 | F8: =OFFSET(gas!$C$18,(ROW(gas!C7)-1)*5,0)*1000 -> 285953.58 | G8: =ccs!$H$6*ccs!B26 -> 157.0429 | H8: =OFFSET(gas!$F$18,(ROW(gas!E7)-1)*5,0)*1000 -> 318222.71 | I8: =ccs!$H$6*ccs!B26 -> 157.0429 | J8: 1157000 | K8: 2857000 | L8: =OFFSET(coal!$C$20,(ROW(L7)-1)*5,0)*1000 -> 495210.68 | M8: =ccs!$C$6*ccs!B26 -> 163.87904 | N8: =OFFSET(coal!$F$20,(ROW(N7)-1)*5,0)*1000 -> 1029882.2 | O8: =ccs!$F$6*ccs!B26 -> 124.38179 | P8: =OFFSET(nuclear!$B$8,(ROW(P7)-1)*5,0)*1000 -> 1738729.6 | Q8: =5969/6.5*1000 -> 918307.69 | R8: =2240.15384615385*1000 -> 2240153.8 | S8: =SMR!T8 -> 425590.3 | T8: =ccs!$J$6*ccs!B26 -> 40.86659 | U8: =SMR!V8 -> 2603313.4 | V8: =ccs!$J$6*ccs!B26 -> 40.86659 | W8: 1245090 | X8: 1562022 | Y8: =OFFSET('H2 turbine'!$B$12,(ROW(Z7)-1)*5,0)*1000 -> 305111.11 | Z8: 69045.9 | AA8: ='hydrogen storage'!D15 -> 1448.832 | AB8: =1.93*1.1*1.0928 -> 2.3200144 | AC8: =AB8*2 -> 4.6400288 | AD8: =3.18*1.1*1.0928 -> 3.8226144 | AE8: =DAC!B25 -> 232.58219

Sheet High_cost_electrolyzer
A1: Vintage | B1: Battery_Storage | C1: Battery_Storage_energy | D1: Central_PV | E1: Residential_PV | F1: Gas_Combustion_Turbine | G1: Gas_Combustion_Turbine_CCS | H1: Gas_CCGT | I1: Gas_CCGT_CCS | J1: Wind | K1: Offshore_Wind | L1: Coal | M1: Coal_CCS | N1: Coal_IGCC | O1: Coal_IGCC_CCS | P1: Nuclear | Q1: Hydro_Pumped | R1: Hydro_NonPumped | S1: SMR | T1: SMR_CCS | U1: Gasification | V1: Gasification_CCS | W1: Electrolyzer | X1: Fuel_cell | Y1: Hydrogen_turbine | Z1: Tank | AA1: Salt_cavern | AB1: CCS_storage_oil | AC1: CCS_storage_saline | AD1: CCS_storage_offshore | AE1: DAC
A2: 2020 | B2: =OFFSET(battery!$F$15,(ROW(B1)-1)*5,0)*1000 -> 492307.69 | C2: =OFFSET(battery!$C$15,(ROW(C1)-1)*5,0)*1000 -> 246153.85 | D2: =OFFSET(Solar!$C$11,(ROW(D1)-1)*5,0)*1000 -> 628000 | E2: =OFFSET(Solar!$F$11,(ROW(Solar!E1)-1)*5,0)*1000 -> 746000 | F2: =OFFSET(gas!$C$18,(ROW(gas!C1)-1)*5,0)*1000 -> 367230.77 | G2: =ccs!$H$6*ccs!B20 -> 337.64225 | H2: =OFFSET(gas!$F$18,(ROW(gas!E1)-1)*5,0)*1000 -> 408913.26 | I2: =ccs!$H$6*ccs!B20 -> 337.64225 | J2: =OFFSET(land!$C$12,(ROW(J1)-1)*5,0)*1000 -> 1157000 | K2: =OFFSET(offshore!$K$13,(ROW(K1)-1)*5,0)*1000 -> 2857000 | L2: =OFFSET(coal!$C$20,(ROW(L1)-1)*5,0)*1000 -> 622461.54 | M2: =ccs!$C$6*ccs!B20 -> 352.33994 | N2: =OFFSET(coal!$F$20,(ROW(N1)-1)*5,0)*1000 -> 1089999.5 | O2: =ccs!$F$6*ccs!B20 -> 267.42084 | P2: =OFFSET(nuclear!$B$8,(ROW(P1)-1)*5,0)*1000 -> 2461538.5 | Q2: =5969/6.5*1000 -> 918307.69 | R2: =2240.15384615385*1000 -> 2240153.8 | S2: =SMR!T2 -> 546556.72 | T2: =ccs!$J$6*ccs!B20 -> 87.863168 | U2: =SMR!V2 -> 3272268.8 | V2: =ccs!$J$6*ccs!B20 -> 87.863168 | W2: =OFFSET(Electrolyzer!$C$2,(ROW(W1)-1)*5,0)*1000 -> 1245090 | X2: ='Fuel cell'!C2*1000 -> 1562022 | Y2: =OFFSET('H2 turbine'!$B$12,(ROW(Z1)-1)*5,0)*1000 -> 314777.78 | Z2: ='hydrogen storage'!B9 -> 69045.9 | AA2: ='hydrogen storage'!D9 -> 3610.761 | AB2: =2.36*1.1*1.0928 -> 2.8369088 | AC2: =AB2*2 -> 5.6738176 | AD2: =3.89*1.1*1.0928 -> 4.6760912 | AE2: =DAC!B19 -> 839.88014
A3: 2025 | B3: =OFFSET(battery!$F$15,(ROW(B2)-1)*5,0)*1000 -> 474606.98 | C3: =OFFSET(battery!$C$15,(ROW(C2)-1)*5,0)*1000 -> 219340.56 | D3: =OFFSET(Solar!$C$11,(ROW(D2)-1)*5,0)*1000 -> 607009.58 | E3: =OFFSET(Solar!$F$11,(ROW(Solar!E2)-1)*5,0)*1000 -> 686543.83 | F3: =OFFSET(gas!$C$18,(ROW(gas!C2)-1)*5,0)*1000 -> 358513.34 | G3: =ccs!$H$6*ccs!B21 -> 235.56436 | H3: =OFFSET(gas!$F$18,(ROW(gas!E2)-1)*5,0)*1000 -> 398327.81 | I3: =ccs!$H$6*ccs!B21 -> 235.56436 | J3: =OFFSET(land!$C$12,(ROW(J2)-1)*5,0)*1000 -> 1076641 | K3: =OFFSET(offshore!$K$13,(ROW(K2)-1)*5,0)*1000 -> 2492044 | L3: =OFFSET(coal!$C$20,(ROW(L2)-1)*5,0)*1000 -> 612285.83 | M3: =ccs!$C$6*ccs!B21 -> 245.81856 | N3: =OFFSET(coal!$F$20,(ROW(N2)-1)*5,0)*1000 -> 1083549.8 | O3: =ccs!$F$6*ccs!B21 -> 186.57268 | P3: =OFFSET(nuclear!$B$8,(ROW(P2)-1)*5,0)*1000 -> 2113664.3 | Q3: =5969/6.5*1000 -> 918307.69 | R3: =2240.15384615385*1000 -> 2240153.8 | S3: =SMR!T3 -> 533582.41 | T3: =ccs!$J$6*ccs!B21 -> 61.299884 | U3: =SMR!V3 -> 3218775.3 | V3: =ccs!$J$6*ccs!B21 -> 61.299884 | W3: =OFFSET(Electrolyzer!$C$2,(ROW(W2)-1)*5,0)*1000 -> 905520 | X3: ='Fuel cell'!C3*1000 -> 1443172.5 | Y3: =OFFSET('H2 turbine'!$B$12,(ROW(Z2)-1)*5,0)*1000 -> 313166.67 | Z3: ='hydrogen storage'!B10 -> 61688.55 | AA3: ='hydrogen storage'!D10 -> 3010.854 | AB3: =2.25*1.1*1.0928 -> 2.70468 | AC3: =AB3*2 -> 5.40936 | AD3: =3.7*1.1*1.0928 -> 4.447696 | AE3: =DAC!B20 -> 620.21918
A4: 2030 | B4: =OFFSET(battery!$F$15,(ROW(B3)-1)*5,0)*1000 -> 483790.42 | C4: =OFFSET(battery!$C$15,(ROW(C3)-1)*5,0)*1000 -> 173879.95 | D4: =OFFSET(Solar!$C$11,(ROW(D3)-1)*5,0)*1000 -> 505217.02 | E4: =OFFSET(Solar!$F$11,(ROW(Solar!E3)-1)*5,0)*1000 -> 548996.6 | F4: =OFFSET(gas!$C$18,(ROW(gas!C3)-1)*5,0)*1000 -> 344008.72 | G4: =ccs!$H$6*ccs!B22 -> 196.30363 | H4: =OFFSET(gas!$F$18,(ROW(gas!E3)-1)*5,0)*1000 -> 380673.19 | I4: =ccs!$H$6*ccs!B22 -> 196.30363 | J4: =OFFSET(land!$C$12,(ROW(J3)-1)*5,0)*1000 -> 976192.22 | K4: =OFFSET(offshore!$K$13,(ROW(K3)-1)*5,0)*1000 -> 2290687.3 | L4: =OFFSET(coal!$C$20,(ROW(L3)-1)*5,0)*1000 -> 595355.36 | M4: =ccs!$C$6*ccs!B22 -> 204.8488 | N4: =OFFSET(coal!$F$20,(ROW(N3)-1)*5,0)*1000 -> 1072807.6 | O4: =ccs!$F$6*ccs!B22 -> 155.47723 | P4: =OFFSET(nuclear!$B$8,(ROW(P3)-1)*5,0)*1000 -> 2015508 | Q4: =5969/6.5*1000 -> 918307.69 | R4: =2240.15384615385*1000 -> 2240153.8 | S4: =SMR!T4 -> 511994.89 | T4: =ccs!$J$6*ccs!B22 -> 51.083237 | U4: =SMR!V4 -> 3129772.1 | V4: =ccs!$J$6*ccs!B22 -> 51.083237 | W4: =OFFSET(Electrolyzer!$C$2,(ROW(W3)-1)*5,0)*1000 -> 565950 | X4: ='Fuel cell'!C4*1000 -> 1324323 | Y4: =OFFSET('H2 turbine'!$B$12,(ROW(Z3)-1)*5,0)*1000 -> 311555.56 | Z4: ='hydrogen storage'!B11 -> 54331.2 | AA4: ='hydrogen storage'!D11 -> 2410.947 | AB4: =2.14*1.1*1.0928 -> 2.5724512 | AC4: =AB4*2 -> 5.1449024 | AD4: =3.52*1.1*1.0928 -> 4.2313216 | AE4: =DAC!B21 -> 387.63699
A5: 2035 | B5: =OFFSET(battery!$F$15,(ROW(B4)-1)*5,0)*1000 -> 467109.57 | C5: =OFFSET(battery!$C$15,(ROW(C4)-1)*5,0)*1000 -> 158078 | D5: =OFFSET(Solar!$C$11,(ROW(D4)-1)*5,0)*1000 -> 403424.47 | E5: =OFFSET(Solar!$F$11,(ROW(Solar!E4)-1)*5,0)*1000 -> 411449.37 | F5: =OFFSET(gas!$C$18,(ROW(gas!C4)-1)*5,0)*1000 -> 329504.09 | G5: =ccs!$H$6*ccs!B23 -> 180.59934 | H5: =OFFSET(gas!$F$18,(ROW(gas!E4)-1)*5,0)*1000 -> 363018.57 | I5: =ccs!$H$6*ccs!B23 -> 180.59934 | J5: =OFFSET(land!$C$12,(ROW(J4)-1)*5,0)*1000 -> 928132.19 | K5: =OFFSET(offshore!$K$13,(ROW(K4)-1)*5,0)*1000 -> 2166215.1 | L5: =OFFSET(coal!$C$20,(ROW(L4)-1)*5,0)*1000 -> 578403.11 | M5: =ccs!$C$6*ccs!B23 -> 188.4609 | N5: =OFFSET(coal!$F$20,(ROW(N4)-1)*5,0)*1000 -> 1062087.1 | O5: =ccs!$F$6*ccs!B23 -> 143.03906 | P5: =OFFSET(nuclear!$B$8,(ROW(P4)-1)*5,0)*1000 -> 1948571.2 | Q5: =5969/6.5*1000 -> 918307.69 | R5: =2240.15384615385*1000 -> 2240153.8 | S5: =SMR!T5 -> 490407.37 | T5: =ccs!$J$6*ccs!B23 -> 46.996578 | U5: =SMR!V5 -> 3040654.4 | V5: =ccs!$J$6*ccs!B23 -> 46.996578 | W5: =OFFSET(Electrolyzer!$C$2,(ROW(W4)-1)*5,0)*1000 -> 694166.67 | X5: ='Fuel cell'!C5*1000 -> 1233771 | Y5: =OFFSET('H2 turbine'!$B$12,(ROW(Z4)-1)*5,0)*1000 -> 309944.44 | Z5: ='hydrogen storage'!B12 -> 43578.15 | AA5: ='hydrogen storage'!D12 -> 2110.9935 | AB5: =(AB4+AB6)/2 -> 2.4462328 | AC5: =AB5*2 -> 4.8924656 | AD5: =(AD4+AD6)/2 -> 4.026968 | AE5: =DAC!B22 -> 329.49144
A6: 2040 | B6: =OFFSET(battery!$F$15,(ROW(B5)-1)*5,0)*1000 -> 449709.83 | C6: =OFFSET(battery!$C$15,(ROW(C5)-1)*5,0)*1000 -> 142362.74 | D6: =OFFSET(Solar!$C$11,(ROW(D5)-1)*5,0)*1000 -> 371518.84 | E6: =OFFSET(Solar!$F$11,(ROW(Solar!E5)-1)*5,0)*1000 -> 371597.4 | F6: =OFFSET(gas!$C$18,(ROW(gas!C5)-1)*5,0)*1000 -> 314962.84 | G6: =ccs!$H$6*ccs!B24 -> 164.89505 | H6: =OFFSET(gas!$F$18,(ROW(gas!E5)-1)*5,0)*1000 -> 348074.41 | I6: =ccs!$H$6*ccs!B24 -> 164.89505 | J6: =OFFSET(land!$C$12,(ROW(J5)-1)*5,0)*1000 -> 880072.15 | K6: =OFFSET(offshore!$K$13,(ROW(K5)-1)*5,0)*1000 -> 2075879.5 | L6: =OFFSET(coal!$C$20,(ROW(L5)-1)*5,0)*1000 -> 550665.03 | M6: =ccs!$C$6*ccs!B24 -> 172.07299 | N6: =OFFSET(coal!$F$20,(ROW(N5)-1)*5,0)*1000 -> 1051344.9 | O6: =ccs!$F$6*ccs!B24 -> 130.60088 | P6: =OFFSET(nuclear!$B$8,(ROW(P5)-1)*5,0)*1000 -> 1879782.7 | Q6: =5969/6.5*1000 -> 918307.69 | R6: =2240.15384615385*1000 -> 2240153.8 | S6: =SMR!T6 -> 468765.34 | T6: =ccs!$J$6*ccs!B24 -> 42.909919 | U6: =SMR!V6 -> 2894835.9 | V6: =ccs!$J$6*ccs!B24 -> 42.909919 | W6: =OFFSET(Electrolyzer!$C$2,(ROW(W5)-1)*5,0)*1000 -> 452760 | X6: ='Fuel cell'!C6*1000 -> 1143219 | Y6: =OFFSET('H2 turbine'!$B$12,(ROW(Z5)-1)*5,0)*1000 -> 308333.33 | Z6: ='hydrogen storage'!B13 -> 32825.1 | AA6: ='hydrogen storage'!D13 -> 1811.04 | AB6: =1.93*1.1*1.0928 -> 2.3200144 | AC6: =AB6*2 -> 4.6400288 | AD6: =3.18*1.1*1.0928 -> 3.8226144 | AE6: =DAC!B23 -> 271.34589
A7: 2045 | B7: =OFFSET(battery!$F$15,(ROW(B6)-1)*5,0)*1000 -> 431425.3 | C7: =OFFSET(battery!$C$15,(ROW(C6)-1)*5,0)*1000 -> 126754.17 | D7: =OFFSET(Solar!$C$11,(ROW(D6)-1)*5,0)*1000 -> 339613.21 | E7: =OFFSET(Solar!$F$11,(ROW(Solar!E6)-1)*5,0)*1000 -> 331745.43 | F7: =OFFSET(gas!$C$18,(ROW(gas!C6)-1)*5,0)*1000 -> 300458.21 | G7: =ccs!$H$6*ccs!B25 -> 160.96898 | H7: =OFFSET(gas!$F$18,(ROW(gas!E6)-1)*5,0)*1000 -> 333130.25 | I7: =ccs!$H$6*ccs!B25 -> 160.96898 | J7: =OFFSET(land!$C$12,(ROW(J6)-1)*5,0)*1000 -> 832012.11 | K7: =OFFSET(offshore!$K$13,(ROW(K6)-1)*5,0)*1000 -> 2004930.7 | L7: =OFFSET(coal!$C$20,(ROW(L6)-1)*5,0)*1000 -> 522948.75 | M7: =ccs!$C$6*ccs!B25 -> 167.97602 | N7: =OFFSET(coal!$F$20,(ROW(N6)-1)*5,0)*1000 -> 1040624.4 | O7: =ccs!$F$6*ccs!B25 -> 127.49133 | P7: =OFFSET(nuclear!$B$8,(ROW(P6)-1)*5,0)*1000 -> 1815208.1 | Q7: =5969/6.5*1000 -> 918307.69 | R7: =2240.15384615385*1000 -> 2240153.8 | S7: =SMR!T7 -> 447177.82 | T7: =ccs!$J$6*ccs!B25 -> 41.888254 | U7: =SMR!V7 -> 2749131.9 | V7: =ccs!$J$6*ccs!B25 -> 41.888254 | W7: =OFFSET(Electrolyzer!$C$2,(ROW(W6)-1)*5,0)*1000 -> 639833.33 | X7: ='Fuel cell'!C7*1000 -> 1052667 | Y7: =OFFSET('H2 turbine'!$B$12,(ROW(Z6)-1)*5,0)*1000 -> 306722.22 | Z7: ='hydrogen storage'!B14 -> 28863.45 | AA7: ='hydrogen storage'!D14 -> 1629.936 | AB7: =1.93*1.1*1.0928 -> 2.3200144 | AC7: =AB7*2 -> 4.6400288 | AD7: =3.18*1.1*1.0928 -> 3.8226144 | AE7: =DAC!B24 -> 251.96404
A8: 2050 | B8: =OFFSET(battery!$F$15,(ROW(B7)-1)*5,0)*1000 -> 412034.81 | C8: =OFFSET(battery!$C$15,(ROW(C7)-1)*5,0)*1000 -> 111278.96 | D8: =OFFSET(Solar!$C$11,(ROW(D7)-1)*5,0)*1000 -> 307707.58 | E8: =OFFSET(Solar!$F$11,(ROW(Solar!E7)-1)*5,0)*1000 -> 291893.46 | F8: =OFFSET(gas!$C$18,(ROW(gas!C7)-1)*5,0)*1000 -> 285953.58 | G8: =ccs!$H$6*ccs!B26 -> 157.0429 | H8: =OFFSET(gas!$F$18,(ROW(gas!E7)-1)*5,0)*1000 -> 318222.71 | I8: =ccs!$H$6*ccs!B26 -> 157.0429 | J8: =OFFSET(land!$C$12,(ROW(J7)-1)*5,0)*1000 -> 783952.07 | K8: =OFFSET(offshore!$K$13,(ROW(K7)-1)*5,0)*1000 -> 1946500.3 | L8: =OFFSET(coal!$C$20,(ROW(L7)-1)*5,0)*1000 -> 495210.68 | M8: =ccs!$C$6*ccs!B26 -> 163.87904 | N8: =OFFSET(coal!$F$20,(ROW(N7)-1)*5,0)*1000 -> 1029882.2 | O8: =ccs!$F$6*ccs!B26 -> 124.38179 | P8: =OFFSET(nuclear!$B$8,(ROW(P7)-1)*5,0)*1000 -> 1738729.6 | Q8: =5969/6.5*1000 -> 918307.69 | R8: =2240.15384615385*1000 -> 2240153.8 | S8: =SMR!T8 -> 425590.3 | T8: =ccs!$J$6*ccs!B26 -> 40.86659 | U8: =SMR!V8 -> 2603313.4 | V8: =ccs!$J$6*ccs!B26 -> 40.86659 | W8: =OFFSET(Electrolyzer!$C$2,(ROW(W7)-1)*5,0)*1000 -> 311272.5 | X8: ='Fuel cell'!C8*1000 -> 962115 | Y8: =OFFSET('H2 turbine'!$B$12,(ROW(Z7)-1)*5,0)*1000 -> 305111.11 | Z8: ='hydrogen storage'!B15 -> 24901.8 | AA8: ='hydrogen storage'!D15 -> 1448.832 | AB8: =1.93*1.1*1.0928 -> 2.3200144 | AC8: =AB8*2 -> 4.6400288 | AD8: =3.18*1.1*1.0928 -> 3.8226144 | AE8: =DAC!B25 -> 232.58219

Sheet High_cost_fuel_cell
A1: Vintage | B1: Battery_Storage | C1: Battery_Storage_energy | D1: Central_PV | E1: Residential_PV | F1: Gas_Combustion_Turbine | G1: Gas_Combustion_Turbine_CCS | H1: Gas_CCGT | I1: Gas_CCGT_CCS | J1: Wind | K1: Offshore_Wind | L1: Coal | M1: Coal_CCS | N1: Coal_IGCC | O1: Coal_IGCC_CCS | P1: Nuclear | Q1: Hydro_Pumped | R1: Hydro_NonPumped | S1: SMR | T1: SMR_CCS | U1: Gasification | V1: Gasification_CCS | W1: Electrolyzer | X1: Fuel_cell | Y1: Hydrogen_turbine | Z1: Tank | AA1: Salt_cavern | AB1: CCS_storage_oil | AC1: CCS_storage_saline | AD1: CCS_storage_offshore | AE1: DAC
A2: 2020 | B2: =OFFSET(battery!$F$15,(ROW(B1)-1)*5,0)*1000 -> 492307.69 | C2: =OFFSET(battery!$C$15,(ROW(C1)-1)*5,0)*1000 -> 246153.85 | D2: =OFFSET(Solar!$C$11,(ROW(D1)-1)*5,0)*1000 -> 628000 | E2: =OFFSET(Solar!$F$11,(ROW(Solar!E1)-1)*5,0)*1000 -> 746000 | F2: =OFFSET(gas!$C$18,(ROW(gas!C1)-1)*5,0)*1000 -> 367230.77 | G2: =ccs!$H$6*ccs!B20 -> 337.64225 | H2: =OFFSET(gas!$F$18,(ROW(gas!E1)-1)*5,0)*1000 -> 408913.26 | I2: =ccs!$H$6*ccs!B20 -> 337.64225 | J2: =OFFSET(land!$C$12,(ROW(J1)-1)*5,0)*1000 -> 1157000 | K2: =OFFSET(offshore!$K$13,(ROW(K1)-1)*5,0)*1000 -> 2857000 | L2: =OFFSET(coal!$C$20,(ROW(L1)-1)*5,0)*1000 -> 622461.54 | M2: =ccs!$C$6*ccs!B20 -> 352.33994 | N2: =OFFSET(coal!$F$20,(ROW(N1)-1)*5,0)*1000 -> 1089999.5 | O2: =ccs!$F$6*ccs!B20 -> 267.42084 | P2: =OFFSET(nuclear!$B$8,(ROW(P1)-1)*5,0)*1000 -> 2461538.5 | Q2: =5969/6.5*1000 -> 918307.69 | R2: =2240.15384615385*1000 -> 2240153.8 | S2: =SMR!T2 -> 546556.72 | T2: =ccs!$J$6*ccs!B20 -> 87.863168 | U2: =SMR!V2 -> 3272268.8 | V2: =ccs!$J$6*ccs!B20 -> 87.863168 | W2: =OFFSET(Electrolyzer!$C$2,(ROW(W1)-1)*5,0)*1000 -> 1245090 | X2: ='Fuel cell'!C2*1000 -> 1562022 | Y2: =OFFSET('H2 turbine'!$B$12,(ROW(Z1)-1)*5,0)*1000 -> 314777.78 | Z2: ='hydrogen storage'!B9 -> 69045.9 | AA2: ='hydrogen storage'!D9 -> 3610.761 | AB2: =2.36*1.1*1.0928 -> 2.8369088 | AC2: =AB2*2 -> 5.6738176 | AD2: =3.89*1.1*1.0928 -> 4.6760912 | AE2: =DAC!B19 -> 839.88014
A3: 2025 | B3: =OFFSET(battery!$F$15,(ROW(B2)-1)*5,0)*1000 -> 474606.98 | C3: =OFFSET(battery!$C$15,(ROW(C2)-1)*5,0)*1000 -> 219340.56 | D3: =OFFSET(Solar!$C$11,(ROW(D2)-1)*5,0)*1000 -> 607009.58 | E3: =OFFSET(Solar!$F$11,(ROW(Solar!E2)-1)*5,0)*1000 -> 686543.83 | F3: =OFFSET(gas!$C$18,(ROW(gas!C2)-1)*5,0)*1000 -> 358513.34 | G3: =ccs!$H$6*ccs!B21 -> 235.56436 | H3: =OFFSET(gas!$F$18,(ROW(gas!E2)-1)*5,0)*1000 -> 398327.81 | I3: =ccs!$H$6*ccs!B21 -> 235.56436 | J3: =OFFSET(land!$C$12,(ROW(J2)-1)*5,0)*1000 -> 1076641 | K3: =OFFSET(offshore!$K$13,(ROW(K2)-1)*5,0)*1000 -> 2492044 | L3: =OFFSET(coal!$C$20,(ROW(L2)-1)*5,0)*1000 -> 612285.83 | M3: =ccs!$C$6*ccs!B21 -> 245.81856 | N3: =OFFSET(coal!$F$20,(ROW(N2)-1)*5,0)*1000 -> 1083549.8 | O3: =ccs!$F$6*ccs!B21 -> 186.57268 | P3: =OFFSET(nuclear!$B$8,(ROW(P2)-1)*5,0)*1000 -> 2113664.3 | Q3: =5969/6.5*1000 -> 918307.69 | R3: =2240.15384615385*1000 -> 2240153.8 | S3: =SMR!T3 -> 533582.41 | T3: =ccs!$J$6*ccs!B21 -> 61.299884 | U3: =SMR!V3 -> 3218775.3 | V3: =ccs!$J$6*ccs!B21 -> 61.299884 | W3: 1245090 | X3: 1562022 | Y3: =OFFSET('H2 turbine'!$B$12,(ROW(Z2)-1)*5,0)*1000 -> 313166.67 | Z3: ='hydrogen storage'!B10 -> 61688.55 | AA3: ='hydrogen storage'!D10 -> 3010.854 | AB3: =2.25*1.1*1.0928 -> 2.70468 | AC3: =AB3*2 -> 5.40936 | AD3: =3.7*1.1*1.0928 -> 4.447696 | AE3: =DAC!B20 -> 620.21918
A4: 2030 | B4: =OFFSET(battery!$F$15,(ROW(B3)-1)*5,0)*1000 -> 483790.42 | C4: =OFFSET(battery!$C$15,(ROW(C3)-1)*5,0)*1000 -> 173879.95 | D4: =OFFSET(Solar!$C$11,(ROW(D3)-1)*5,0)*1000 -> 505217.02 | E4: =OFFSET(Solar!$F$11,(ROW(Solar!E3)-1)*5,0)*1000 -> 548996.6 | F4: =OFFSET(gas!$C$18,(ROW(gas!C3)-1)*5,0)*1000 -> 344008.72 | G4: =ccs!$H$6*ccs!B22 -> 196.30363 | H4: =OFFSET(gas!$F$18,(ROW(gas!E3)-1)*5,0)*1000 -> 380673.19 | I4: =ccs!$H$6*ccs!B22 -> 196.30363 | J4: =OFFSET(land!$C$12,(ROW(J3)-1)*5,0)*1000 -> 976192.22 | K4: =OFFSET(offshore!$K$13,(ROW(K3)-1)*5,0)*1000 -> 2290687.3 | L4: =OFFSET(coal!$C$20,(ROW(L3)-1)*5,0)*1000 -> 595355.36 | M4: =ccs!$C$6*ccs!B22 -> 204.8488 | N4: =OFFSET(coal!$F$20,(ROW(N3)-1)*5,0)*1000 -> 1072807.6 | O4: =ccs!$F$6*ccs!B22 -> 155.47723 | P4: =OFFSET(nuclear!$B$8,(ROW(P3)-1)*5,0)*1000 -> 2015508 | Q4: =5969/6.5*1000 -> 918307.69 | R4: =2240.15384615385*1000 -> 2240153.8 | S4: =SMR!T4 -> 511994.89 | T4: =ccs!$J$6*ccs!B22 -> 51.083237 | U4: =SMR!V4 -> 3129772.1 | V4: =ccs!$J$6*ccs!B22 -> 51.083237 | W4: 1245090 | X4: 1562022 | Y4: =OFFSET('H2 turbine'!$B$12,(ROW(Z3)-1)*5,0)*1000 -> 311555.56 | Z4: ='hydrogen storage'!B11 -> 54331.2 | AA4: ='hydrogen storage'!D11 -> 2410.947 | AB4: =2.14*1.1*1.0928 -> 2.5724512 | AC4: =AB4*2 -> 5.1449024 | AD4: =3.52*1.1*1.0928 -> 4.2313216 | AE4: =DAC!B21 -> 387.63699
A5: 2035 | B5: =OFFSET(battery!$F$15,(ROW(B4)-1)*5,0)*1000 -> 467109.57 | C5: =OFFSET(battery!$C$15,(ROW(C4)-1)*5,0)*1000 -> 158078 | D5: =OFFSET(Solar!$C$11,(ROW(D4)-1)*5,0)*1000 -> 403424.47 | E5: =OFFSET(Solar!$F$11,(ROW(Solar!E4)-1)*5,0)*1000 -> 411449.37 | F5: =OFFSET(gas!$C$18,(ROW(gas!C4)-1)*5,0)*1000 -> 329504.09 | G5: =ccs!$H$6*ccs!B23 -> 180.59934 | H5: =OFFSET(gas!$F$18,(ROW(gas!E4)-1)*5,0)*1000 -> 363018.57 | I5: =ccs!$H$6*ccs!B23 -> 180.59934 | J5: =OFFSET(land!$C$12,(ROW(J4)-1)*5,0)*1000 -> 928132.19 | K5: =OFFSET(offshore!$K$13,(ROW(K4)-1)*5,0)*1000 -> 2166215.1 | L5: =OFFSET(coal!$C$20,(ROW(L4)-1)*5,0)*1000 -> 578403.11 | M5: =ccs!$C$6*ccs!B23 -> 188.4609 | N5: =OFFSET(coal!$F$20,(ROW(N4)-1)*5,0)*1000 -> 1062087.1 | O5: =ccs!$F$6*ccs!B23 -> 143.03906 | P5: =OFFSET(nuclear!$B$8,(ROW(P4)-1)*5,0)*1000 -> 1948571.2 | Q5: =5969/6.5*1000 -> 918307.69 | R5: =2240.15384615385*1000 -> 2240153.8 | S5: =SMR!T5 -> 490407.37 | T5: =ccs!$J$6*ccs!B23 -> 46.996578 | U5: =SMR!V5 -> 3040654.4 | V5: =ccs!$J$6*ccs!B23 -> 46.996578 | W5: 1245090 | X5: 1562022 | Y5: =OFFSET('H2 turbine'!$B$12,(ROW(Z4)-1)*5,0)*1000 -> 309944.44 | Z5: ='hydrogen storage'!B12 -> 43578.15 | AA5: ='hydrogen storage'!D12 -> 2110.9935 | AB5: =(AB4+AB6)/2 -> 2.4462328 | AC5: =AB5*2 -> 4.8924656 | AD5: =(AD4+AD6)/2 -> 4.026968 | AE5: =DAC!B22 -> 329.49144
A6: 2040 | B6: =OFFSET(battery!$F$15,(ROW(B5)-1)*5,0)*1000 -> 449709.83 | C6: =OFFSET(battery!$C$15,(ROW(C5)-1)*5,0)*1000 -> 142362.74 | D6: =OFFSET(Solar!$C$11,(ROW(D5)-1)*5,0)*1000 -> 371518.84 | E6: =OFFSET(Solar!$F$11,(ROW(Solar!E5)-1)*5,0)*1000 -> 371597.4 | F6: =OFFSET(gas!$C$18,(ROW(gas!C5)-1)*5,0)*1000 -> 314962.84 | G6: =ccs!$H$6*ccs!B24 -> 164.89505 | H6: =OFFSET(gas!$F$18,(ROW(gas!E5)-1)*5,0)*1000 -> 348074.41 | I6: =ccs!$H$6*ccs!B24 -> 164.89505 | J6: =OFFSET(land!$C$12,(ROW(J5)-1)*5,0)*1000 -> 880072.15 | K6: =OFFSET(offshore!$K$13,(ROW(K5)-1)*5,0)*1000 -> 2075879.5 | L6: =OFFSET(coal!$C$20,(ROW(L5)-1)*5,0)*1000 -> 550665.03 | M6: =ccs!$C$6*ccs!B24 -> 172.07299 | N6: =OFFSET(coal!$F$20,(ROW(N5)-1)*5,0)*1000 -> 1051344.9 | O6: =ccs!$F$6*ccs!B24 -> 130.60088 | P6: =OFFSET(nuclear!$B$8,(ROW(P5)-1)*5,0)*1000 -> 1879782.7 | Q6: =5969/6.5*1000 -> 918307.69 | R6: =2240.15384615385*1000 -> 2240153.8 | S6: =SMR!T6 -> 468765.34 | T6: =ccs!$J$6*ccs!B24 -> 42.909919 | U6: =SMR!V6 -> 2894835.9 | V6: =ccs!$J$6*ccs!B24 -> 42.909919 | W6: 1245090 | X6: 1562022 | Y6: =OFFSET('H2 turbine'!$B$12,(ROW(Z5)-1)*5,0)*1000 -> 308333.33 | Z6: ='hydrogen storage'!B13 -> 32825.1 | AA6: ='hydrogen storage'!D13 -> 1811.04 | AB6: =1.93*1.1*1.0928 -> 2.3200144 | AC6: =AB6*2 -> 4.6400288 | AD6: =3.18*1.1*1.0928 -> 3.8226144 | AE6: =DAC!B23 -> 271.34589
A7: 2045 | B7: =OFFSET(battery!$F$15,(ROW(B6)-1)*5,0)*1000 -> 431425.3 | C7: =OFFSET(battery!$C$15,(ROW(C6)-1)*5,0)*1000 -> 126754.17 | D7: =OFFSET(Solar!$C$11,(ROW(D6)-1)*5,0)*1000 -> 339613.21 | E7: =OFFSET(Solar!$F$11,(ROW(Solar!E6)-1)*5,0)*1000 -> 331745.43 | F7: =OFFSET(gas!$C$18,(ROW(gas!C6)-1)*5,0)*1000 -> 300458.21 | G7: =ccs!$H$6*ccs!B25 -> 160.96898 | H7: =OFFSET(gas!$F$18,(ROW(gas!E6)-1)*5,0)*1000 -> 333130.25 | I7: =ccs!$H$6*ccs!B25 -> 160.96898 | J7: =OFFSET(land!$C$12,(ROW(J6)-1)*5,0)*1000 -> 832012.11 | K7: =OFFSET(offshore!$K$13,(ROW(K6)-1)*5,0)*1000 -> 2004930.7 | L7: =OFFSET(coal!$C$20,(ROW(L6)-1)*5,0)*1000 -> 522948.75 | M7: =ccs!$C$6*ccs!B25 -> 167.97602 | N7: =OFFSET(coal!$F$20,(ROW(N6)-1)*5,0)*1000 -> 1040624.4 | O7: =ccs!$F$6*ccs!B25 -> 127.49133 | P7: =OFFSET(nuclear!$B$8,(ROW(P6)-1)*5,0)*1000 -> 1815208.1 | Q7: =5969/6.5*1000 -> 918307.69 | R7: =2240.15384615385*1000 -> 2240153.8 | S7: =SMR!T7 -> 447177.82 | T7: =ccs!$J$6*ccs!B25 -> 41.888254 | U7: =SMR!V7 -> 2749131.9 | V7: =ccs!$J$6*ccs!B25 -> 41.888254 | W7: 1245090 | X7: 1562022 | Y7: =OFFSET('H2 turbine'!$B$12,(ROW(Z6)-1)*5,0)*1000 -> 306722.22 | Z7: ='hydrogen storage'!B14 -> 28863.45 | AA7: ='hydrogen storage'!D14 -> 1629.936 | AB7: =1.93*1.1*1.0928 -> 2.3200144 | AC7: =AB7*2 -> 4.6400288 | AD7: =3.18*1.1*1.0928 -> 3.8226144 | AE7: =DAC!B24 -> 251.96404
A8: 2050 | B8: =OFFSET(battery!$F$15,(ROW(B7)-1)*5,0)*1000 -> 412034.81 | C8: =OFFSET(battery!$C$15,(ROW(C7)-1)*5,0)*1000 -> 111278.96 | D8: =OFFSET(Solar!$C$11,(ROW(D7)-1)*5,0)*1000 -> 307707.58 | E8: =OFFSET(Solar!$F$11,(ROW(Solar!E7)-1)*5,0)*1000 -> 291893.46 | F8: =OFFSET(gas!$C$18,(ROW(gas!C7)-1)*5,0)*1000 -> 285953.58 | G8: =ccs!$H$6*ccs!B26 -> 157.0429 | H8: =OFFSET(gas!$F$18,(ROW(gas!E7)-1)*5,0)*1000 -> 318222.71 | I8: =ccs!$H$6*ccs!B26 -> 157.0429 | J8: =OFFSET(land!$C$12,(ROW(J7)-1)*5,0)*1000 -> 783952.07 | K8: =OFFSET(offshore!$K$13,(ROW(K7)-1)*5,0)*1000 -> 1946500.3 | L8: =OFFSET(coal!$C$20,(ROW(L7)-1)*5,0)*1000 -> 495210.68 | M8: =ccs!$C$6*ccs!B26 -> 163.87904 | N8: =OFFSET(coal!$F$20,(ROW(N7)-1)*5,0)*1000 -> 1029882.2 | O8: =ccs!$F$6*ccs!B26 -> 124.38179 | P8: =OFFSET(nuclear!$B$8,(ROW(P7)-1)*5,0)*1000 -> 1738729.6 | Q8: =5969/6.5*1000 -> 918307.69 | R8: =2240.15384615385*1000 -> 2240153.8 | S8: =SMR!T8 -> 425590.3 | T8: =ccs!$J$6*ccs!B26 -> 40.86659 | U8: =SMR!V8 -> 2603313.4 | V8: =ccs!$J$6*ccs!B26 -> 40.86659 | W8: 1245090 | X8: 1562022 | Y8: =OFFSET('H2 turbine'!$B$12,(ROW(Z7)-1)*5,0)*1000 -> 305111.11 | Z8: ='hydrogen storage'!B15 -> 24901.8 | AA8: ='hydrogen storage'!D15 -> 1448.832 | AB8: =1.93*1.1*1.0928 -> 2.3200144 | AC8: =AB8*2 -> 4.6400288 | AD8: =3.18*1.1*1.0928 -> 3.8226144 | AE8: =DAC!B25 -> 232.58219

Sheet High_cost_tank
A1: Vintage | B1: Battery_Storage | C1: Battery_Storage_energy | D1: Central_PV | E1: Residential_PV | F1: Gas_Combustion_Turbine | G1: Gas_Combustion_Turbine_CCS | H1: Gas_CCGT | I1: Gas_CCGT_CCS | J1: Wind | K1: Offshore_Wind | L1: Coal | M1: Coal_CCS | N1: Coal_IGCC | O1: Coal_IGCC_CCS | P1: Nuclear | Q1: Hydro_Pumped | R1: Hydro_NonPumped | S1: SMR | T1: SMR_CCS | U1: Gasification | V1: Gasification_CCS | W1: Electrolyzer | X1: Fuel_cell | Y1: Hydrogen_turbine | Z1: Tank | AA1: Salt_cavern | AB1: CCS_storage_oil | AC1: CCS_storage_saline | AD1: CCS_storage_offshore | AE1: DAC
A2: 2020 | B2: =OFFSET(battery!$F$15,(ROW(B1)-1)*5,0)*1000 -> 492307.69 | C2: =OFFSET(battery!$C$15,(ROW(C1)-1)*5,0)*1000 -> 246153.85 | D2: =OFFSET(Solar!$C$11,(ROW(D1)-1)*5,0)*1000 -> 628000 | E2: =OFFSET(Solar!$F$11,(ROW(Solar!E1)-1)*5,0)*1000 -> 746000 | F2: =OFFSET(gas!$C$18,(ROW(gas!C1)-1)*5,0)*1000 -> 367230.77 | G2: =ccs!$H$6*ccs!B20 -> 337.64225 | H2: =OFFSET(gas!$F$18,(ROW(gas!E1)-1)*5,0)*1000 -> 408913.26 | I2: =ccs!$H$6*ccs!B20 -> 337.64225 | J2: =OFFSET(land!$C$12,(ROW(J1)-1)*5,0)*1000 -> 1157000 | K2: =OFFSET(offshore!$K$13,(ROW(K1)-1)*5,0)*1000 -> 2857000 | L2: =OFFSET(coal!$C$20,(ROW(L1)-1)*5,0)*1000 -> 622461.54 | M2: =ccs!$C$6*ccs!B20 -> 352.33994 | N2: =OFFSET(coal!$F$20,(ROW(N1)-1)*5,0)*1000 -> 1089999.5 | O2: =ccs!$F$6*ccs!B20 -> 267.42084 | P2: =OFFSET(nuclear!$B$8,(ROW(P1)-1)*5,0)*1000 -> 2461538.5 | Q2: =5969/6.5*1000 -> 918307.69 | R2: =2240.15384615385*1000 -> 2240153.8 | S2: =SMR!T2 -> 546556.72 | T2: =ccs!$J$6*ccs!B20 -> 87.863168 | U2: =SMR!V2 -> 3272268.8 | V2: =ccs!$J$6*ccs!B20 -> 87.863168 | W2: =OFFSET(Electrolyzer!$C$2,(ROW(W1)-1)*5,0)*1000 -> 1245090 | X2: ='Fuel cell'!C2*1000 -> 1562022 | Y2: =OFFSET('H2 turbine'!$B$12,(ROW(Z1)-1)*5,0)*1000 -> 314777.78 | Z2: ='hydrogen storage'!B9 -> 69045.9 | AA2: ='hydrogen storage'!D9 -> 3610.761 | AB2: =2.36*1.1*1.0928 -> 2.8369088 | AC2: =AB2*2 -> 5.6738176 | AD2: =3.89*1.1*1.0928 -> 4.6760912 | AE2: =DAC!B19 -> 839.88014
A3: 2025 | B3: =OFFSET(battery!$F$15,(ROW(B2)-1)*5,0)*1000 -> 474606.98 | C3: =OFFSET(battery!$C$15,(ROW(C2)-1)*5,0)*1000 -> 219340.56 | D3: =OFFSET(Solar!$C$11,(ROW(D2)-1)*5,0)*1000 -> 607009.58 | E3: =OFFSET(Solar!$F$11,(ROW(Solar!E2)-1)*5,0)*1000 -> 686543.83 | F3: =OFFSET(gas!$C$18,(ROW(gas!C2)-1)*5,0)*1000 -> 358513.34 | G3: =ccs!$H$6*ccs!B21 -> 235.56436 | H3: =OFFSET(gas!$F$18,(ROW(gas!E2)-1)*5,0)*1000 -> 398327.81 | I3: =ccs!$H$6*ccs!B21 -> 235.56436 | J3: =OFFSET(land!$C$12,(ROW(J2)-1)*5,0)*1000 -> 1076641 | K3: =OFFSET(offshore!$K$13,(ROW(K2)-1)*5,0)*1000 -> 2492044 | L3: =OFFSET(coal!$C$20,(ROW(L2)-1)*5,0)*1000 -> 612285.83 | M3: =ccs!$C$6*ccs!B21 -> 245.81856 | N3: =OFFSET(coal!$F$20,(ROW(N2)-1)*5,0)*1000 -> 1083549.8 | O3: =ccs!$F$6*ccs!B21 -> 186.57268 | P3: =OFFSET(nuclear!$B$8,(ROW(P2)-1)*5,0)*1000 -> 2113664.3 | Q3: =5969/6.5*1000 -> 918307.69 | R3: =2240.15384615385*1000 -> 2240153.8 | S3: =SMR!T3 -> 533582.41 | T3: =ccs!$J$6*ccs!B21 -> 61.299884 | U3: =SMR!V3 -> 3218775.3 | V3: =ccs!$J$6*ccs!B21 -> 61.299884 | W3: 1245090 | X3: 1562022 | Y3: =OFFSET('H2 turbine'!$B$12,(ROW(Z2)-1)*5,0)*1000 -> 313166.67 | Z3: 69045.9 | AA3: ='hydrogen storage'!D10 -> 3010.854 | AB3: =2.25*1.1*1.0928 -> 2.70468 | AC3: =AB3*2 -> 5.40936 | AD3: =3.7*1.1*1.0928 -> 4.447696 | AE3: =DAC!B20 -> 620.21918
A4: 2030 | B4: =OFFSET(battery!$F$15,(ROW(B3)-1)*5,0)*1000 -> 483790.42 | C4: =OFFSET(battery!$C$15,(ROW(C3)-1)*5,0)*1000 -> 173879.95 | D4: =OFFSET(Solar!$C$11,(ROW(D3)-1)*5,0)*1000 -> 505217.02 | E4: =OFFSET(Solar!$F$11,(ROW(Solar!E3)-1)*5,0)*1000 -> 548996.6 | F4: =OFFSET(gas!$C$18,(ROW(gas!C3)-1)*5,0)*1000 -> 344008.72 | G4: =ccs!$H$6*ccs!B22 -> 196.30363 | H4: =OFFSET(gas!$F$18,(ROW(gas!E3)-1)*5,0)*1000 -> 380673.19 | I4: =ccs!$H$6*ccs!B22 -> 196.30363 | J4: =OFFSET(land!$C$12,(ROW(J3)-1)*5,0)*1000 -> 976192.22 | K4: =OFFSET(offshore!$K$13,(ROW(K3)-1)*5,0)*1000 -> 2290687.3 | L4: =OFFSET(coal!$C$20,(ROW(L3)-1)*5,0)*1000 -> 595355.36 | M4: =ccs!$C$6*ccs!B22 -> 204.8488 | N4: =OFFSET(coal!$F$20,(ROW(N3)-1)*5,0)*1000 -> 1072807.6 | O4: =ccs!$F$6*ccs!B22 -> 155.47723 | P4: =OFFSET(nuclear!$B$8,(ROW(P3)-1)*5,0)*1000 -> 2015508 | Q4: =5969/6.5*1000 -> 918307.69 | R4: =2240.15384615385*1000 -> 2240153.8 | S4: =SMR!T4 -> 511994.89 | T4: =ccs!$J$6*ccs!B22 -> 51.083237 | U4: =SMR!V4 -> 3129772.1 | V4: =ccs!$J$6*ccs!B22 -> 51.083237 | W4: 1245090 | X4: 1562022 | Y4: =OFFSET('H2 turbine'!$B$12,(ROW(Z3)-1)*5,0)*1000 -> 311555.56 | Z4: 69045.9 | AA4: ='hydrogen storage'!D11 -> 2410.947 | AB4: =2.14*1.1*1.0928 -> 2.5724512 | AC4: =AB4*2 -> 5.1449024 | AD4: =3.52*1.1*1.0928 -> 4.2313216 | AE4: =DAC!B21 -> 387.63699
A5: 2035 | B5: =OFFSET(battery!$F$15,(ROW(B4)-1)*5,0)*1000 -> 467109.57 | C5: =OFFSET(battery!$C$15,(ROW(C4)-1)*5,0)*1000 -> 158078 | D5: =OFFSET(Solar!$C$11,(ROW(D4)-1)*5,0)*1000 -> 403424.47 | E5: =OFFSET(Solar!$F$11,(ROW(Solar!E4)-1)*5,0)*1000 -> 411449.37 | F5: =OFFSET(gas!$C$18,(ROW(gas!C4)-1)*5,0)*1000 -> 329504.09 | G5: =ccs!$H$6*ccs!B23 -> 180.59934 | H5: =OFFSET(gas!$F$18,(ROW(gas!E4)-1)*5,0)*1000 -> 363018.57 | I5: =ccs!$H$6*ccs!B23 -> 180.59934 | J5: =OFFSET(land!$C$12,(ROW(J4)-1)*5,0)*1000 -> 928132.19 | K5: =OFFSET(offshore!$K$13,(ROW(K4)-1)*5,0)*1000 -> 2166215.1 | L5: =OFFSET(coal!$C$20,(ROW(L4)-1)*5,0)*1000 -> 578403.11 | M5: =ccs!$C$6*ccs!B23 -> 188.4609 | N5: =OFFSET(coal!$F$20,(ROW(N4)-1)*5,0)*1000 -> 1062087.1 | O5: =ccs!$F$6*ccs!B23 -> 143.03906 | P5: =OFFSET(nuclear!$B$8,(ROW(P4)-1)*5,0)*1000 -> 1948571.2 | Q5: =5969/6.5*1000 -> 918307.69 | R5: =2240.15384615385*1000 -> 2240153.8 | S5: =SMR!T5 -> 490407.37 | T5: =ccs!$J$6*ccs!B23 -> 46.996578 | U5: =SMR!V5 -> 3040654.4 | V5: =ccs!$J$6*ccs!B23 -> 46.996578 | W5: 1245090 | X5: 1562022 | Y5: =OFFSET('H2 turbine'!$B$12,(ROW(Z4)-1)*5,0)*1000 -> 309944.44 | Z5: 69045.9 | AA5: ='hydrogen storage'!D12 -> 2110.9935 | AB5: =(AB4+AB6)/2 -> 2.4462328 | AC5: =AB5*2 -> 4.8924656 | AD5: =(AD4+AD6)/2 -> 4.026968 | AE5: =DAC!B22 -> 329.49144
A6: 2040 | B6: =OFFSET(battery!$F$15,(ROW(B5)-1)*5,0)*1000 -> 449709.83 | C6: =OFFSET(battery!$C$15,(ROW(C5)-1)*5,0)*1000 -> 142362.74 | D6: =OFFSET(Solar!$C$11,(ROW(D5)-1)*5,0)*1000 -> 371518.84 | E6: =OFFSET(Solar!$F$11,(ROW(Solar!E5)-1)*5,0)*1000 -> 371597.4 | F6: =OFFSET(gas!$C$18,(ROW(gas!C5)-1)*5,0)*1000 -> 314962.84 | G6: =ccs!$H$6*ccs!B24 -> 164.89505 | H6: =OFFSET(gas!$F$18,(ROW(gas!E5)-1)*5,0)*1000 -> 348074.41 | I6: =ccs!$H$6*ccs!B24 -> 164.89505 | J6: =OFFSET(land!$C$12,(ROW(J5)-1)*5,0)*1000 -> 880072.15 | K6: =OFFSET(offshore!$K$13,(ROW(K5)-1)*5,0)*1000 -> 2075879.5 | L6: =OFFSET(coal!$C$20,(ROW(L5)-1)*5,0)*1000 -> 550665.03 | M6: =ccs!$C$6*ccs!B24 -> 172.07299 | N6: =OFFSET(coal!$F$20,(ROW(N5)-1)*5,0)*1000 -> 1051344.9 | O6: =ccs!$F$6*ccs!B24 -> 130.60088 | P6: =OFFSET(nuclear!$B$8,(ROW(P5)-1)*5,0)*1000 -> 1879782.7 | Q6: =5969/6.5*1000 -> 918307.69 | R6: =2240.15384615385*1000 -> 2240153.8 | S6: =SMR!T6 -> 468765.34 | T6: =ccs!$J$6*ccs!B24 -> 42.909919 | U6: =SMR!V6 -> 2894835.9 | V6: =ccs!$J$6*ccs!B24 -> 42.909919 | W6: 1245090 | X6: 1562022 | Y6: =OFFSET('H2 turbine'!$B$12,(ROW(Z5)-1)*5,0)*1000 -> 308333.33 | Z6: 69045.9 | AA6: ='hydrogen storage'!D13 -> 1811.04 | AB6: =1.93*1.1*1.0928 -> 2.3200144 | AC6: =AB6*2 -> 4.6400288 | AD6: =3.18*1.1*1.0928 -> 3.8226144 | AE6: =DAC!B23 -> 271.34589
A7: 2045 | B7: =OFFSET(battery!$F$15,(ROW(B6)-1)*5,0)*1000 -> 431425.3 | C7: =OFFSET(battery!$C$15,(ROW(C6)-1)*5,0)*1000 -> 126754.17 | D7: =OFFSET(Solar!$C$11,(ROW(D6)-1)*5,0)*1000 -> 339613.21 | E7: =OFFSET(Solar!$F$11,(ROW(Solar!E6)-1)*5,0)*1000 -> 331745.43 | F7: =OFFSET(gas!$C$18,(ROW(gas!C6)-1)*5,0)*1000 -> 300458.21 | G7: =ccs!$H$6*ccs!B25 -> 160.96898 | H7: =OFFSET(gas!$F$18,(ROW(gas!E6)-1)*5,0)*1000 -> 333130.25 | I7: =ccs!$H$6*ccs!B25 -> 160.96898 | J7: =OFFSET(land!$C$12,(ROW(J6)-1)*5,0)*1000 -> 832012.11 | K7: =OFFSET(offshore!$K$13,(ROW(K6)-1)*5,0)*1000 -> 2004930.7 | L7: =OFFSET(coal!$C$20,(ROW(L6)-1)*5,0)*1000 -> 522948.75 | M7: =ccs!$C$6*ccs!B25 -> 167.97602 | N7: =OFFSET(coal!$F$20,(ROW(N6)-1)*5,0)*1000 -> 1040624.4 | O7: =ccs!$F$6*ccs!B25 -> 127.49133 | P7: =OFFSET(nuclear!$B$8,(ROW(P6)-1)*5,0)*1000 -> 1815208.1 | Q7: =5969/6.5*1000 -> 918307.69 | R7: =2240.15384615385*1000 -> 2240153.8 | S7: =SMR!T7 -> 447177.82 | T7: =ccs!$J$6*ccs!B25 -> 41.888254 | U7: =SMR!V7 -> 2749131.9 | V7: =ccs!$J$6*ccs!B25 -> 41.888254 | W7: 1245090 | X7: 1562022 | Y7: =OFFSET('H2 turbine'!$B$12,(ROW(Z6)-1)*5,0)*1000 -> 306722.22 | Z7: 69045.9 | AA7: ='hydrogen storage'!D14 -> 1629.936 | AB7: =1.93*1.1*1.0928 -> 2.3200144 | AC7: =AB7*2 -> 4.6400288 | AD7: =3.18*1.1*1.0928 -> 3.8226144 | AE7: =DAC!B24 -> 251.96404
A8: 2050 | B8: =OFFSET(battery!$F$15,(ROW(B7)-1)*5,0)*1000 -> 412034.81 | C8: =OFFSET(battery!$C$15,(ROW(C7)-1)*5,0)*1000 -> 111278.96 | D8: =OFFSET(Solar!$C$11,(ROW(D7)-1)*5,0)*1000 -> 307707.58 | E8: =OFFSET(Solar!$F$11,(ROW(Solar!E7)-1)*5,0)*1000 -> 291893.46 | F8: =OFFSET(gas!$C$18,(ROW(gas!C7)-1)*5,0)*1000 -> 285953.58 | G8: =ccs!$H$6*ccs!B26 -> 157.0429 | H8: =OFFSET(gas!$F$18,(ROW(gas!E7)-1)*5,0)*1000 -> 318222.71 | I8: =ccs!$H$6*ccs!B26 -> 157.0429 | J8: =OFFSET(land!$C$12,(ROW(J7)-1)*5,0)*1000 -> 783952.07 | K8: =OFFSET(offshore!$K$13,(ROW(K7)-1)*5,0)*1000 -> 1946500.3 | L8: =OFFSET(coal!$C$20,(ROW(L7)-1)*5,0)*1000 -> 495210.68 | M8: =ccs!$C$6*ccs!B26 -> 163.87904 | N8: =OFFSET(coal!$F$20,(ROW(N7)-1)*5,0)*1000 -> 1029882.2 | O8: =ccs!$F$6*ccs!B26 -> 124.38179 | P8: =OFFSET(nuclear!$B$8,(ROW(P7)-1)*5,0)*1000 -> 1738729.6 | Q8: =5969/6.5*1000 -> 918307.69 | R8: =2240.15384615385*1000 -> 2240153.8 | S8: =SMR!T8 -> 425590.3 | T8: =ccs!$J$6*ccs!B26 -> 40.86659 | U8: =SMR!V8 -> 2603313.4 | V8: =ccs!$J$6*ccs!B26 -> 40.86659 | W8: 1245090 | X8: 1562022 | Y8: =OFFSET('H2 turbine'!$B$12,(ROW(Z7)-1)*5,0)*1000 -> 305111.11 | Z8: 69045.9 | AA8: ='hydrogen storage'!D15 -> 1448.832 | AB8: =1.93*1.1*1.0928 -> 2.3200144 | AC8: =AB8*2 -> 4.6400288 | AD8: =3.18*1.1*1.0928 -> 3.8226144 | AE8: =DAC!B25 -> 232.58219

Sheet lifetime
A1: Vintage | B1: Battery_Storage | C1: Battery_Storage_energy | D1: Central_PV | E1: Residential_PV | F1: Gas_Combustion_Turbine | G1: Gas_Combustion_Turbine_CCS | H1: Gas_CCGT | I1: Gas_CCGT_CCS | J1: Wind | K1: Offshore_Wind | L1: Coal | M1: Coal_CCS | N1: Coal_IGCC | O1: Coal_IGCC_CCS | P1: Nuclear | Q1: Hydro_Pumped | R1: Hydro_NonPumped | S1: SMR | T1: SMR_CCS | U1: Gasification | V1: Gasification_CCS | W1: Electrolyzer | X1: Fuel_cell | Y1: Hydrogen_turbine | Z1: Tank | AA1: Salt_cavern | AB1: CCS_storage_oil | AC1: CCS_storage_saline | AD1: CCS_storage_offshore | AE1: DAC
A2: 2020 | B2: 15 | C2: 15 | D2: 20 | E2: 20 | F2: 40 | G2: 40 | H2: 40 | I2: 40 | J2: 30 | K2: 30 | L2: 40 | M2: 40 | N2: 40 | O2: 40 | P2: 60 | Q2: 100 | R2: 100 | S2: 40 | T2: 40 | U2: 40 | V2: 40 | W2: 25 | X2: 10 | Y2: 40 | Z2: 25 | AA2: 100 | AB2: 30 | AC2: 30 | AD2: 30 | AE2: 25
A3: 2025 | B3: 15 | C3: 15 | D3: 20 | E3: 20 | F3: 40 | G3: 40 | H3: 40 | I3: 40 | J3: 30 | K3: 30 | L3: 40 | M3: 40 | N3: 40 | O3: 40 | P3: 60 | Q3: 100 | R3: 100 | S3: 40 | T3: 40 | U3: 40 | V3: 40 | W3: 25 | X3: 10 | Y3: 40 | Z3: 25 | AA3: 100 | AB3: 30 | AC3: 30 | AD3: 30 | AE3: 25
A4: 2030 | B4: 15 | C4: 15 | D4: 20 | E4: 20 | F4: 40 | G4: 40 | H4: 40 | I4: 40 | J4: 30 | K4: 30 | L4: 40 | M4: 40 | N4: 40 | O4: 40 | P4: 60 | Q4: 100 | R4: 100 | S4: 40 | T4: 40 | U4: 40 | V4: 40 | W4: 25 | X4: 10 | Y4: 40 | Z4: 25 | AA4: 100 | AB4: 30 | AC4: 30 | AD4: 30 | AE4: 30
A5: 2035 | B5: 15 | C5: 15 | D5: 20 | E5: 20 | F5: 40 | G5: 40 | H5: 40 | I5: 40 | J5: 30 | K5: 30 | L5: 40 | M5: 40 | N5: 40 | O5: 40 | P5: 60 | Q5: 100 | R5: 100 | S5: 40 | T5: 40 | U5: 40 | V5: 40 | W5: 25 | X5: 10 | Y5: 40 | Z5: 25 | AA5: 100 | AB5: 30 | AC5: 30 | AD5: 30 | AE5: 30
A6: 2040 | B6: 15 | C6: 15 | D6: 20 | E6: 20 | F6: 40 | G6: 40 | H6: 40 | I6: 40 | J6: 30 | K6: 30 | L6: 40 | M6: 40 | N6: 40 | O6: 40 | P6: 60 | Q6: 100 | R6: 100 | S6: 40 | T6: 40 | U6: 40 | V6: 40 | W6: 25 | X6: 10 | Y6: 40 | Z6: 25 | AA6: 100 | AB6: 30 | AC6: 30 | AD6: 30 | AE6: 30
A7: 2045 | B7: 15 | C7: 15 | D7: 20 | E7: 20 | F7: 40 | G7: 40 | H7: 40 | I7: 40 | J7: 30 | K7: 30 | L7: 40 | M7: 40 | N7: 40 | O7: 40 | P7: 60 | Q7: 100 | R7: 100 | S7: 40 | T7: 40 | U7: 40 | V7: 40 | W7: 25 | X7: 10 | Y7: 40 | Z7: 25 | AA7: 100 | AB7: 30 | AC7: 30 | AD7: 30 | AE7: 30
A8: 2050 | B8: 15 | C8: 15 | D8: 20 | E8: 20 | F8: 40 | G8: 40 | H8: 40 | I8: 40 | J8: 30 | K8: 30 | L8: 40 | M8: 40 | N8: 40 | O8: 40 | P8: 60 | Q8: 100 | R8: 100 | S8: 40 | T8: 40 | U8: 40 | V8: 40 | W8: 25 | X8: 10 | Y8: 40 | Z8: 25 | AA8: 100 | AB8: 30 | AC8: 30 | AD8: 30 | AE8: 30

Sheet battery
B1: 2021 | C1: 2022 | D1: 2023 | E1: 2024 | F1: 2025 | G1: 2026 | H1: 2027 | I1: 2028 | J1: 2029 | K1: 2030 | L1: 2031 | M1: 2032 | N1: 2033 | O1: 2034 | P1: 2035 | Q1: 2036 | R1: 2037 | S1: 2038 | T1: 2039 | U1: 2040 | V1: 2041 | W1: 2042 | X1: 2043 | Y1: 2044 | Z1: 2045 | AA1: 2046 | AB1: 2047 | AC1: 2048 | AD1: 2049 | AE1: 2050
A2: Energy cost | B2: 322.05105 | C2: 361.97092 | D2: 260.46297 | E2: 245.91307 | F2: 233.48492 | G2: 223.4918 | H2: 213.51187 | I2: 203.50908 | J2: 193.49964 | K2: 183.80197 | L2: 180.61764 | M2: 177.4333 | N2: 173.94617 | O2: 170.76211 | P2: 167.90164 | Q2: 164.413 | R2: 161.22934 | S2: 158.04569 | T2: 154.86207 | U2: 151.3697 | V2: 148.18635 | W2: 145.33341 | X2: 142.15041 | Y2: 138.65616 | Z2: 135.47346 | AA2: 132.29084 | AB2: 129.10829 | AC2: 125.60866 | AD2: 122.42635 | AE2: 119.58492
A3: Energy cost | B3: 322.05105 | C3: 361.97092 | D3: 346.56711 | E3: 329.40172 | F3: 286.97037 | G3: 275.12638 | H3: 263.25963 | I3: 251.36734 | J3: 239.44632 | K3: 227.49277 | L3: 223.34989 | M3: 219.21087 | N3: 215.07587 | O3: 210.94505 | P3: 206.81857 | Q3: 202.6966 | R3: 198.57934 | S3: 194.46698 | T3: 190.35972 | U3: 186.25778 | V3: 182.16141 | W3: 178.07083 | X3: 173.98631 | Y3: 169.90813 | Z3: 165.83658 | AA3: 161.77197 | AB3: 157.71463 | AC3: 153.66491 | AD3: 149.62319 | AE3: 145.58986
A4: Energy cost | B4: 322.05105 | C4: 361.97092 | D4: 375.50474 | E4: 378.03249 | F4: 372.50804 | G4: 356.95913 | H4: 341.43017 | I4: 325.92328 | J4: 310.44086 | K4: 294.9857 | L4: 292.966 | M4: 290.9463 | N4: 288.92659 | O4: 286.90689 | P4: 284.88719 | Q4: 282.86748 | R4: 280.84778 | S4: 278.82808 | T4: 276.80837 | U4: 274.78867 | V4: 272.76897 | W4: 270.74927 | X4: 268.72956 | Y4: 266.70986 | Z4: 264.69016 | AA4: 262.67045 | AB4: 260.65075 | AC4: 258.63105 | AD4: 256.61135 | AE4: 254.59164
A5: Capacity cost | B5: 299.0478 | C5: 336.1163 | D5: 241.55707 | E5: 227.71642 | F5: 215.79816 | G5: 206.96845 | H5: 198.08668 | I5: 189.29517 | J5: 180.52991 | K5: 170.53368 | L5: 167.39041 | M5: 164.24717 | N5: 162.29946 | O5: 159.15511 | P5: 154.73309 | Q5: 152.79132 | R5: 149.64541 | S5: 146.49942 | T5: 143.35334 | U5: 141.42629 | V5: 138.27916 | W5: 133.8274 | X5: 130.67887 | Y5: 128.75926 | Z5: 125.60953 | AA5: 122.45951 | AB5: 119.30918 | AC5: 117.41083 | AD5: 114.25957 | AE5: 109.76237
A6: Capacity cost | B6: 299.0478 | C6: 336.1163 | D6: 329.2339 | E6: 321.16779 | F6: 288.29567 | G6: 289.2129 | H6: 290.21783 | I6: 291.32105 | J6: 292.53495 | K6: 293.87406 | L6: 291.87849 | M6: 289.86804 | N6: 287.84212 | O6: 285.80014 | P6: 283.74143 | Q6: 281.66534 | R6: 279.57114 | S6: 277.45807 | T6: 275.32535 | U6: 273.17212 | V6: 270.9975 | W6: 268.80054 | X6: 266.58025 | Y6: 264.33556 | Z6: 262.06535 | AA6: 259.76842 | AB6: 257.44349 | AC6: 255.08922 | AD6: 252.70416 | AE6: 250.28677
A7: Capacity cost | B7: 299.0478 | C7: 336.1163 | D7: 348.06089 | E7: 351.15774 | F7: 346.81857 | G7: 340.2243 | H7: 333.55112 | I7: 326.79069 | J7: 319.93347 | K7: 312.96846 | L7: 310.82563 | M7: 308.6828 | N7: 306.53997 | O7: 304.39715 | P7: 302.25432 | Q7: 300.11149 | R7: 297.96867 | S7: 295.82584 | T7: 293.68301 | U7: 291.54019 | V7: 289.39736 | W7: 287.25453 | X7: 285.1117 | Y7: 282.96888 | Z7: 280.82605 | AA7: 278.68322 | AB7: 276.5404 | AC7: 274.39757 | AD7: 272.25474 | AE7: 270.11192
A9: updated from 2021
J13: Mw | K13: WMh
B14: Energy cost | C14: Energy cost | D14: Energy cost | E14: Capacity cost | F14: Capacity cost | G14: Capacity cost | I14: China | J14: =3200/6.5 -> 492.30769 | K14: =1600/6.5 -> 246.15385 | M14: Energy cost | N14: Energy cost | O14: Energy cost | P14: Capacity cost | Q14: Capacity cost | R14: Capacity cost
A15: 2020 | B15: =$K$14*M15/M$15 -> 246.15385 | C15: =$K$14*N15/N$15 -> 246.15385 | D15: =$K$14*O15/O$15 -> 246.15385 | E15: =$J$14*P15/P$15 -> 492.30769 | F15: =$J$14*Q15/Q$15 -> 492.30769 | G15: =$J$14*R15/R$15 -> 492.30769 | M15: 322.05105 | N15: 322.05105 | O15: 322.05105 | P15: 299.0478 | Q15: 299.0478 | R15: 299.0478
A16: 2021 | B16: =$K$14*M16/M$15 -> 246.15385 | C16: =$K$14*N16/N$15 -> 246.15385 | D16: =$K$14*O16/O$15 -> 246.15385 | E16: =$J$14*P16/P$15 -> 492.30769 | F16: =$J$14*Q16/Q$15 -> 492.30769 | G16: =$J$14*R16/R$15 -> 492.30769 | M16: 322.05105 | N16: 322.05105 | O16: 322.05105 | P16: 299.0478 | Q16: 299.0478 | R16: 299.0478
A17: 2022 | B17: =$K$14*M17/M$15 -> 276.66587 | C17: =$K$14*N17/N$15 -> 276.66587 | D17: =$K$14*O17/O$15 -> 276.66587 | E17: =$J$14*P17/P$15 -> 553.33175 | F17: =$J$14*Q17/Q$15 -> 553.33175 | G17: =$J$14*R17/R$15 -> 553.33175 | M17: 361.97092 | N17: 361.97092 | O17: 361.97092 | P17: 336.1163 | Q17: 336.1163 | R17: 336.1163
A18: 2023 | B18: =$K$14*M18/M$15 -> 199.08012 | C18: =$K$14*N18/N$15 -> 264.89225 | D18: =$K$14*O18/O$15 -> 287.0102 | E18: =$J$14*P18/P$15 -> 397.66352 | F18: =$J$14*Q18/Q$15 -> 542.00159 | G18: =$J$14*R18/R$15 -> 572.99553 | M18: 260.46297 | N18: 346.56711 | O18: 375.50474 | P18: 241.55707 | Q18: 329.2339 | R18: 348.06089
A19: 2024 | B19: =$K$14*M19/M$15 -> 187.95917 | C19: =$K$14*N19/N$15 -> 251.7722 | D19: =$K$14*O19/O$15 -> 288.94224 | E19: =$J$14*P19/P$15 -> 374.87835 | F19: =$J$14*Q19/Q$15 -> 528.72275 | G19: =$J$14*R19/R$15 -> 578.09372 | M19: 245.91307 | N19: 329.40172 | O19: 378.03249 | P19: 227.71642 | Q19: 321.16779 | R19: 351.15774
A20: 2025 | B20: =$K$14*M20/M$15 -> 178.45994 | C20: =$K$14*N20/N$15 -> 219.34056 | D20: =$K$14*O20/O$15 -> 284.71973 | E20: =$J$14*P20/P$15 -> 355.25791 | F20: =$J$14*Q20/Q$15 -> 474.60698 | G20: =$J$14*R20/R$15 -> 570.95036 | M20: 233.48492 | N20: 286.97037 | O20: 372.50804 | P20: 215.79816 | Q20: 288.29567 | R20: 346.81857
A21: 2026 | B21: =$K$14*M21/M$15 -> 170.82188 | C21: =$K$14*N21/N$15 -> 210.28783 | D21: =$K$14*O21/O$15 -> 272.8352 | E21: =$J$14*P21/P$15 -> 340.72199 | F21: =$J$14*Q21/Q$15 -> 476.11699 | G21: =$J$14*R21/R$15 -> 560.09454 | M21: 223.4918 | N21: 275.12638 | O21: 356.95913 | P21: 206.96845 | Q21: 289.2129 | R21: 340.2243
A22: 2027 | B22: =$K$14*M22/M$15 -> 163.19391 | C22: =$K$14*N22/N$15 -> 201.2177 | D22: =$K$14*O22/O$15 -> 260.96593 | E22: =$J$14*P22/P$15 -> 326.10037 | F22: =$J$14*Q22/Q$15 -> 477.77135 | G22: =$J$14*R22/R$15 -> 549.10881 | M22: 213.51187 | N22: 263.25963 | O22: 341.43017 | P22: 198.08668 | Q22: 290.21783 | R22: 333.55112
A23: 2028 | B23: =$K$14*M23/M$15 -> 155.54846 | C23: =$K$14*N23/N$15 -> 192.12804 | D23: =$K$14*O23/O$15 -> 249.11352 | E23: =$J$14*P23/P$15 -> 311.62734 | F23: =$J$14*Q23/Q$15 -> 479.58753 | G23: =$J$14*R23/R$15 -> 537.97945 | M23: 203.50908 | N23: 251.36734 | O23: 325.92328 | P23: 189.29517 | Q23: 291.32105 | R23: 326.79069
A24: 2029 | B24: =$K$14*M24/M$15 -> 147.89792 | C24: =$K$14*N24/N$15 -> 183.01642 | D24: =$K$14*O24/O$15 -> 237.27981 | E24: =$J$14*P24/P$15 -> 297.19752 | F24: =$J$14*Q24/Q$15 -> 481.5859 | G24: =$J$14*R24/R$15 -> 526.69074 | M24: 193.49964 | N24: 239.44632 | O24: 310.44086 | P24: 180.52991 | Q24: 292.53495 | R24: 319.93347
A25: 2030 | B25: =$K$14*M25/M$15 -> 140.48569 | C25: =$K$14*N25/N$15 -> 173.87995 | D25: =$K$14*O25/O$15 -> 225.46694 | E25: =$J$14*P25/P$15 -> 280.74121 | F25: =$J$14*Q25/Q$15 -> 483.79042 | G25: =$J$14*R25/R$15 -> 515.22458 | M25: 183.80197 | N25: 227.49277 | O25: 294.9857 | P25: 170.53368 | Q25: 293.87406 | R25: 312.96846
A26: 2031 | B26: =$K$14*M26/M$15 -> 138.0518 | C26: =$K$14*N26/N$15 -> 170.71341 | D26: =$K$14*O26/O$15 -> 223.92322 | E26: =$J$14*P26/P$15 -> 275.5666 | F26: =$J$14*Q26/Q$15 -> 480.50521 | G26: =$J$14*R26/R$15 -> 511.69695 | M26: 180.61764 | N26: 223.34989 | O26: 292.966 | P26: 167.39041 | Q26: 291.87849 | R26: 310.82563
... A45: 2050 | B45: =$K$14*M45/M$15 -> 91.402554 | C45: =$K$14*N45/N$15 -> 111.27896 | D45: =$K$14*O45/O$15 -> 194.59248 | E45: =$J$14*P45/P$15 -> 180.6964 | F45: =$J$14*Q45/Q$15 -> 412.03481 | G45: =$J$14*R45/R$15 -> 444.67197 | M45: 119.58492 | N45: 145.58986 | O45: 254.59164 | P45: 109.76237 | Q45: 250.28677 | R45: 270.11192

Sheet Solar
A1: Utility scale | B1: 2021 | C1: 2022 | D1: 2023 | E1: 2024 | F1: 2025 | G1: 2026 | H1: 2027 | I1: 2028 | J1: 2029 | K1: 2030 | L1: 2031 | M1: 2032 | N1: 2033 | O1: 2034 | P1: 2035 | Q1: 2036 | R1: 2037 | S1: 2038 | T1: 2039 | U1: 2040 | V1: 2041 | W1: 2042 | X1: 2043 | Y1: 2044 | Z1: 2045 | AA1: 2046 | AB1: 2047 | AC1: 2048 | AD1: 2049 | AE1: 2050
A2: Utility PV - Class 10 - Advanced | B2: 1290.8063 | C2: 1373.1982 | D2: 1316.219 | E2: 1259.2399 | F2: 1202.2608 | G2: 1145.2817 | H2: 1088.3025 | I2: 1031.3234 | J2: 974.34429 | K2: 917.36516 | L2: 860.38604 | M2: 803.40692 | N2: 746.42779 | O2: 689.44867 | P2: 632.46954 | Q2: 625.04006 | R2: 617.61057 | S2: 610.18108 | T2: 602.75159 | U2: 595.32211 | V2: 587.89262 | W2: 580.46313 | X2: 573.03365 | Y2: 565.60416 | Z2: 558.17467 | AA2: 550.74518 | AB2: 543.3157 | AC2: 535.88621 | AD2: 528.45672 | AE2: 521.02724
A3: Utility PV - Class 10 - Moderate | B3: 1290.8063 | C3: 1373.1982 | D3: 1331.3528 | E3: 1289.5074 | F3: 1247.662 | G3: 1205.8167 | H3: 1163.9713 | I3: 1122.1259 | J3: 1080.2806 | K3: 1038.4352 | L3: 996.58982 | M3: 954.74445 | N3: 912.89908 | O3: 871.05371 | P3: 829.20834 | Q3: 816.09242 | R3: 802.9765 | S3: 789.86058 | T3: 776.74466 | U3: 763.62874 | V3: 750.51282 | W3: 737.3969 | X3: 724.28098 | Y3: 711.16506 | Z3: 698.04914 | AA3: 684.93322 | AB3: 671.8173 | AC3: 658.70138 | AD3: 645.58546 | AE3: 632.46954
A4: Utility PV - Class 10 - Conservative | B4: 1290.8063 | C4: 1373.1982 | D4: 1352.2929 | E4: 1331.3877 | F4: 1310.4824 | G4: 1289.5772 | H4: 1268.672 | I4: 1247.7667 | J4: 1226.8615 | K4: 1205.9562 | L4: 1185.051 | M4: 1164.1458 | N4: 1143.2405 | O4: 1122.3353 | P4: 1101.43 | Q4: 1083.2819 | R4: 1065.1338 | S4: 1046.9857 | T4: 1028.8376 | U4: 1010.6895 | V4: 992.54136 | W4: 974.39325 | X4: 956.24514 | Y4: 938.09702 | Z4: 919.94891 | AA4: 901.8008 | AB4: 883.65268 | AC4: 865.50457 | AD4: 847.35646 | AE4: 829.20834
A5: Residential PV - Class 10 - Advanced | B5: 2858.7294 | C5: 2947.1437 | D5: 2806.4833 | E5: 2665.8229 | F5: 2525.1625 | G5: 2384.502 | H5: 2243.8416 | I5: 2103.1812 | J5: 1962.5208 | K5: 1821.8603 | L5: 1681.1999 | M5: 1540.5395 | N5: 1399.8791 | O5: 1259.2186 | P5: 1118.5582 | Q5: 1102.1522 | R5: 1085.7461 | S5: 1069.3401 | T5: 1052.934 | U5: 1036.528 | V5: 1020.122 | W5: 1003.7159 | X5: 987.30986 | Y5: 970.90382 | Z5: 954.49778 | AA5: 938.09173 | AB5: 921.68569 | AC5: 905.27964 | AD5: 888.8736 | AE5: 872.46755
A6: Residential PV - Class 10 - Moderate | B6: 2858.7294 | C6: 2947.1437 | D6: 2841.7254 | E6: 2736.3071 | F6: 2630.8888 | G6: 2525.4705 | H6: 2420.0522 | I6: 2314.6339 | J6: 2209.2155 | K6: 2103.7972 | L6: 1998.3789 | M6: 1892.9606 | N6: 1787.5423 | O6: 1682.124 | P6: 1576.7057 | Q6: 1546.1625 | R6: 1515.6193 | S6: 1485.0762 | T6: 1454.533 | U6: 1423.9898 | V6: 1393.4467 | W6: 1362.9035 | X6: 1332.3604 | Y6: 1301.8172 | Z6: 1271.274 | AA6: 1240.7309 | AB6: 1210.1877 | AC6: 1179.6445 | AD6: 1149.1014 | AE6: 1118.5582
A7: Residential PV - Class 10 - Conservative | B7: 2858.7294 | C7: 2947.1437 | D7: 2891.8397 | E7: 2836.5356 | F7: 2781.2315 | G7: 2725.9275 | H7: 2670.6234 | I7: 2615.3193 | J7: 2560.0153 | K7: 2504.7112 | L7: 2449.4071 | M7: 2394.1031 | N7: 2338.799 | O7: 2283.4949 | P7: 2228.1909 | Q7: 2184.7585 | R7: 2141.3262 | S7: 2097.8938 | T7: 2054.4615 | U7: 2011.0291 | V7: 1967.5968 | W7: 1924.1644 | X7: 1880.7321 | Y7: 1837.2998 | Z7: 1793.8674 | AA7: 1750.4351 | AB7: 1707.0027 | AC7: 1663.5704 | AD7: 1620.138 | AE7: 1576.7057
M9: Utility | N9: Residential
A10: Utility scale | B10: Utility PV - Class 10 - Advanced | C10: Utility PV - Class 10 - Moderate | D10: Utility PV - Class 10 - Conservative | E10: Residential PV - Class 10 - Advanced | F10: Residential PV - Class 10 - Moderate | G10: Residential PV - Class 10 - Conservative | I10: China | J10: 628 | K10: 746 | M10: Utility scale | N10: Utility PV - Class 10 - Advanced | O10: Utility PV - Class 10 - Moderate | P10: Utility PV - Class 10 - Conservative | Q10: Residential PV - Class 10 - Advanced | R10: Residential PV - Class 10 - Moderate | S10: Residential PV - Class 10 - Conservative
A11: 2020 | B11: =$J$10/N$11*N11 -> 628 | C11: =$J$10/O$11*O11 -> 628 | D11: =$J$10/P$11*P11 -> 628 | E11: =$K$10*Q11/Q$11 -> 746 | F11: =$K$10*R11/R$11 -> 746 | G11: =$K$10*S11/S$11 -> 746 | M11: 2020 | N11: 1290.8063 | O11: 1290.8063 | P11: 1290.8063 | Q11: 2858.7294 | R11: 2858.7294 | S11: 2858.7294
A12: 2021 | B12: =$J$10/N$11*N12 -> 628 | C12: =$J$10/O$11*O12 -> 628 | D12: =$J$10/P$11*P12 -> 628 | E12: =$K$10*Q12/Q$11 -> 746 | F12: =$K$10*R12/R$11 -> 746 | G12: =$K$10*S12/S$11 -> 746 | M12: 2021 | N12: 1290.8063 | O12: 1290.8063 | P12: 1290.8063 | Q12: 2858.7294 | R12: 2858.7294 | S12: 2858.7294
A13: 2022 | B13: =$J$10/N$11*N13 -> 668.08511 | C13: =$J$10/O$11*O13 -> 668.08511 | D13: =$J$10/P$11*P13 -> 668.08511 | E13: =$K$10*Q13/Q$11 -> 769.07216 | F13: =$K$10*R13/R$11 -> 769.07216 | G13: =$K$10*S13/S$11 -> 769.07216 | M13: 2022 | N13: 1373.1982 | O13: 1373.1982 | P13: 1373.1982 | Q13: 2947.1437 | R13: 2947.1437 | S13: 2947.1437
A14: 2023 | B14: =$J$10/N$11*N14 -> 640.36376 | C14: =$J$10/O$11*O14 -> 647.7266 | D14: =$J$10/P$11*P14 -> 657.91434 | E14: =$K$10*Q14/Q$11 -> 732.36611 | F14: =$K$10*R14/R$11 -> 741.56272 | G14: =$K$10*S14/S$11 -> 754.64029 | M14: 2023 | N14: 1316.219 | O14: 1331.3528 | P14: 1352.2929 | Q14: 2806.4833 | R14: 2841.7254 | S14: 2891.8397
A15: 2024 | B15: =$J$10/N$11*N15 -> 612.64241 | C15: =$J$10/O$11*O15 -> 627.36809 | D15: =$J$10/P$11*P15 -> 647.74357 | E15: =$K$10*Q15/Q$11 -> 695.66006 | F15: =$K$10*R15/R$11 -> 714.05327 | G15: =$K$10*S15/S$11 -> 740.20841 | M15: 2024 | N15: 1259.2399 | O15: 1289.5074 | P15: 1331.3877 | Q15: 2665.8229 | R15: 2736.3071 | S15: 2836.5356
A16: 2025 | B16: =$J$10/N$11*N16 -> 584.92106 | C16: =$J$10/O$11*O16 -> 607.00958 | D16: =$J$10/P$11*P16 -> 637.5728 | E16: =$K$10*Q16/Q$11 -> 658.954 | F16: =$K$10*R16/R$11 -> 686.54383 | G16: =$K$10*S16/S$11 -> 725.77653 | M16: 2025 | N16: 1202.2608 | O16: 1247.662 | P16: 1310.4824 | Q16: 2525.1625 | R16: 2630.8888 | S16: 2781.2315
A17: 2026 | B17: =$J$10/N$11*N17 -> 557.19971 | C17: =$J$10/O$11*O17 -> 586.65107 | D17: =$J$10/P$11*P17 -> 627.40204 | E17: =$K$10*Q17/Q$11 -> 622.24795 | F17: =$K$10*R17/R$11 -> 659.03438 | G17: =$K$10*S17/S$11 -> 711.34465 | M17: 2026 | N17: 1145.2817 | O17: 1205.8167 | P17: 1289.5772 | Q17: 2384.502 | R17: 2525.4705 | S17: 2725.9275
A18: 2027 | B18: =$J$10/N$11*N18 -> 529.47837 | C18: =$J$10/O$11*O18 -> 566.29256 | D18: =$J$10/P$11*P18 -> 617.23127 | E18: =$K$10*Q18/Q$11 -> 585.54189 | F18: =$K$10*R18/R$11 -> 631.52494 | G18: =$K$10*S18/S$11 -> 696.91278 | M18: 2027 | N18: 1088.3025 | O18: 1163.9713 | P18: 1268.672 | Q18: 2243.8416 | R18: 2420.0522 | S18: 2670.6234
A19: 2028 | B19: =$J$10/N$11*N19 -> 501.75702 | C19: =$J$10/O$11*O19 -> 545.93404 | D19: =$J$10/P$11*P19 -> 607.0605 | E19: =$K$10*Q19/Q$11 -> 548.83584 | F19: =$K$10*R19/R$11 -> 604.01549 | G19: =$K$10*S19/S$11 -> 682.4809 | M19: 2028 | N19: 1031.3234 | O19: 1122.1259 | P19: 1247.7667 | Q19: 2103.1812 | R19: 2314.6339 | S19: 2615.3193
A20: 2029 | B20: =$J$10/N$11*N20 -> 474.03567 | C20: =$J$10/O$11*O20 -> 525.57553 | D20: =$J$10/P$11*P20 -> 596.88973 | E20: =$K$10*Q20/Q$11 -> 512.12979 | F20: =$K$10*R20/R$11 -> 576.50604 | G20: =$K$10*S20/S$11 -> 668.04902 | M20: 2029 | N20: 974.34429 | O20: 1080.2806 | P20: 1226.8615 | Q20: 1962.5208 | R20: 2209.2155 | S20: 2560.0153
A21: 2030 | B21: =$J$10/N$11*N21 -> 446.31432 | C21: =$J$10/O$11*O21 -> 505.21702 | D21: =$J$10/P$11*P21 -> 586.71897 | E21: =$K$10*Q21/Q$11 -> 475.42373 | F21: =$K$10*R21/R$11 -> 548.9966 | G21: =$K$10*S21/S$11 -> 653.61714 | M21: 2030 | N21: 917.36516 | O21: 1038.4352 | P21: 1205.9562 | Q21: 1821.8603 | R21: 2103.7972 | S21: 2504.7112
A22: 2031 | B22: =$J$10/N$11*N22 -> 418.59297 | C22: =$J$10/O$11*O22 -> 484.85851 | D22: =$J$10/P$11*P22 -> 576.5482 | E22: =$K$10*Q22/Q$11 -> 438.71768 | F22: =$K$10*R22/R$11 -> 521.48715 | G22: =$K$10*S22/S$11 -> 639.18527 | M22: 2031 | N22: 860.38604 | O22: 996.58982 | P22: 1185.051 | Q22: 1681.1999 | R22: 1998.3789 | S22: 2449.4071
... A41: 2050 | B41: =$J$10/N$11*N41 -> 253.48893 | C41: =$J$10/O$11*O41 -> 307.70758 | D41: =$J$10/P$11*P41 -> 403.42447 | E41: =$K$10*Q41/Q$11 -> 227.67485 | F41: =$K$10*R41/R$11 -> 291.89346 | G41: =$K$10*S41/S$11 -> 411.44937 | M41: 2050 | N41: 521.02724 | O41: 632.46954 | P41: 829.20834 | Q41: 872.46755 | R41: 1118.5582 | S41: 1576.7057

Sheet offshore
A1: Offshore wind | B1: 2021 | C1: 2022 | D1: 2023 | E1: 2024 | F1: 2025 | G1: 2026 | H1: 2027 | I1: 2028 | J1: 2029 | K1: 2030 | L1: 2031 | M1: 2032 | N1: 2033 | O1: 2034 | P1: 2035 | Q1: 2036 | R1: 2037 | S1: 2038 | T1: 2039 | U1: 2040 | V1: 2041 | W1: 2042 | X1: 2043 | Y1: 2044 | Z1: 2045 | AA1: 2046 | AB1: 2047 | AC1: 2048 | AD1: 2049 | AE1: 2050
A2: Class 1 - Advanced | B2: 3149.9376 | C2: 3327.1977 | D2: 3068.7789 | E2: 2765.6388 | F2: 2689.1719 | G2: 2624.52 | H2: 2568.516 | I2: 2519.1169 | J2: 2474.928 | K2: 2434.9542 | L2: 2398.4611 | M2: 2364.8906 | N2: 2333.8092 | O2: 2304.8731 | P2: 2277.8052 | Q2: 2252.3788 | R2: 2228.4061 | S2: 2205.73 | T2: 2184.2172 | U2: 2163.7543 | V2: 2144.2434 | W2: 2125.6001 | X2: 2107.7503 | Y2: 2090.6292 | Z2: 2074.1798 | AA2: 2058.3512 | AB2: 2043.0984 | AC2: 2028.3808 | AD2: 2014.1623 | AE2: 2000.41
A3: Class 1 - Moderate | B3: 3396.2021 | C3: 3613.2633 | D3: 3351.3293 | E3: 3034.3653 | F3: 2962.3678 | G3: 2901.4948 | H3: 2848.7642 | I3: 2802.2525 | J3: 2760.6464 | K3: 2723.0091 | L3: 2688.6489 | M3: 2657.0406 | N3: 2627.7759 | O3: 2600.5311 | P3: 2575.0453 | Q3: 2551.105 | R3: 2528.5336 | S3: 2507.1828 | T3: 2486.9275 | U3: 2467.6606 | V3: 2449.2901 | W3: 2431.7365 | X3: 2414.93 | Y3: 2398.8096 | Z3: 2383.3217 | AA3: 2368.4183 | AB3: 2354.0569 | AC3: 2340.1996 | AD3: 2326.8121 | AE3: 2313.8637
A4: Class 1 - Conservative | B4: 3870.7654 | C4: 4185.5618 | D4: 3930.3863 | E4: 3594.7914 | F4: 3539.8787 | G4: 3493.4506 | H4: 3453.2328 | I4: 3417.7582 | J4: 3386.0251 | K4: 3357.319 | L4: 3331.1124 | M4: 3307.0046 | N4: 3284.6843 | O4: 3263.9047 | P4: 3244.4666 | Q4: 3226.2073 | R4: 3208.9919 | S4: 3192.7077 | T4: 3177.2588 | U4: 3162.5639 | V4: 3148.5527 | W4: 3135.1645 | X4: 3122.3461 | Y4: 3110.0511 | Z4: 3098.2384 | AA4: 3086.8715 | AB4: 3075.9181 | AC4: 3065.3491 | AD4: 3055.1384 | AE4: 3045.2625
A12: Offshore wind | B12: Class 1 - Advanced | C12: Class 1 - Moderate | D12: Class 1 - Conservative | G12: China | H12: 2857 | J12: Class 1 - Advanced | K12: Class 1 - Moderate | L12: Class 1 - Conservative
A13: 2020 | B13: 3149.9376 | C13: 3396.2021 | D13: 3870.7654 | J13: =$H$12/B$13*B13 -> 2857 | K13: =$H$12/C$13*C13 -> 2857 | L13: =$H$12/D$13*D13 -> 2857
A14: 2021 | B14: 3149.9376 | C14: 3396.2021 | D14: 3870.7654 | J14: =$H$12/B$13*B14 -> 2857 | K14: =$H$12/C$13*C14 -> 2857 | L14: =$H$12/D$13*D14 -> 2857
A15: 2022 | B15: 3327.1977 | C15: 3613.2633 | D15: 4185.5618 | J15: =$H$12/B$13*B15 -> 3017.7753 | K15: =$H$12/C$13*C15 -> 3039.5992 | L15: =$H$12/D$13*D15 -> 3089.3502
A16: 2023 | B16: 3068.7789 | C16: 3351.3293 | D16: 3930.3863 | J16: =$H$12/B$13*B16 -> 2783.389 | K16: =$H$12/C$13*C16 -> 2819.2515 | L16: =$H$12/D$13*D16 -> 2901.006
A17: 2024 | B17: 2765.6388 | C17: 3034.3653 | D17: 3594.7914 | J17: =$H$12/B$13*B17 -> 2508.4402 | K17: =$H$12/C$13*C17 -> 2552.6107 | L17: =$H$12/D$13*D17 -> 2653.3044
A18: 2025 | B18: 2689.1719 | C18: 2962.3678 | D18: 3539.8787 | J18: =$H$12/B$13*B18 -> 2439.0845 | K18: =$H$12/C$13*C18 -> 2492.044 | L18: =$H$12/D$13*D18 -> 2612.7735
A19: 2026 | B19: 2624.52 | C19: 2901.4948 | D19: 3493.4506 | J19: =$H$12/B$13*B19 -> 2380.4451 | K19: =$H$12/C$13*C19 -> 2440.8355 | L19: =$H$12/D$13*D19 -> 2578.5051
A20: 2027 | B20: 2568.516 | C20: 2848.7642 | D20: 3453.2328 | J20: =$H$12/B$13*B20 -> 2329.6494 | K20: =$H$12/C$13*C20 -> 2396.4767 | L20: =$H$12/D$13*D20 -> 2548.8205
A21: 2028 | B21: 2519.1169 | C21: 2802.2525 | D21: 3417.7582 | J21: =$H$12/B$13*B21 -> 2284.8444 | K21: =$H$12/C$13*C21 -> 2357.3495 | L21: =$H$12/D$13*D21 -> 2522.6368
A22: 2029 | B22: 2474.928 | C22: 2760.6464 | D22: 3386.0251 | J22: =$H$12/B$13*B22 -> 2244.7649 | K22: =$H$12/C$13*C22 -> 2322.3491 | L22: =$H$12/D$13*D22 -> 2499.2147
A23: 2030 | B23: 2434.9542 | C23: 2723.0091 | D23: 3357.319 | J23: =$H$12/B$13*B23 -> 2208.5086 | K23: =$H$12/C$13*C23 -> 2290.6873 | L23: =$H$12/D$13*D23 -> 2478.0268
A24: 2031 | B24: 2398.4611 | C24: 2688.6489 | D24: 3331.1124 | J24: =$H$12/B$13*B24 -> 2175.4092 | K24: =$H$12/C$13*C24 -> 2261.7823 | L24: =$H$12/D$13*D24 -> 2458.6838
... A43: 2050 | B43: 2000.41 | C43: 2313.8637 | D43: 3045.2625 | J43: =$H$12/B$13*B43 -> 1814.3761 | K43: =$H$12/C$13*C43 -> 1946.5003 | L43: =$H$12/D$13*D43 -> 2247.6989

Sheet land
B1: 2021 | C1: 2022 | D1: 2023 | E1: 2024 | F1: 2025 | G1: 2026 | H1: 2027 | I1: 2028 | J1: 2029 | K1: 2030 | L1: 2031 | M1: 2032 | N1: 2033 | O1: 2034 | P1: 2035 | Q1: 2036 | R1: 2037 | S1: 2038 | T1: 2039 | U1: 2040 | V1: 2041 | W1: 2042 | X1: 2043 | Y1: 2044 | Z1: 2045 | AA1: 2046 | AB1: 2047 | AC1: 2048 | AD1: 2049 | AE1: 2050
A2: Class 1 - Advanced | B2: 1363 | C2: 1533.3167 | D2: 1434.0015 | E2: 1273.9566 | F2: 1244.2755 | G2: 1214.5944 | H2: 1184.9133 | I2: 1155.2322 | J2: 1125.5511 | K2: 1095.8699 | L2: 1083.5552 | M2: 1071.2404 | N2: 1058.9257 | O2: 1046.6109 | P2: 1034.2961 | Q2: 1021.9814 | R2: 1009.6666 | S2: 997.35186 | T2: 985.0371 | U2: 972.72234 | V2: 960.40758 | W2: 948.09282 | X2: 935.77806 | Y2: 923.46331 | Z2: 911.14855 | AA2: 898.83379 | AB2: 886.51903 | AC2: 874.20427 | AD2: 861.88951 | AE2: 849.57475
A3: Class 1 - Moderate | B3: 1363 | C3: 1540.2333 | D3: 1447.2333 | E3: 1292 | F3: 1268.3333 | G3: 1244.6667 | H3: 1221 | I3: 1197.3333 | J3: 1173.6667 | K3: 1150 | L3: 1138.6766 | M3: 1127.3532 | N3: 1116.0298 | O3: 1104.7064 | P3: 1093.383 | Q3: 1082.0596 | R3: 1070.7362 | S3: 1059.4129 | T3: 1048.0895 | U3: 1036.7661 | V3: 1025.4427 | W3: 1014.1193 | X3: 1002.7959 | Y3: 991.47249 | Z3: 980.1491 | AA3: 968.8257 | AB3: 957.50231 | AC3: 946.17892 | AD3: 934.85552 | AE3: 923.53213
A4: Class 1 - Conservative | B4: 1363 | C4: 1556.0722 | D4: 1477.5338 | E4: 1333.3189 | F4: 1323.4252 | G4: 1313.5315 | H4: 1303.6378 | I4: 1293.7441 | J4: 1283.8504 | K4: 1273.9566 | L4: 1265.3665 | M4: 1256.7764 | N4: 1248.1862 | O4: 1239.5961 | P4: 1231.0059 | Q4: 1222.4158 | R4: 1213.8257 | S4: 1205.2355 | T4: 1196.6454 | U4: 1188.0552 | V4: 1179.4651 | W4: 1170.875 | X4: 1162.2848 | Y4: 1153.6947 | Z4: 1145.1045 | AA4: 1136.5144 | AB4: 1127.9243 | AC4: 1119.3341 | AD4: 1110.744 | AE4: 1102.1538
B11: Class 1 - Advanced | C11: Class 1 - Moderate | D11: Class 1 - Conservative | H11: China | I11: 1157 | L11: Class 1 - Advanced | M11: Class 1 - Moderate | N11: Class 1 - Conservative
A12: 2020 | B12: =$I$11/L$12*L12 -> 1157 | C12: =$I$11/M$12*M12 -> 1157 | D12: =$I$11/N$12*N12 -> 1157 | K12: 2020 | L12: 1363 | M12: 1363 | N12: 1363
A13: 2021 | B13: =$I$11/L$12*L13 -> 1157 | C13: =$I$11/M$12*M13 -> 1157 | D13: =$I$11/N$12*N13 -> 1157 | K13: 2021 | L13: 1363 | M13: 1363 | N13: 1363
A14: 2022 | B14: =$I$11/L$12*L14 -> 1301.5755 | C14: =$I$11/M$12*M14 -> 1307.4468 | D14: =$I$11/N$12*N14 -> 1320.8918 | K14: 2022 | L14: 1533.3167 | M14: 1540.2333 | N14: 1556.0722
A15: 2023 | B15: =$I$11/L$12*L15 -> 1217.2706 | C15: =$I$11/M$12*M15 -> 1228.5025 | D15: =$I$11/N$12*N15 -> 1254.2235 | K15: 2023 | L15: 1434.0015 | M15: 1447.2333 | N15: 1477.5338
A16: 2024 | B16: =$I$11/L$12*L16 -> 1081.4144 | C16: =$I$11/M$12*M16 -> 1096.7307 | D16: =$I$11/N$12*N16 -> 1131.8048 | K16: 2024 | L16: 1273.9566 | M16: 1292 | N16: 1333.3189
A17: 2025 | B17: =$I$11/L$12*L17 -> 1056.2192 | C17: =$I$11/M$12*M17 -> 1076.641 | D17: =$I$11/N$12*N17 -> 1123.4064 | K17: 2025 | L17: 1244.2755 | M17: 1268.3333 | N17: 1323.4252
A18: 2026 | B18: =$I$11/L$12*L18 -> 1031.024 | C18: =$I$11/M$12*M18 -> 1056.5512 | D18: =$I$11/N$12*N18 -> 1115.008 | K18: 2026 | L18: 1214.5944 | M18: 1244.6667 | N18: 1313.5315
A19: 2027 | B19: =$I$11/L$12*L19 -> 1005.8288 | C19: =$I$11/M$12*M19 -> 1036.4615 | D19: =$I$11/N$12*N19 -> 1106.6096 | K19: 2027 | L19: 1184.9133 | M19: 1221 | N19: 1303.6378
A20: 2028 | B20: =$I$11/L$12*L20 -> 980.63362 | C20: =$I$11/M$12*M20 -> 1016.3717 | D20: =$I$11/N$12*N20 -> 1098.2112 | K20: 2028 | L20: 1155.2322 | M20: 1197.3333 | N20: 1293.7441
A21: 2029 | B21: =$I$11/L$12*L21 -> 955.43843 | C21: =$I$11/M$12*M21 -> 996.28198 | D21: =$I$11/N$12*N21 -> 1089.8128 | K21: 2029 | L21: 1125.5511 | M21: 1173.6667 | N21: 1283.8504
A22: 2030 | B22: =$I$11/L$12*L22 -> 930.24323 | C22: =$I$11/M$12*M22 -> 976.19222 | D22: =$I$11/N$12*N22 -> 1081.4144 | K22: 2030 | L22: 1095.8699 | M22: 1150 | N22: 1273.9566
A23: 2031 | B23: =$I$11/L$12*L23 -> 919.78969 | C23: =$I$11/M$12*M23 -> 966.58022 | D23: =$I$11/N$12*N23 -> 1074.1226 | K23: 2031 | L23: 1083.5552 | M23: 1138.6766 | N23: 1265.3665
... A42: 2050 | B42: =$I$11/L$12*L42 -> 721.1724 | C42: =$I$11/M$12*M42 -> 783.95207 | D42: =$I$11/N$12*N42 -> 935.57739 | K42: 2050 | L42: 849.57475 | M42: 923.53213 | N42: 1102.1538

Sheet nuclear
B1: 2021 | C1: 2022 | D1: 2023 | E1: 2024 | F1: 2025 | G1: 2026 | H1: 2027 | I1: 2028 | J1: 2029 | K1: 2030 | L1: 2031 | M1: 2032 | N1: 2033 | O1: 2034 | P1: 2035 | Q1: 2036 | R1: 2037 | S1: 2038 | T1: 2039 | U1: 2040 | V1: 2041 | W1: 2042 | X1: 2043 | Y1: 2044 | Z1: 2045 | AA1: 2046 | AB1: 2047 | AC1: 2048 | AD1: 2049 | AE1: 2050
A2: Moderate | B2: 9440.1377 | C2: 9125.5788 | D2: 8811.0199 | E2: 8496.461 | F2: 8106.021 | G2: 7955.8391 | H2: 7876.0186 | I2: 7824.1906 | J2: 7776.1801 | K2: 7729.5858 | L2: 7669.694 | M2: 7614.2989 | N2: 7568.6284 | O2: 7520.0573 | P2: 7472.8797 | Q2: 7418.8324 | R2: 7365.2549 | S2: 7316.2214 | T2: 7258.8535 | U2: 7209.0719 | V2: 7164.5079 | W2: 7111.8596 | X2: 7065.3424 | Y2: 7015.0198 | Z2: 6961.4246 | AA2: 6908.9194 | AB2: 6859.1547 | AC2: 6808.0842 | AD2: 6752.1785 | AE2: 6668.1252
A3: Conservative | B3: 9440.1377 | C3: 9125.5788 | D3: 8811.0199 | E3: 8811.0199 | F3: 8811.0199 | G3: 8811.0199 | H3: 8811.0199 | I3: 8811.0199 | J3: 8811.0199 | K3: 8811.0199 | L3: 8811.0199 | M3: 8811.0199 | N3: 8811.0199 | O3: 8811.0199 | P3: 8811.0199 | Q3: 8811.0199 | R3: 8811.0199 | S3: 8811.0199 | T3: 8811.0199 | U3: 8811.0199 | V3: 8811.0199 | W3: 8811.0199 | X3: 8811.0199 | Y3: 8811.0199 | Z3: 8811.0199 | AA3: 8811.0199 | AB3: 8811.0199 | AC3: 8811.0199 | AD3: 8811.0199 | AE3: 8811.0199
A4: Var | B4: 2.3517787 | C4: 2.3517787 | D4: 2.3517787 | E4: 2.3517787 | F4: 2.3517787 | G4: 2.3517787 | H4: 2.3517787 | I4: 2.3517787 | J4: 2.3517787 | K4: 2.3517787 | L4: 2.3517787 | M4: 2.3517787 | N4: 2.3517787 | O4: 2.3517787 | P4: 2.3517787 | Q4: 2.3517787 | R4: 2.3517787 | S4: 2.3517787 | T4: 2.3517787 | U4: 2.3517787 | V4: 2.3517787 | W4: 2.3517787 | X4: 2.3517787 | Y4: 2.3517787 | Z4: 2.3517787 | AA4: 2.3517787 | AB4: 2.3517787 | AC4: 2.3517787 | AD4: 2.3517787 | AE4: 2.3517787
B7: Moderate | C7: Conservative | D7: Var | G7: China | H7: =16000/6.5 -> 2461.5385 | K7: Capital | L7: OM | M7: Var
A8: 2020 | B8: =$H$7*K8/K$8 -> 2461.5385 | C8: =$H$7*L8/L$8 -> 2461.5385 | D8: 2.3517787 | J8: 2020 | K8: 9440.1377 | L8: 9440.1377 | M8: 2.3517787
A9: 2021 | B9: =$H$7*K9/K$8 -> 2461.5385 | C9: =$H$7*L9/L$8 -> 2461.5385 | D9: 2.3517787 | J9: 2021 | K9: 9440.1377 | L9: 9440.1377 | M9: 2.3517787
A10: 2022 | B10: =$H$7*K10/K$8 -> 2379.5165 | C10: =$H$7*L10/L$8 -> 2379.5165 | D10: 2.3517787 | J10: 2022 | K10: 9125.5788 | L10: 9125.5788 | M10: 2.3517787
A11: 2023 | B11: =$H$7*K11/K$8 -> 2297.4945 | C11: =$H$7*L11/L$8 -> 2297.4945 | D11: 2.3517787 | J11: 2023 | K11: 8811.0199 | L11: 8811.0199 | M11: 2.3517787
A12: 2024 | B12: =$H$7*K12/K$8 -> 2215.4725 | C12: =$H$7*L12/L$8 -> 2297.4945 | D12: 2.3517787 | J12: 2024 | K12: 8496.461 | L12: 8811.0199 | M12: 2.3517787
A13: 2025 | B13: =$H$7*K13/K$8 -> 2113.6643 | C13: =$H$7*L13/L$8 -> 2297.4945 | D13: 2.3517787 | J13: 2025 | K13: 8106.021 | L13: 8811.0199 | M13: 2.3517787
A14: 2026 | B14: =$H$7*K14/K$8 -> 2074.504 | C14: =$H$7*L14/L$8 -> 2297.4945 | D14: 2.3517787 | J14: 2026 | K14: 7955.8391 | L14: 8811.0199 | M14: 2.3517787
A15: 2027 | B15: =$H$7*K15/K$8 -> 2053.6906 | C15: =$H$7*L15/L$8 -> 2297.4945 | D15: 2.3517787 | J15: 2027 | K15: 7876.0186 | L15: 8811.0199 | M15: 2.3517787
A16: 2028 | B16: =$H$7*K16/K$8 -> 2040.1764 | C16: =$H$7*L16/L$8 -> 2297.4945 | D16: 2.3517787 | J16: 2028 | K16: 7824.1906 | L16: 8811.0199 | M16: 2.3517787
A17: 2029 | B17: =$H$7*K17/K$8 -> 2027.6575 | C17: =$H$7*L17/L$8 -> 2297.4945 | D17: 2.3517787 | J17: 2029 | K17: 7776.1801 | L17: 8811.0199 | M17: 2.3517787
A18: 2030 | B18: =$H$7*K18/K$8 -> 2015.508 | C18: =$H$7*L18/L$8 -> 2297.4945 | D18: 2.3517787 | J18: 2030 | K18: 7729.5858 | L18: 8811.0199 | M18: 2.3517787
A19: 2031 | B19: =$H$7*K19/K$8 -> 1999.891 | C19: =$H$7*L19/L$8 -> 2297.4945 | D19: 2.3517787 | J19: 2031 | K19: 7669.694 | L19: 8811.0199 | M19: 2.3517787
... A38: 2050 | B38: =$H$7*K38/K$8 -> 1738.7296 | C38: =$H$7*L38/L$8 -> 2297.4945 | D38: 2.3517787 | J38: 2050 | K38: 6668.1252 | L38: 8811.0199 | M38: 2.3517787

Sheet coal
B1: 2021 | C1: 2022 | D1: 2023 | E1: 2024 | F1: 2025 | G1: 2026 | H1: 2027 | I1: 2028 | J1: 2029 | K1: 2030 | L1: 2031 | M1: 2032 | N1: 2033 | O1: 2034 | P1: 2035 | Q1: 2036 | R1: 2037 | S1: 2038 | T1: 2039 | U1: 2040 | V1: 2041 | W1: 2042 | X1: 2043 | Y1: 2044 | Z1: 2045 | AA1: 2046 | AB1: 2047 | AC1: 2048 | AD1: 2049 | AE1: 2050
A2: Coal-new-AvgCF-Advanced | B2: 3549.4085 | C2: 3549.4085 | D2: 3539.3443 | E2: 3529.2802 | F2: 3519.0918 | G2: 3509.0277 | H2: 3498.9636 | I2: 3488.8994 | J2: 3478.8353 | K2: 3468.6469 | L2: 3458.5828 | M2: 3448.5186 | N2: 3438.4545 | O2: 3428.3904 | P2: 3418.202 | Q2: 3383.5367 | R2: 3348.8713 | S2: 3314.206 | T2: 3279.5406 | U2: 3244.751 | V2: 3210.0857 | W2: 3175.4203 | X2: 3140.755 | Y2: 3106.0896 | Z2: 3071.3 | AA2: 3036.6347 | AB2: 3001.9693 | AC2: 2967.304 | AD2: 2932.6386 | AE2: 2897.8491
A3: Coal-new-AvgCF-Moderate | B3: 3549.4085 | C3: 3549.4085 | D3: 3530.1499 | E3: 3510.7672 | F3: 3491.3844 | G3: 3472.1259 | H3: 3452.7431 | I3: 3433.4846 | J3: 3414.1018 | K3: 3394.8433 | L3: 3375.4605 | M3: 3356.202 | N3: 3336.8192 | O3: 3317.5607 | P3: 3298.1779 | Q3: 3266.6188 | R3: 3234.9354 | S3: 3203.252 | T3: 3171.6929 | U3: 3140.0095 | V3: 3108.4504 | W3: 3076.767 | X3: 3045.2078 | Y3: 3013.5245 | Z3: 2981.9653 | AA3: 2950.2819 | AB3: 2918.7228 | AC3: 2887.0394 | AD3: 2855.4803 | AE3: 2823.7969
A4: Coal-new-AvgCF-Conservative | B4: 3549.4085 | C4: 3549.4085 | D4: 3520.8313 | E4: 3492.2541 | F4: 3463.677 | G4: 3435.2241 | H4: 3406.6469 | I4: 3378.0697 | J4: 3349.4925 | K4: 3320.9154 | L4: 3292.3382 | M4: 3263.761 | N4: 3235.3081 | O4: 3206.731 | P4: 3178.1538 | Q4: 3149.5766 | R4: 3120.9995 | S4: 3092.4223 | T4: 3063.8451 | U4: 3035.268 | V4: 3006.815 | W4: 2978.2379 | X4: 2949.6607 | Y4: 2921.0835 | Z4: 2892.5064 | AA4: 2863.9292 | AB4: 2835.352 | AC4: 2806.8991 | AD4: 2778.3219 | AE4: 2749.7448
A5: Coal-IGCC-AvgCF-Advanced | B5: 6215.4097 | C5: 6215.4097 | D5: 6203.1091 | E5: 6190.9328 | F5: 6178.6321 | G5: 6166.4558 | H5: 6154.1552 | I5: 6141.9788 | J5: 6129.6782 | K5: 6117.3776 | L5: 6105.2013 | M5: 6092.9006 | N5: 6080.7243 | O5: 6068.4237 | P5: 6056.2473 | Q5: 6043.9467 | R5: 6031.7704 | S5: 6019.4698 | T5: 6007.2934 | U5: 5994.9928 | V5: 5982.8164 | W5: 5970.5158 | X5: 5958.3395 | Y5: 5946.0389 | Z5: 5933.8625 | AA5: 5921.5619 | AB5: 5909.3855 | AC5: 5897.0849 | AD5: 5884.9086 | AE5: 5872.608
A6: Coal-IGCC-AvgCF-Moderate | B6: 6215.4097 | C6: 6215.4097 | D6: 6203.1091 | E6: 6190.9328 | F6: 6178.6321 | G6: 6166.4558 | H6: 6154.1552 | I6: 6141.9788 | J6: 6129.6782 | K6: 6117.3776 | L6: 6105.2013 | M6: 6092.9006 | N6: 6080.7243 | O6: 6068.4237 | P6: 6056.2473 | Q6: 6043.9467 | R6: 6031.7704 | S6: 6019.4698 | T6: 6007.2934 | U6: 5994.9928 | V6: 5982.8164 | W6: 5970.5158 | X6: 5958.3395 | Y6: 5946.0389 | Z6: 5933.8625 | AA6: 5921.5619 | AB6: 5909.3855 | AC6: 5897.0849 | AD6: 5884.9086 | AE6: 5872.608
A7: Coal-IGCC-AvgCF-Conservative | B7: 6215.4097 | C7: 6215.4097 | D7: 6203.1091 | E7: 6190.9328 | F7: 6178.6321 | G7: 6166.4558 | H7: 6154.1552 | I7: 6141.9788 | J7: 6129.6782 | K7: 6117.3776 | L7: 6105.2013 | M7: 6092.9006 | N7: 6080.7243 | O7: 6068.4237 | P7: 6056.2473 | Q7: 6043.9467 | R7: 6031.7704 | S7: 6019.4698 | T7: 6007.2934 | U7: 5994.9928 | V7: 5982.8164 | W7: 5970.5158 | X7: 5958.3395 | Y7: 5946.0389 | Z7: 5933.8625 | AA7: 5921.5619 | AB7: 5909.3855 | AC7: 5897.0849 | AD7: 5884.9086 | AE7: 5872.608
A8: OM
A9: Coal-new-AvgCF-Advanced | B9: 71.8 | C9: 71.8 | D9: 71.8 | E9: 71.8 | F9: 71 | G9: 70.2 | H9: 69.4 | I9: 68.6 | J9: 67.8 | K9: 67 | L9: 66.2 | M9: 65.3 | N9: 64.5 | O9: 64.5 | P9: 64.5 | Q9: 64.5 | R9: 64.5 | S9: 64.5 | T9: 64.5 | U9: 64.5 | V9: 64.5 | W9: 64.5 | X9: 64.5 | Y9: 64.5 | Z9: 64.5 | AA9: 64.5 | AB9: 64.5 | AC9: 64.5 | AD9: 64.5 | AE9: 64.5
A10: Coal-new-AvgCF-Moderate | B10: 71.8 | C10: 71.8 | D10: 71.8 | E10: 71.8 | F10: 71.4 | G10: 71 | H10: 70.6 | I10: 70.2 | J10: 69.8 | K10: 69.4 | L10: 69 | M10: 68.6 | N10: 68.2 | O10: 68.2 | P10: 68.2 | Q10: 68.2 | R10: 68.2 | S10: 68.2 | T10: 68.2 | U10: 68.2 | V10: 68.2 | W10: 68.2 | X10: 68.2 | Y10: 68.2 | Z10: 68.2 | AA10: 68.2 | AB10: 68.2 | AC10: 68.2 | AD10: 68.2 | AE10: 68.2
A11: Coal-new-AvgCF-Conservative | B11: 71.8 | C11: 71.8 | D11: 71.8 | E11: 71.8 | F11: 71.8 | G11: 71.8 | H11: 71.8 | I11: 71.8 | J11: 71.8 | K11: 71.8 | L11: 71.8 | M11: 71.8 | N11: 71.8 | O11: 71.8 | P11: 71.8 | Q11: 71.8 | R11: 71.8 | S11: 71.8 | T11: 71.8 | U11: 71.8 | V11: 71.8 | W11: 71.8 | X11: 71.8 | Y11: 71.8 | Z11: 71.8 | AA11: 71.8 | AB11: 71.8 | AC11: 71.8 | AD11: 71.8 | AE11: 71.8
A12: Coal-IGCC-AvgCF-Advanced | B12: 142.9 | C12: 142.9 | D12: 142.9 | E12: 142.9 | F12: 142.9 | G12: 142.9 | H12: 142.9 | I12: 142.9 | J12: 142.9 | K12: 142.9 | L12: 142.9 | M12: 142.9 | N12: 142.9 | O12: 142.9 | P12: 142.9 | Q12: 142.9 | R12: 142.9 | S12: 142.9 | T12: 142.9 | U12: 142.9 | V12: 142.9 | W12: 142.9 | X12: 142.9 | Y12: 142.9 | Z12: 142.9 | AA12: 142.9 | AB12: 142.9 | AC12: 142.9 | AD12: 142.9 | AE12: 142.9
A13: Coal-IGCC-AvgCF-Moderate | B13: 142.9 | C13: 142.9 | D13: 142.9 | E13: 142.9 | F13: 142.9 | G13: 142.9 | H13: 142.9 | I13: 142.9 | J13: 142.9 | K13: 142.9 | L13: 142.9 | M13: 142.9 | N13: 142.9 | O13: 142.9 | P13: 142.9 | Q13: 142.9 | R13: 142.9 | S13: 142.9 | T13: 142.9 | U13: 142.9 | V13: 142.9 | W13: 142.9 | X13: 142.9 | Y13: 142.9 | Z13: 142.9 | AA13: 142.9 | AB13: 142.9 | AC13: 142.9 | AD13: 142.9 | AE13: 142.9
A14: Coal-IGCC-AvgCF-Conservative | B14: 142.9 | C14: 142.9 | D14: 142.9 | E14: 142.9 | F14: 142.9 | G14: 142.9 | H14: 142.9 | I14: 142.9 | J14: 142.9 | K14: 142.9 | L14: 142.9 | M14: 142.9 | N14: 142.9 | O14: 142.9 | P14: 142.9 | Q14: 142.9 | R14: 142.9 | S14: 142.9 | T14: 142.9 | U14: 142.9 | V14: 142.9 | W14: 142.9 | X14: 142.9 | Y14: 142.9 | Z14: 142.9 | AA14: 142.9 | AB14: 142.9 | AC14: 142.9 | AD14: 142.9 | AE14: 142.9
A15: VAR
A16: Coal-new-HighCF-Conservative | B16: 7.86 | C16: 7.86 | D16: 7.86 | E16: 7.86 | F16: 7.86 | G16: 7.86 | H16: 7.86 | I16: 7.86 | J16: 7.86 | K16: 7.86 | L16: 7.86 | M16: 7.86 | N16: 7.86 | O16: 7.86 | P16: 7.86 | Q16: 7.86 | R16: 7.86 | S16: 7.86 | T16: 7.86 | U16: 7.86 | V16: 7.86 | W16: 7.86 | X16: 7.86 | Y16: 7.86 | Z16: 7.86 | AA16: 7.86 | AB16: 7.86 | AC16: 7.86 | AD16: 7.86 | AE16: 7.86
A17: Coal-IGCC-AvgCF-Advanced | B17: 14.36 | C17: 14.36 | D17: 14.36 | E17: 14.36 | F17: 14.36 | G17: 14.36 | H17: 14.36 | I17: 14.36 | J17: 14.36 | K17: 14.36 | L17: 14.36 | M17: 14.36 | N17: 14.36 | O17: 14.36 | P17: 14.36 | Q17: 14.36 | R17: 14.36 | S17: 14.36 | T17: 14.36 | U17: 14.36 | V17: 14.36 | W17: 14.36 | X17: 14.36 | Y17: 14.36 | Z17: 14.36 | AA17: 14.36 | AB17: 14.36 | AC17: 14.36 | AD17: 14.36 | AE17: 14.36
B19: Coal-new-AvgCF-Advanced | C19: Coal-new-AvgCF-Moderate | D19: Coal-new-AvgCF-Conservative | E19: Coal-IGCC-AvgCF-Advanced | H19: China | I19: =4046/6.5 -> 622.46154 | J19: =I19*P20/M20 -> 1089.9995
A20: 2020 | B20: =$I$19*L20/L$20 -> 622.46154 | C20: =$I$19*M20/M$20 -> 622.46154 | D20: =$I$19*N20/N$20 -> 622.46154 | E20: =$J$19*O20/O$20 -> 1089.9995 | F20: =$J$19*P20/P$20 -> 1089.9995 | G20: =$J$19*Q20/Q$20 -> 1089.9995 | L20: 3549.4085 | M20: 3549.4085 | N20: 3549.4085 | O20: 6215.4097 | P20: 6215.4097 | Q20: 6215.4097
A21: 2021 | B21: =$I$19*L21/L$20 -> 622.46154 | C21: =$I$19*M21/M$20 -> 622.46154 | D21: =$I$19*N21/N$20 -> 622.46154 | E21: =$J$19*O21/O$20 -> 1089.9995 | F21: =$J$19*P21/P$20 -> 1089.9995 | G21: =$J$19*Q21/Q$20 -> 1089.9995 | L21: 3549.4085 | M21: 3549.4085 | N21: 3549.4085 | O21: 6215.4097 | P21: 6215.4097 | Q21: 6215.4097
A22: 2022 | B22: =$I$19*L22/L$20 -> 622.46154 | C22: =$I$19*M22/M$20 -> 622.46154 | D22: =$I$19*N22/N$20 -> 622.46154 | E22: =$J$19*O22/O$20 -> 1089.9995 | F22: =$J$19*P22/P$20 -> 1089.9995 | G22: =$J$19*Q22/Q$20 -> 1089.9995 | L22: 3549.4085 | M22: 3549.4085 | N22: 3549.4085 | O22: 6215.4097 | P22: 6215.4097 | Q22: 6215.4097
A23: 2023 | B23: =$I$19*L23/L$20 -> 617.44995 | C23: =$I$19*M23/M$20 -> 619.08416 | D23: =$I$19*N23/N$20 -> 620.69659 | E23: =$J$19*O23/O$20 -> 1087.8423 | F23: =$J$19*P23/P$20 -> 1087.8423 | G23: =$J$19*Q23/Q$20 -> 1087.8423 | L23: 3520.8313 | M23: 3530.1499 | N23: 3539.3443 | O23: 6203.1091 | P23: 6203.1091 | Q23: 6203.1091
A24: 2024 | B24: =$I$19*L24/L$20 -> 612.43835 | C24: =$I$19*M24/M$20 -> 615.68499 | D24: =$I$19*N24/N$20 -> 618.93163 | E24: =$J$19*O24/O$20 -> 1085.707 | F24: =$J$19*P24/P$20 -> 1085.707 | G24: =$J$19*Q24/Q$20 -> 1085.707 | L24: 3492.2541 | M24: 3510.7672 | N24: 3529.2802 | O24: 6190.9328 | P24: 6190.9328 | Q24: 6190.9328
A25: 2025 | B25: =$I$19*L25/L$20 -> 607.42676 | C25: =$I$19*M25/M$20 -> 612.28583 | D25: =$I$19*N25/N$20 -> 617.14489 | E25: =$J$19*O25/O$20 -> 1083.5498 | F25: =$J$19*P25/P$20 -> 1083.5498 | G25: =$J$19*Q25/Q$20 -> 1083.5498 | L25: 3463.677 | M25: 3491.3844 | N25: 3519.0918 | O25: 6178.6321 | P25: 6178.6321 | Q25: 6178.6321
A26: 2026 | B26: =$I$19*L26/L$20 -> 602.43696 | C26: =$I$19*M26/M$20 -> 608.90845 | D26: =$I$19*N26/N$20 -> 615.37994 | E26: =$J$19*O26/O$20 -> 1081.4144 | F26: =$J$19*P26/P$20 -> 1081.4144 | G26: =$J$19*Q26/Q$20 -> 1081.4144 | L26: 3435.2241 | M26: 3472.1259 | N26: 3509.0277 | O26: 6166.4558 | P26: 6166.4558 | Q26: 6166.4558
A27: 2027 | B27: =$I$19*L27/L$20 -> 597.42537 | C27: =$I$19*M27/M$20 -> 605.50928 | D27: =$I$19*N27/N$20 -> 613.61499 | E27: =$J$19*O27/O$20 -> 1079.2573 | F27: =$J$19*P27/P$20 -> 1079.2573 | G27: =$J$19*Q27/Q$20 -> 1079.2573 | L27: 3406.6469 | M27: 3452.7431 | N27: 3498.9636 | O27: 6154.1552 | P27: 6154.1552 | Q27: 6154.1552
A28: 2028 | B28: =$I$19*L28/L$20 -> 592.41377 | C28: =$I$19*M28/M$20 -> 602.13191 | D28: =$I$19*N28/N$20 -> 611.85004 | E28: =$J$19*O28/O$20 -> 1077.1219 | F28: =$J$19*P28/P$20 -> 1077.1219 | G28: =$J$19*Q28/Q$20 -> 1077.1219 | L28: 3378.0697 | M28: 3433.4846 | N28: 3488.8994 | O28: 6141.9788 | P28: 6141.9788 | Q28: 6141.9788
A29: 2029 | B29: =$I$19*L29/L$20 -> 587.40218 | C29: =$I$19*M29/M$20 -> 598.73274 | D29: =$I$19*N29/N$20 -> 610.08508 | E29: =$J$19*O29/O$20 -> 1074.9647 | F29: =$J$19*P29/P$20 -> 1074.9647 | G29: =$J$19*Q29/Q$20 -> 1074.9647 | L29: 3349.4925 | M29: 3414.1018 | N29: 3478.8353 | O29: 6129.6782 | P29: 6129.6782 | Q29: 6129.6782
A30: 2030 | B30: =$I$19*L30/L$20 -> 582.39059 | C30: =$I$19*M30/M$20 -> 595.35536 | D30: =$I$19*N30/N$20 -> 608.29834 | E30: =$J$19*O30/O$20 -> 1072.8076 | F30: =$J$19*P30/P$20 -> 1072.8076 | G30: =$J$19*Q30/Q$20 -> 1072.8076 | L30: 3320.9154 | M30: 3394.8433 | N30: 3468.6469 | O30: 6117.3776 | P30: 6117.3776 | Q30: 6117.3776
A31: 2031 | B31: =$I$19*L31/L$20 -> 577.379 | C31: =$I$19*M31/M$20 -> 591.95619 | D31: =$I$19*N31/N$20 -> 606.53339 | E31: =$J$19*O31/O$20 -> 1070.6722 | F31: =$J$19*P31/P$20 -> 1070.6722 | G31: =$J$19*Q31/Q$20 -> 1070.6722 | L31: 3292.3382 | M31: 3375.4605 | N31: 3458.5828 | O31: 6105.2013 | P31: 6105.2013 | Q31: 6105.2013
... A50: 2050 | B50: =$I$19*L50/L$20 -> 482.22412 | C50: =$I$19*M50/M$20 -> 495.21068 | D50: =$I$19*N50/N$20 -> 508.19724 | E50: =$J$19*O50/O$20 -> 1029.8822 | F50: =$J$19*P50/P$20 -> 1029.8822 | G50: =$J$19*Q50/Q$20 -> 1029.8822 | L50: 2749.7448 | M50: 2823.7969 | N50: 2897.8491 | O50: 5872.608 | P50: 5872.608 | Q50: 5872.608

Sheet gas
B1: 2021 | C1: 2022 | D1: 2023 | E1: 2024 | F1: 2025 | G1: 2026 | H1: 2027 | I1: 2028 | J1: 2029 | K1: 2030 | L1: 2031 | M1: 2032 | N1: 2033 | O1: 2034 | P1: 2035 | Q1: 2036 | R1: 2037 | S1: 2038 | T1: 2039 | U1: 2040 | V1: 2041 | W1: 2042 | X1: 2043 | Y1: 2044 | Z1: 2045 | AA1: 2046 | AB1: 2047 | AC1: 2048 | AD1: 2049 | AE1: 2050
A2: Gas-CT-AvgCF - Advanced | B2: 1120.3676 | C2: 1120.3676 | D2: 1111.4279 | E2: 1102.6 | F2: 1093.772 | G2: 1084.9441 | H2: 1076.0044 | I2: 1067.1764 | J2: 1058.3485 | K2: 1049.5205 | L2: 1040.6926 | M2: 1031.7529 | N2: 1022.9249 | O2: 1014.097 | P2: 1005.269 | Q2: 996.32933 | R2: 987.50138 | S2: 978.67343 | T2: 969.84548 | U2: 960.90578 | V2: 952.07783 | W2: 943.24988 | X2: 934.42192 | Y2: 925.59397 | Z2: 916.65427 | AA2: 907.82632 | AB2: 898.99837 | AC2: 890.17042 | AD2: 881.23072 | AE2: 872.40277
A3: Gas-CT-AvgCF - Advanced | B3: 1120.3676 | C3: 1120.3676 | D3: 1111.4279 | E3: 1102.6 | F3: 1093.772 | G3: 1084.9441 | H3: 1076.0044 | I3: 1067.1764 | J3: 1058.3485 | K3: 1049.5205 | L3: 1040.6926 | M3: 1031.7529 | N3: 1022.9249 | O3: 1014.097 | P3: 1005.269 | Q3: 996.32933 | R3: 987.50138 | S3: 978.67343 | T3: 969.84548 | U3: 960.90578 | V3: 952.07783 | W3: 943.24988 | X3: 934.42192 | Y3: 925.59397 | Z3: 916.65427 | AA3: 907.82632 | AB3: 898.99837 | AC3: 890.17042 | AD3: 881.23072 | AE3: 872.40277
A4: Gas-CT-AvgCF - Advanced | B4: 1120.3676 | C4: 1120.3676 | D4: 1111.4279 | E4: 1102.6 | F4: 1093.772 | G4: 1084.9441 | H4: 1076.0044 | I4: 1067.1764 | J4: 1058.3485 | K4: 1049.5205 | L4: 1040.6926 | M4: 1031.7529 | N4: 1022.9249 | O4: 1014.097 | P4: 1005.269 | Q4: 996.32933 | R4: 987.50138 | S4: 978.67343 | T4: 969.84548 | U4: 960.90578 | V4: 952.07783 | W4: 943.24988 | X4: 934.42192 | Y4: 925.59397 | Z4: 916.65427 | AA4: 907.82632 | AB4: 898.99837 | AC4: 890.17042 | AD4: 881.23072 | AE4: 872.40277
A5: Gas-CC-HighCF - Conservative | B5: 1247.5348 | C5: 1247.5348 | D5: 1234.237 | E5: 1221.051 | F5: 1207.7532 | G5: 1194.4554 | H5: 1181.2693 | I5: 1167.9715 | J5: 1154.7855 | K5: 1141.4877 | L5: 1128.1899 | M5: 1115.0038 | N5: 1101.706 | O5: 1088.4082 | P5: 1075.2222 | Q5: 1065.2768 | R5: 1055.3313 | S5: 1045.3859 | T5: 1035.4405 | U5: 1025.4951 | V5: 1015.5497 | W5: 1005.6043 | X5: 995.65885 | Y5: 985.71344 | Z5: 975.87977 | AA5: 965.93436 | AB5: 955.98895 | AC5: 946.04353 | AD5: 936.09812 | AE5: 926.1527
A6: Gas-CC-HighCF - Conservative | B6: 1247.5348 | C6: 1247.5348 | D6: 1236.8072 | E6: 1225.9678 | F6: 1215.2402 | G6: 1204.4008 | H6: 1193.6732 | I6: 1182.9455 | J6: 1172.1061 | K6: 1161.3785 | L6: 1150.5391 | M6: 1139.8115 | N6: 1129.0838 | O6: 1118.2445 | P6: 1107.5168 | Q6: 1098.3536 | R6: 1089.3022 | S6: 1080.139 | T6: 1071.0876 | U6: 1061.9244 | V6: 1052.8729 | W6: 1043.7097 | X6: 1034.6583 | Y6: 1025.4951 | Z6: 1016.3319 | AA6: 1007.2805 | AB6: 998.11727 | AC6: 989.06583 | AD6: 979.90264 | AE6: 970.85119
A7: Gas-CC-HighCF - Conservative | B7: 1247.5348 | C7: 1247.5348 | D7: 1239.2656 | E7: 1230.9964 | F7: 1222.6154 | G7: 1214.3462 | H7: 1206.077 | I7: 1197.8078 | J7: 1189.5386 | K7: 1181.2693 | L7: 1173.0001 | M7: 1164.6191 | N7: 1156.3499 | O7: 1148.0807 | P7: 1139.8115 | Q7: 1131.5423 | R7: 1123.273 | S7: 1114.8921 | T7: 1106.6229 | U7: 1098.3536 | V7: 1090.0844 | W7: 1081.8152 | X7: 1073.546 | Y7: 1065.2768 | Z7: 1056.8958 | AA7: 1048.6266 | AB7: 1040.3573 | AC7: 1032.0881 | AD7: 1023.8189 | AE7: 1015.5497
A12: Var
A13: Gas-CT-AvgCF - Advanced | B13: 4.94 | C13: 4.94 | D13: 4.94 | E13: 4.94 | F13: 4.94 | G13: 4.94 | H13: 4.94 | I13: 4.94 | J13: 4.94 | K13: 4.94 | L13: 4.94 | M13: 4.94 | N13: 4.94 | O13: 4.94 | P13: 4.94 | Q13: 4.94 | R13: 4.94 | S13: 4.94 | T13: 4.94 | U13: 4.94 | V13: 4.94 | W13: 4.94 | X13: 4.94 | Y13: 4.94 | Z13: 4.94 | AA13: 4.94 | AB13: 4.94 | AC13: 4.94 | AD13: 4.94 | AE13: 4.94
A14: Gas-CT-AvgCF - Moderate | B14: 2 | C14: 2 | D14: 2 | E14: 2 | F14: 2 | G14: 2 | H14: 2 | I14: 2 | J14: 2 | K14: 2 | L14: 2 | M14: 2 | N14: 2 | O14: 2 | P14: 2 | Q14: 2 | R14: 2 | S14: 2 | T14: 2 | U14: 2 | V14: 2 | W14: 2 | X14: 2 | Y14: 2 | Z14: 2 | AA14: 2 | AB14: 2 | AC14: 2 | AD14: 2 | AE14: 2
B17: CT-convservative | C17: CT-moderate | D17: CT-convservative | E17: CCGT-convservative | F17: CCGT-moderate | G17: CCGT-convservative | H17: China | I17: =2387/6.5 -> 367.23077 | J17: =I17*O18/L18 -> 408.91326
A18: 2020 | B18: =$I$17*K18/K$18 -> 367.23077 | C18: =$I$17*L18/L$18 -> 367.23077 | D18: =$I$17*M18/M$18 -> 367.23077 | E18: =$J$17*N18/N$18 -> 408.91326 | F18: =$J$17*O18/O$18 -> 408.91326 | G18: =$J$17*P18/P$18 -> 408.91326 | K18: 1120.3676 | L18: 1120.3676 | M18: 1120.3676 | N18: 1247.5348 | O18: 1247.5348 | P18: 1247.5348
A19: 2021 | B19: =$I$17*K19/K$18 -> 367.23077 | C19: =$I$17*L19/L$18 -> 367.23077 | D19: =$I$17*M19/M$18 -> 367.23077 | E19: =$J$17*N19/N$18 -> 408.91326 | F19: =$J$17*O19/O$18 -> 408.91326 | G19: =$J$17*P19/P$18 -> 408.91326 | K19: 1120.3676 | L19: 1120.3676 | M19: 1120.3676 | N19: 1247.5348 | O19: 1247.5348 | P19: 1247.5348
A20: 2022 | B20: =$I$17*K20/K$18 -> 367.23077 | C20: =$I$17*L20/L$18 -> 367.23077 | D20: =$I$17*M20/M$18 -> 367.23077 | E20: =$J$17*N20/N$18 -> 408.91326 | F20: =$J$17*O20/O$18 -> 408.91326 | G20: =$J$17*P20/P$18 -> 408.91326 | K20: 1120.3676 | L20: 1120.3676 | M20: 1120.3676 | N20: 1247.5348 | O20: 1247.5348 | P20: 1247.5348
A21: 2023 | B21: =$I$17*K21/K$18 -> 364.30054 | C21: =$I$17*L21/L$18 -> 364.30054 | D21: =$I$17*M21/M$18 -> 364.30054 | E21: =$J$17*N21/N$18 -> 404.55454 | F21: =$J$17*O21/O$18 -> 405.39698 | G21: =$J$17*P21/P$18 -> 406.2028 | K21: 1111.4279 | L21: 1111.4279 | M21: 1111.4279 | N21: 1234.237 | O21: 1236.8072 | P21: 1239.2656
A22: 2024 | B22: =$I$17*K22/K$18 -> 361.40694 | C22: =$I$17*L22/L$18 -> 361.40694 | D22: =$I$17*M22/M$18 -> 361.40694 | E22: =$J$17*N22/N$18 -> 400.23246 | F22: =$J$17*O22/O$18 -> 401.84408 | G22: =$J$17*P22/P$18 -> 403.49234 | K22: 1102.6 | L22: 1102.6 | M22: 1102.6 | N22: 1221.051 | O22: 1225.9678 | P22: 1230.9964
A23: 2025 | B23: =$I$17*K23/K$18 -> 358.51334 | C23: =$I$17*L23/L$18 -> 358.51334 | D23: =$I$17*M23/M$18 -> 358.51334 | E23: =$J$17*N23/N$18 -> 395.87374 | F23: =$J$17*O23/O$18 -> 398.32781 | G23: =$J$17*P23/P$18 -> 400.74525 | K23: 1093.772 | L23: 1093.772 | M23: 1093.772 | N23: 1207.7532 | O23: 1215.2402 | P23: 1222.6154
A24: 2026 | B24: =$I$17*K24/K$18 -> 355.61974 | C24: =$I$17*L24/L$18 -> 355.61974 | D24: =$I$17*M24/M$18 -> 355.61974 | E24: =$J$17*N24/N$18 -> 391.51503 | F24: =$J$17*O24/O$18 -> 394.77491 | G24: =$J$17*P24/P$18 -> 398.03479 | K24: 1084.9441 | L24: 1084.9441 | M24: 1084.9441 | N24: 1194.4554 | O24: 1204.4008 | P24: 1214.3462
A25: 2027 | B25: =$I$17*K25/K$18 -> 352.68951 | C25: =$I$17*L25/L$18 -> 352.68951 | D25: =$I$17*M25/M$18 -> 352.68951 | E25: =$J$17*N25/N$18 -> 387.19294 | F25: =$J$17*O25/O$18 -> 391.25864 | G25: =$J$17*P25/P$18 -> 395.32433 | K25: 1076.0044 | L25: 1076.0044 | M25: 1076.0044 | N25: 1181.2693 | O25: 1193.6732 | P25: 1206.077
A26: 2028 | B26: =$I$17*K26/K$18 -> 349.79592 | C26: =$I$17*L26/L$18 -> 349.79592 | D26: =$I$17*M26/M$18 -> 349.79592 | E26: =$J$17*N26/N$18 -> 382.83423 | F26: =$J$17*O26/O$18 -> 387.74236 | G26: =$J$17*P26/P$18 -> 392.61387 | K26: 1067.1764 | L26: 1067.1764 | M26: 1067.1764 | N26: 1167.9715 | O26: 1182.9455 | P26: 1197.8078
A27: 2029 | B27: =$I$17*K27/K$18 -> 346.90232 | C27: =$I$17*L27/L$18 -> 346.90232 | D27: =$I$17*M27/M$18 -> 346.90232 | E27: =$J$17*N27/N$18 -> 378.51215 | F27: =$J$17*O27/O$18 -> 384.18946 | G27: =$J$17*P27/P$18 -> 389.9034 | K27: 1058.3485 | L27: 1058.3485 | M27: 1058.3485 | N27: 1154.7855 | O27: 1172.1061 | P27: 1189.5386
A28: 2030 | B28: =$I$17*K28/K$18 -> 344.00872 | C28: =$I$17*L28/L$18 -> 344.00872 | D28: =$I$17*M28/M$18 -> 344.00872 | E28: =$J$17*N28/N$18 -> 374.15343 | F28: =$J$17*O28/O$18 -> 380.67319 | G28: =$J$17*P28/P$18 -> 387.19294 | K28: 1049.5205 | L28: 1049.5205 | M28: 1049.5205 | N28: 1141.4877 | O28: 1161.3785 | P28: 1181.2693
A29: 2031 | B29: =$I$17*K29/K$18 -> 341.11512 | C29: =$I$17*L29/L$18 -> 341.11512 | D29: =$I$17*M29/M$18 -> 341.11512 | E29: =$J$17*N29/N$18 -> 369.79472 | F29: =$J$17*O29/O$18 -> 377.12029 | G29: =$J$17*P29/P$18 -> 384.48248 | K29: 1040.6926 | L29: 1040.6926 | M29: 1040.6926 | N29: 1128.1899 | O29: 1150.5391 | P29: 1173.0001
... A48: 2050 | B48: =$I$17*K48/K$18 -> 285.95358 | C48: =$I$17*L48/L$18 -> 285.95358 | D48: =$I$17*M48/M$18 -> 285.95358 | E48: =$J$17*N48/N$18 -> 303.57158 | F48: =$J$17*O48/O$18 -> 318.22271 | G48: =$J$17*P48/P$18 -> 332.87385 | K48: 872.40277 | L48: 872.40277 | M48: 872.40277 | N48: 926.1527 | O48: 970.85119 | P48: 1015.5497

Sheet hydro
A1: China | B1: =14561/6.5 -> 2240.1538

Sheet Electrolyzer
A1: Year | B1: Advance | C1: Moderate | D1: Conservative | H1: efficiency
A2: 2020 | B2: =1.1*875*L2 -> 990.4125 | C2: =$L$3*1100*$L$2 -> 1245.09 | D2: =L2*L3*1450 -> 1641.255 | G2: 2020 | H2: 0.577 | K2: inflation | L2: 1.029 | O2: https://www.in2013dollars.com/europe/inflation/2015?endYear=2021&amount=100
A3: 2021 | B3: 749.45556 | C3: 770.23333 | D3: 791.13333 | G3: 2025 | H3: 0.587 | K3: Euro to US | L3: 1.1
A4: 2022 | B4: 742.13333 | C4: 764.8 | D4: 787.6 | G4: 2030 | H4: 0.622
A5: 2023 | B5: 734.81111 | C5: 759.36667 | D5: 784.06667 | G5: 2035
A6: 2024 | B6: 727.48889 | C6: 753.93333 | D6: 780.53333 | G6: 2040 | H6: 0.653
A7: 2025 | B7: 720.16667 | C7: =L2*L3*800 -> 905.52 | D7: 777 | G7: 2045
A8: 2026 | B8: 712.84444 | C8: 743.06667 | D8: 773.46667 | G8: 2050 | H8: 0.699
A9: 2027 | B9: 705.52222 | C9: 737.63333 | D9: 769.93333
A10: 2028 | B10: 698.2 | C10: 732.2 | D10: 766.4
A11: 2029 | B11: 690.87778 | C11: 726.76667 | D11: 762.86667
A12: 2030 | B12: 683.55556 | C12: =500*L2*L3 -> 565.95 | D12: 759.33333
A13: 2031 | B13: 676.23333 | C13: 715.9 | D13: 755.8
A14: 2032 | B14: 668.91111 | C14: 710.46667 | D14: 752.26667
A15: 2033 | B15: 661.58889 | C15: 705.03333 | D15: 748.73333
A16: 2034 | B16: 654.26667 | C16: 699.6 | D16: 745.2
A17: 2035 | B17: 646.94444 | C17: 694.16667 | D17: 741.66667
A18: 2036 | B18: 639.62222 | C18: 688.73333 | D18: 738.13333
A19: 2037 | B19: 632.3 | C19: 683.3 | D19: 734.6
A20: 2038 | B20: 624.97778 | C20: 677.86667 | D20: 731.06667
A21: 2039 | B21: 617.65556 | C21: 672.43333 | D21: 727.53333
A22: 2040 | B22: 610.33333 | C22: =400*L2*L3 -> 452.76 | D22: 724
A23: 2041 | B23: 603.01111 | C23: 661.56667 | D23: 720.46667
A24: 2042 | B24: 595.68889 | C24: 656.13333 | D24: 716.93333
A25: 2043 | B25: 588.36667 | C25: 650.7 | D25: 713.4
A26: 2044 | B26: 581.04444 | C26: 645.26667 | D26: 709.86667
A27: 2045 | B27: 573.72222 | C27: 639.83333 | D27: 706.33333
A28: 2046 | B28: 566.4 | C28: 634.4 | D28: 702.8
A29: 2047 | B29: 559.07778 | C29: 628.96667 | D29: 699.26667
A30: 2048 | B30: 551.75556 | C30: 623.53333 | D30: 695.73333
A31: 2049 | B31: 544.43333 | C31: 618.1 | D31: 692.2
A32: 2050 | B32: =250*L2*L3 -> 282.975 | C32: =275*L2*L3 -> 311.2725 | D32: =1.1*350 -> 385

Sheet SMR
A1: 1997 data | B1: MJ/kg | C1: MWh/kg | D1: kg/MWh | I1: CT | J1: Coal-new-AvgCF-Advanced | K1: Coal-new-AvgCF-Moderate | L1: Coal-new-AvgCF-Conservative | T1: SMR
B2: 120 | C2: =120/3600 -> 0.033333333 | D2: =1/C2 -> 30 | H2: 2020 | I2: 367.23077 | J2: 622.46154 | K2: 622.46154 | L2: 622.46154 | N2: =I2/I$2 -> 1 | O2: =J2/J$2 -> 1 | P2: =K2/K$2 -> 1 | Q2: =L2/L$2 -> 1 | S2: 2020 | T2: =$B$12*N2 -> 546556.72 | U2: =$C$12*O2 -> 3272268.8 | V2: =$C$12*P2 -> 3272268.8 | W2: =$C$12*Q2 -> 3272268.8
H3: 2025 | I3: 358.51334 | J3: 607.42676 | K3: 612.28583 | L3: 617.14489 | N3: =I3/I$2 -> 0.97626172 | O3: =J3/J$2 -> 0.97584626 | P3: =K3/K$2 -> 0.98365247 | Q3: =L3/L$2 -> 0.99145868 | S3: 2025 | T3: =$B$12*N3 -> 533582.41 | U3: =$C$12*O3 -> 3193231.3 | V3: =$C$12*P3 -> 3218775.3 | W3: =$C$12*Q3 -> 3244319.3
A4: Inflation | B4: 1.92 | H4: 2030 | I4: 344.00872 | J4: 582.39059 | K4: 595.35536 | L4: 608.29834 | N4: =I4/I$2 -> 0.93676441 | O4: =J4/J$2 -> 0.93562502 | P4: =K4/K$2 -> 0.95645325 | Q4: =L4/L$2 -> 0.97724647 | S4: 2030 | T4: =$B$12*N4 -> 511994.89 | U4: =$C$12*O4 -> 3061616.6 | V4: =$C$12*P4 -> 3129772.1 | W4: =$C$12*Q4 -> 3197813.1
B5: SMR | C5: Gasification | H5: 2035 | I5: 329.50409 | J5: 557.35442 | K5: 578.40311 | L5: 599.45179 | N5: =I5/I$2 -> 0.89726711 | O5: =J5/J$2 -> 0.89540379 | P5: =K5/K$2 -> 0.92921903 | Q5: =L5/L$2 -> 0.96303427 | S5: 2035 | T5: =$B$12*N5 -> 490407.37 | U5: =$C$12*O5 -> 2930001.9 | V5: =$C$12*P5 -> 3040654.4 | W5: =$C$12*Q5 -> 3151307
A6: tonne/year | B6: 125000 | C6: 81000 | H6: 2040 | I6: 314.96284 | J6: 532.29646 | K6: 550.66503 | L6: 569.03361 | N6: =I6/I$2 -> 0.85767006 | O6: =J6/J$2 -> 0.85514755 | P6: =K6/K$2 -> 0.88465712 | Q6: =L6/L$2 -> 0.9141667 | S6: 2040 | T6: =$B$12*N6 -> 468765.34 | U6: =$C$12*O6 -> 2798272.6 | V6: =$C$12*P6 -> 2894835.9 | W6: =$C$12*Q6 -> 2991399.2
A7: MW | B7: =B6*C2/8760*1000 -> 475.64688 | C7: =C6*C2/8760*1000 -> 308.21918 | H7: 2045 | I7: 300.45821 | J7: 507.26029 | K7: 522.94875 | L7: 538.61542 | N7: =I7/I$2 -> 0.81817275 | O7: =J7/J$2 -> 0.81492631 | P7: =K7/K$2 -> 0.84013022 | Q7: =L7/L$2 -> 0.86529912 | S7: 2045 | T7: =$B$12*N7 -> 447177.82 | U7: =$C$12*O7 -> 2666658 | V7: =$C$12*P7 -> 2749131.9 | W7: =$C$12*Q7 -> 2831491.3
A8: Total capital cost | B8: =135.4*10^6*B4 -> 259968000 | C8: =525.3*10^6*$B$4 -> 1.008576e+09 | H8: 2050 | I8: 285.95358 | J8: 482.22412 | K8: 495.21068 | L8: 508.19724 | N8: =I8/I$2 -> 0.77867544 | O8: =J8/J$2 -> 0.77470508 | P8: =K8/K$2 -> 0.79556831 | Q8: =L8/L$2 -> 0.81643155 | S8: 2050 | T8: =$B$12*N8 -> 425590.3 | U8: =$C$12*O8 -> 2535043.3 | V8: =$C$12*P8 -> 2603313.4 | W8: =$C$12*Q8 -> 2671583.5
A9: OM | B9: =5.8*10^6*B4 -> 11136000 | C9: =27000000*$B$4 -> 51840000
A10: Var | B10: =2.1*B4*10^6 -> 4032000 | C10: =2.3*B4*10^6 -> 4416000
A12: Capita cost per MW | B12: =B8/B7 -> 546556.72 | C12: =C8/C7 -> 3272268.8 | E12: =C8/C$6/1000/B4 -> 6.4851852
A13: OM per MW | B13: =B9/B7 -> 23412.326 | C13: =C9/C7 -> 168192 | E13: =C9/C$6/1000/B4 -> 0.33333333
A14: Variable cost per mwh | B14: =B10/B7/8760 -> 0.96768 | C14: =C10/C7/8760 -> 1.6355556 | E14: =C10/C$6/1000/B4 -> 0.028395062
A16: Efficiency | B16: 0.718 | C16: 0.641
A17: Heat rate(mmbtu per MWh) | B17: =3600/1055/B16 -> 4.752538 | C17: =3600/1055/C16 -> 5.3234357

Sheet Fuel cell
A1: Year | B1: Advance | C1: Moderate | D1: Conservative | G1: efficiency
A2: 2020 | B2: =1170*J2*J3 -> 1324.323 | C2: =1380*J2*J3 -> 1562.022 | D2: =1700*J2*J3 -> 1924.23 | G2: 0.5 | I2: inflation | J2: 1.029
A3: 2025 | B3: =(B$8-B$2)/30*5+B2 -> 1203.587 | C3: =(C2+C4)/2 -> 1443.1725 | D3: =(D$8-D$2)/30*5+D2 -> 1784.629 | I3: Euro to US | J3: 1.1
A4: 2030 | B4: =(B$8-B$2)/30*5+B3 -> 1082.851 | C4: =J2*J3*1170 -> 1324.323 | D4: =(D$8-D$2)/30*5+D3 -> 1645.028
A5: 2035 | B5: =(B$8-B$2)/30*5+B4 -> 962.115 | C5: =(C$8-C$4)/20*5+C4 -> 1233.771 | D5: =(D$8-D$2)/30*5+D4 -> 1505.427
A6: 2040 | B6: =(B$8-B$2)/30*5+B5 -> 841.379 | C6: =(C$8-C$4)/20*5+C5 -> 1143.219 | D6: =(D$8-D$2)/30*5+D5 -> 1365.826
A7: 2045 | B7: =(B$8-B$2)/30*5+B6 -> 720.643 | C7: =(C$8-C$4)/20*5+C6 -> 1052.667 | D7: =(D$8-D$2)/30*5+D6 -> 1226.225
A8: 2050 | B8: =J2*J3*530 -> 599.907 | C8: =J2*J3*850 -> 962.115 | D8: =J2*J3*960 -> 1086.624
A13: OM
A14: Year | B14: Advance | C14: Moderate | D14: Conservative
A15: 2020 | C15: =69119.22667*J2*J3 -> 78236.053
A16: 2025 | C16: =(C15+C17)/2 -> 72217.895
A17: 2030 | C17: =J2*J3*58485.49949 -> 66199.737
A18: 2035 | C18: =(C$21-C$17)/20*5+C17 -> 61686.118
A19: 2040 | C19: =(C$21-C$17)/20*5+C18 -> 57172.5
A20: 2045 | C20: =(C$21-C$17)/20*5+C19 -> 52658.882
A21: 2050 | C21: =J2*J3*42534.90872 -> 48145.263

Sheet H2 turbine
A1: Year | B1: Advance | C1: Moderate | D1: Conservative
A2: 2010 | B2: 318 | C2: 318 | D2: 318
A3: 2011 | B3: 317.67778 | C3: 317.67778 | D3: 317.67778
A4: 2012 | B4: 317.35556 | C4: 317.35556 | D4: 317.35556
A5: 2013 | B5: 317.03333 | C5: 317.03333 | D5: 317.03333
A6: 2014 | B6: 316.71111 | C6: 316.71111 | D6: 316.71111
A7: 2015 | B7: 316.38889 | C7: 316.38889 | D7: 316.38889
A8: 2016 | B8: 316.06667 | C8: 316.06667 | D8: 316.06667
A9: 2017 | B9: 315.74444 | C9: 315.74444 | D9: 315.74444
A10: 2018 | B10: 315.42222 | C10: 315.42222 | D10: 315.42222
A11: 2019 | B11: 315.1 | C11: 315.1 | D11: 315.1
A12: 2020 | B12: 314.77778 | C12: 314.77778 | D12: 314.77778
A13: 2021 | B13: 314.45556 | C13: 314.45556 | D13: 314.45556
... A92: 2100 | B92: 289 | C92: 289 | D92: 289

Sheet hydrogen storage
B1: MJ/kg | C1: MWh/kg | D1: MWh | E1: tonne | G1: cost (million $ for 5000 tonne H2) | M1: inflacttion | N1: exchange rate | U1: Compressed | V1: Liquid | W1: Salt cavern
B2: 120 | C2: =120/3600 -> 0.033333333 | D2: =C2*E2*1000 -> 166666.67 | E2: 5000 | G2: Compressed | H2: Liguid | I2: Salt cavern | L2: factor | M2: 1.029 | N2: 1.1 | O2: =M2*N2 -> 1.1319 | T2: 2020 | U2: 23058 | V2: 55740 | W2: 2364
G3: 3843 | H3: 9290 | I3: 394 | T3: 2025 | U3: 20252.61 | V3: 48958.3 | W3: 2076.38
G4: =G3/E2*1000 -> 768.6 | H4: =H3/E2*1000 -> 1858 | I4: =I3/E2*1000 -> 78.8 | T4: 2030 | U4: 17447.22 | V4: 42176.6 | W4: 1788.76
T5: 2035 | U5: 14641.83 | V5: 35394.9 | W5: 1501.14
A6: $/MWh | T6: 2040 | U6: 11836.44 | V6: 28613.2 | W6: 1213.52
T7: 2045 | U7: 9031.05 | V7: 21831.5 | W7: 925.9
B8: Compressed | C8: Liquid | D8: Salt cavern | E8: Advance | F8: Conservative | O8: charging efficiency | T8: 2050 | U8: 6225.66 | V8: 15049.8 | W8: 638.28
A9: 2020 | B9: =0.061*10^6*$O2 -> 69045.9 | C9: 55740 | D9: =0.00319*10^6*$O2 -> 3610.761 | J9: =0.061*10^6*$O2 -> 69045.9 | L9: =0.00319*10^6*$O2 -> 3610.761 | O9: 0.88 | P9: 0.99
A10: 2025 | B10: =(B9+B11)/2 -> 61688.55 | C10: 48958.3 | D10: =(D9+D11)/2 -> 3010.854
A11: 2030 | B11: =0.048*10^6*$O2 -> 54331.2 | C11: 42176.6 | D11: =0.00213*10^6*$O2 -> 2410.947 | J11: =0.048*10^6*$O2 -> 54331.2 | L11: =0.00213*10^6*$O2 -> 2410.947 | O11: 0.89 | P11: 0.99
A12: 2035 | B12: =(B11+B13)/2 -> 43578.15 | C12: 35394.9 | D12: =(D11+D13)/2 -> 2110.9935 | G12: reduction rate | H12: 0.73
A13: 2040 | B13: =0.029*10^6*$O2 -> 32825.1 | C13: 28613.2 | D13: =0.0016*10^6*$O2 -> 1811.04 | J13: =0.029*10^6*$O2 -> 32825.1 | L13: =0.0016*10^6*$O2 -> 1811.04 | O13: 0.9 | P13: 0.99
A14: 2045 | B14: =(B13+B15)/2 -> 28863.45 | C14: 21831.5 | D14: =(D13+D15)/2 -> 1629.936
A15: 2050 | B15: =0.022*10^6*$O2 -> 24901.8 | C15: 15049.8 | D15: =0.00128*10^6*$O2 -> 1448.832 | E15: =0.00106*10^6*$O2 -> 1199.814 | F15: =0.00191*10^6*$O2 -> 2161.929 | J15: =0.022*10^6*$O2 -> 24901.8 | L15: =0.00128*10^6*$O2 -> 1448.832 | O15: 0.9 | P15: 0.99
B16: =0.022*10^6*$O2 -> 24901.8
B17: =0.037*10^6*$O2 -> 41880.3
A18: $/MW
A19: om | B19: Compressed | C19: Liquid | D19: Salt cavern
A20: 2020 | B20: =O2*638.04 -> 722.19748 | D20: 0
A21: 2025 | B21: =(B22+B20)/2 -> 662.01435 | D21: 0
A22: 2030 | B22: =O2*531.7 -> 601.83123 | D22: 0
A23: 2035 | B23: =(B24+B22)/2 -> 601.83123 | D23: 0
A24: 2040 | B24: =O2*531.7 -> 601.83123 | D24: 0
A25: 2045 | B25: =(B26+B24)/2 -> 541.64811 | D25: 0
A26: 2050 | B26: =O2*425.36 -> 481.46498 | D26: 0
B27: =O2*319.02 -> 361.09874
B28: =O2*478.53 -> 541.64811

Sheet ccs
A1: coal | B1: CCS institute | F1: IGCC | H1: NGCC | J1: Fertilizer | O1: IPCC | P1: NGCC | Q1: PC | U1: Inflaction | V1: 1.3
B2: super critical | C2: super critical 2
A3: capacity factor | B3: 0.85 | C3: 0.85 | F3: 0.85 | H3: 0.85 | P3: 0.8 | Q3: 0.8 | R3: 0.8
A4: capital cost/mw | B4: =(3754-2158)*10^3 -> 1596000 | C4: =(3781-2099)*10^3 -> 1682000 | F4: =(4186-2896)*10^3 -> 1290000 | H4: =(1531-686)*10^3 -> 845000 | J4: =15*10^6 -> 15000000 | O4: capita cost per MW | P4: =(998-568)*1000 -> 430000 | Q4: =(2096-1286)*1000 -> 810000 | R4: =(1825-1326)*1000 -> 499000
A5: co2 capacity/mw | B5: =480*8760*B3/642 -> 5567.1028 | C5: =551*8760*C3/661.1 -> 6205.9386 | F5: =436*8760*F3/673 -> 4823.8574 | H5: =202*8760*H3/601 -> 2502.6489 | J5: =194000*0.88 -> 170720 | O5: co2 capture per MWh | P5: =(0.736-0.052) -> 0.684 | Q5: =0.762-0.112 -> 0.65 | R5: =0.773-0.108 -> 0.665
A6: capital cost per tonne co2 per year | B6: =B4/B5*V1 -> 372.68936 | C6: =C4/C5*V1 -> 352.33994 | F6: =F4/F5 -> 267.42084 | H6: =H4/H5 -> 337.64225 | J6: =J4/J5 -> 87.863168 | O6: capital cost per tonn per year | P6: =P4/P5/8760/P3 -> 89.705333 | Q6: =Q4/Q5/8760/Q3 -> 177.81876 | R6: =R4/R5/8760/R3 -> 107.07419
A8: fixed | B8: =(33.1/642-22.6/580)*10^6/B5*V1 -> 2.9404432 | C8: =(39.3/661.1-26.6/580.2)*10^6/C5*V1 -> 2.8489087 | F8: =(52/673-50.4/737)*10^6/F5 -> 1.8409805 | H8: =(14.8/601-9.7/641)*10^6/H5 -> 3.7931883 | J8: =0.5*10^6/J4 -> 0.033333333 | O8: var
A9: var | B9: =(17.84-9.64)/(0.774-0.097)*V1 -> 15.745938 | C9: =(8.95-4.64)/(0.8-0.112)*V1 -> 8.1438953 | F9: =(17.37-11.97)/(0.724-0.099) -> 8.64 | H9: =(2.3-1.18)/(0.356-0.04) -> 3.5443038 | J9: =0.5*10^6/J4 -> 0.033333333 | O9: fixed
A10: discount | B10: =0.06*0.4+0.12*0.6 -> 0.096 | C10: =0.06*0.4+0.12*0.6 -> 0.096 | F10: =0.06*0.4+0.12*0.6 -> 0.096 | H10: =0.06*0.4+0.12*0.6 -> 0.096 | J10: =0.06*0.4+0.12*0.6 -> 0.096
B11: =B10*(1+B10)^30/((1+B10)^30-1) -> 0.10255609 | C11: =C10*(1+C10)^30/((1+C10)^30-1) -> 0.10255609 | F11: =F10*(1+F10)^30/((1+F10)^30-1) -> 0.10255609 | H11: =H10*(1+H10)^30/((1+H10)^30-1) -> 0.10255609 | J11: =J10*(1+J10)^30/((1+J10)^30-1) -> 0.10255609
B13: =B6*B11+B9+B8 -> 56.907945 | C13: =C6*C11+C8+C9 -> 47.12741 | F13: =F6*F11+F9+F8 -> 37.906616 | H13: =H6*H11+H9+H8 -> 41.96476 | J13: =J6*J11+J9+J8 -> 9.0775695
A15: electricity per tonne | L15: IPCC
M16: ngcc | N16: h2
A17: CO2 tonne/mwh | B17: =61/480 -> 0.12708333 | C17: =79.9/551 -> 0.14500907 | F17: =(177-108*497/629)/436 -> 0.21023979 | H17: =(42-11*559/630)/202 -> 0.15960239 | J17: =N19 -> 0.61087355 | L17: mwh | M17: 0.16 | N17: 0.08
L18: ton | M18: =0.672*1.16-0.052 -> 0.72752 | N18: =0.137*1.08-0.017 -> 0.13096
A19: Cost projection from Energy technology | B19: capital | C19: OM | M19: =M17/M18 -> 0.21992523 | N19: =N17/N18 -> 0.61087355
A20: 2020 | B20: 1 | C20: =1 -> 1
A21: 2025 | B21: =3/4.3 -> 0.69767442 | C21: =0.09/0.13 -> 0.69230769
A22: 2030 | B22: =2.5/4.3 -> 0.58139535 | C22: =0.08/0.13 -> 0.61538462
A23: 2035 | B23: =(B22+B24)/2 -> 0.53488372 | C23: =(C22+C24)/2 -> 0.53846154
A24: 2040 | B24: =2.1/4.3 -> 0.48837209 | C24: =0.06/0.13 -> 0.46153846
A25: 2045 | B25: =(B24+B26)/2 -> 0.47674419 | C25: =(C24+C26)/2 -> 0.42307692
A26: 2050 | B26: =2/4.3 -> 0.46511628 | C26: =0.05/0.13 -> 0.38461538

Sheet DAC
B1: MWh/ton | H1: inflacttion | I1: exchange rate
A2: 2020 | B2: =1.75+0.25 -> 2 | C2: =0.16+0.11 -> 0.27 | D2: =B2+C2 -> 2.27 | G2: factor | H2: 1.029 | I2: 1.1 | J2: =H2*I2 -> 1.1319
A3: 2025 | B3: =1.75+0.25 -> 2 | C3: =0.16+0.11 -> 0.27 | D3: =B3+C3 -> 2.27
A4: 2030 | B4: =1.5+1 -> 2.5 | C4: =0.16+0.11 -> 0.27 | D4: =B4+C4 -> 2.77
A5: 2040 | B5: =1.286+0.203 -> 1.489 | C5: =0.16+0.11 -> 0.27 | D5: =B5+C5 -> 1.759
A6: 2050 | B6: =1.012+0.182 -> 1.194 | C6: =0.16+0.11 -> 0.27 | D6: =B6+C6 -> 1.464
G7: ton
F8: 1 MWh | G8: =1/(B2+C2) -> 0.44052863
A10: capital cost | B10: dollar/t CO2/hour | C10: OM | F10: 1 MW | G10: capital cost for 1 MW | H10: OM cost
A11: 2020 | B11: =6.5*10^6*J2 -> 7357350 | C11: =0.34*10^6*J2 -> 384846 | G11: =$G$8*B11 -> 3241123.3 | H11: =$G$8*C11 -> 169535.68
A12: 2025 | B12: =4.8*10^6*J2 -> 5433120 | C12: =0.34*10^6*J2 -> 384846 | G12: =$G$8*B12 -> 2393444.9 | H12: =$G$8*C12 -> 169535.68
A13: 2030 | B13: =3*10^6*J2 -> 3395700 | C13: =0.34*10^6*J2 -> 384846 | G13: =$G$8*B13 -> 1495903.1 | H13: =$G$8*C13 -> 169535.68
A14: 2035 | B14: =(B13+B15)/2 -> 2886345 | C14: =(C13+C15)/2 -> 384846 | G14: =$G$8*B14 -> 1271517.6 | H14: =$G$8*C14 -> 169535.68
A15: 2040 | B15: =2.1*10^6*J2 -> 2376990 | C15: =0.34*10^6*J2 -> 384846 | G15: =$G$8*B15 -> 1047132.2 | H15: =$G$8*C15 -> 169535.68
A16: 2045 | B16: =(B15+B17)/2 -> 2207205 | C16: =(C15+C17)/2 -> 384846 | G16: =$G$8*B16 -> 972337 | H16: =$G$8*C16 -> 169535.68
A17: 2050 | B17: =1.8*10^6*J2 -> 2037420 | C17: =0.34*10^6*J2 -> 384846 | G17: =$G$8*B17 -> 897541.85 | H17: =$G$8*C17 -> 169535.68
A19: 2020 | B19: =B11/8760 -> 839.88014 | C19: =C11/8760 -> 43.932192
A20: 2025 | B20: =B12/8760 -> 620.21918 | C20: =C12/8760 -> 43.932192
A21: 2030 | B21: =B13/8760 -> 387.63699 | C21: =C13/8760 -> 43.932192
A22: 2035 | B22: =B14/8760 -> 329.49144 | C22: =C14/8760 -> 43.932192
A23: 2040 | B23: =B15/8760 -> 271.34589 | C23: =C15/8760 -> 43.932192
A24: 2045 | B24: =B16/8760 -> 251.96404 | C24: =C16/8760 -> 43.932192
A25: 2050 | B25: =B17/8760 -> 232.58219 | C25: =C17/8760 -> 43.932192
